Workbook
Name Slicer_City: #N/A
Name Slicer_Coupon_Code: #N/A
Name Slicer_Gender: #N/A
Name Slicer_Product_Category: #N/A
Name Slicer_PRODUCTS: #N/A
Name Slicer_Referral_Source: #N/A

Sheet Raw Data
A1: OrderID | B1: Date | C1: CustomerID | D1: Product | E1: Quantity | F1: UnitPrice | G1: ShippingAddress | H1: PaymentMethod | I1: OrderStatus | J1: TrackingNumber | K1: ItemsInCart | L1: CouponCode | M1: ReferralSource | N1: TotalPrice
A2: ORD200000 | B2: 44930 | C2: C72649 | D2: Monitor | E2: 5 | F2: 570.62 | G2: 928 Main St | H2: Debit Card | I2: Shipped | J2: TRK37947903 | K2: 7 | L2: SAVE10 | M2: Instagram | N2: 2853.1
A3: ORD200001 | B3: 45527 | C3: C75739 | D3: Phone | E3: 2 | F3: 151.35 | G3: 823 Main St | H3: Online | I3: Shipped | J3: TRK91186779 | K3: 3 | L3: SAVE10 | M3: Referral | N3: 302.7
A4: ORD200002 | B4: 45349 | C4: C81728 | D4: Tablet | E4: 5 | F4: 550.68 | G4: 512 Main St | H4: Credit Card | I4: Cancelled | J4: TRK42903982 | K4: 8 | L4: FREESHIP | M4: Email | N4: 2753.4
A5: ORD200003 | B5: 45214 | C5: C33540 | D5: Chair | E5: 1 | F5: 273.19 | G5: 275 Main St | H5: Debit Card | I5: Returned | J5: TRK62788070 | K5: 5 | L5: SAVE10 | M5: Facebook | N5: 273.19
A6: ORD200004 | B6: 45785 | C6: C81840 | D6: Printer | E6: 4 | F6: 626.01 | G6: 668 Main St | H6: Online | I6: Delivered | J6: TRK29241424 | K6: 8 | L6: SAVE10 | M6: Email | N6: 2504.04
A7: ORD200005 | B7: 45222 | C7: C37249 | D7: Phone | E7: 2 | F7: 245.86 | G7: 934 Main St | H7: Credit Card | I7: Shipped | J7: TRK72976927 | K7: 4 | L7: SAVE10 | M7: Instagram | N7: 491.72
A8: ORD200006 | B8: 45825 | C8: C83492 | D8: Laptop | E8: 1 | F8: 664.42 | G8: 986 Main St | H8: Gift Card | I8: Returned | J8: TRK96417362 | K8: 6 | L8: SAVE10 | M8: Facebook | N8: 664.42
A9: ORD200007 | B9: 45058 | C9: C41460 | D9: Monitor | E9: 5 | F9: 149.55 | G9: 706 Main St | H9: Cash | I9: Shipped | J9: TRK78809193 | K9: 9 | L9: FREESHIP | M9: Facebook | N9: 747.75
A10: ORD200008 | B10: 45749 | C10: C26817 | D10: Phone | E10: 2 | F10: 134.28 | G10: 904 Main St | H10: Gift Card | I10: Cancelled | J10: TRK61042692 | K10: 2 | M10: Email | N10: 268.56
A11: ORD200009 | B11: 45251 | C11: C31946 | D11: Desk | E11: 4 | F11: 509.38 | G11: 102 Main St | H11: Credit Card | I11: Shipped | J11: TRK33478363 | K11: 6 | L11: SAVE10 | M11: Google | N11: 2037.52
A12: ORD200010 | B12: 45289 | C12: C43443 | D12: Tablet | E12: 5 | F12: 625.97 | G12: 333 Main St | H12: Credit Card | I12: Returned | J12: TRK98859248 | K12: 9 | L12: WINTER15 | M12: Instagram | N12: 3129.85
A13: ORD200011 | B13: 45339 | C13: C93861 | D13: Monitor | E13: 3 | F13: 49.14 | G13: 831 Main St | H13: Online | I13: Returned | J13: TRK48234646 | K13: 7 | L13: SAVE10 | M13: Email | N13: 147.42
A14: ORD200012 | B14: 45580 | C14: C38785 | D14: Monitor | E14: 2 | F14: 180.5 | G14: 179 Main St | H14: Debit Card | I14: Pending | J14: TRK20419991 | K14: 6 | L14: FREESHIP | M14: Referral | N14: 361
A15: ORD200013 | B15: 45168 | C15: C88348 | D15: Laptop | E15: 3 | F15: 201.49 | G15: 903 Main St | H15: Credit Card | I15: Returned | J15: TRK81913874 | K15: 4 | L15: FREESHIP | M15: Facebook | N15: 604.47
A16: ORD200014 | B16: 45012 | C16: C98474 | D16: Tablet | E16: 2 | F16: 393.33 | G16: 980 Main St | H16: Debit Card | I16: Pending | J16: TRK79186539 | K16: 3 | L16: SAVE10 | M16: Instagram | N16: 786.66
A17: ORD200015 | B17: 45124 | C17: C39416 | D17: Printer | E17: 1 | F17: 473.96 | G17: 942 Main St | H17: Cash | I17: Delivered | J17: TRK54930938 | K17: 3 | M17: Google | N17: 473.96
A18: ORD200016 | B18: 44950 | C18: C28976 | D18: Printer | E18: 2 | F18: 533.81 | G18: 914 Main St | H18: Credit Card | I18: Pending | J18: TRK13194259 | K18: 3 | L18: FREESHIP | M18: Email | N18: 1067.62
A19: ORD200017 | B19: 45353 | C19: C60672 | D19: Tablet | E19: 1 | F19: 423.4 | G19: 382 Main St | H19: Debit Card | I19: Shipped | J19: TRK11972116 | K19: 3 | M19: Referral | N19: 423.4
A20: ORD200018 | B20: 45742 | C20: C84329 | D20: Desk | E20: 1 | F20: 431.44 | G20: 891 Main St | H20: Gift Card | I20: Pending | J20: TRK65191045 | K20: 3 | L20: SAVE10 | M20: Facebook | N20: 431.44
A21: ORD200019 | B21: 44949 | C21: C14552 | D21: Monitor | E21: 5 | F21: 224 | G21: 273 Main St | H21: Cash | I21: Returned | J21: TRK59101365 | K21: 9 | L21: SAVE10 | M21: Google | N21: 1120
A22: ORD200020 | B22: 45054 | C22: C54829 | D22: Chair | E22: 5 | F22: 62.51 | G22: 587 Main St | H22: Cash | I22: Pending | J22: TRK16718651 | K22: 9 | L22: WINTER15 | M22: Instagram | N22: 312.55
A23: ORD200021 | B23: 45613 | C23: C99023 | D23: Monitor | E23: 4 | F23: 342.95 | G23: 569 Main St | H23: Cash | I23: Delivered | J23: TRK52646983 | K23: 6 | M23: Google | N23: 1371.8
A24: ORD200022 | B24: 44955 | C24: C34416 | D24: Monitor | E24: 2 | F24: 49.62 | G24: 633 Main St | H24: Online | I24: Pending | J24: TRK75937350 | K24: 2 | L24: SAVE10 | M24: Google | N24: 99.24
A25: ORD200023 | B25: 45756 | C25: C42372 | D25: Phone | E25: 4 | F25: 273.25 | G25: 755 Main St | H25: Debit Card | I25: Cancelled | J25: TRK36168083 | K25: 5 | L25: FREESHIP | M25: Referral | N25: 1093
A26: ORD200024 | B26: 45595 | C26: C17470 | D26: Laptop | E26: 2 | F26: 230.95 | G26: 956 Main St | H26: Online | I26: Delivered | J26: TRK28775057 | K26: 3 | L26: WINTER15 | M26: Referral | N26: 461.9
A27: ORD200025 | B27: 45497 | C27: C42577 | D27: Monitor | E27: 1 | F27: 399.98 | G27: 709 Main St | H27: Debit Card | I27: Delivered | J27: TRK69423327 | K27: 3 | L27: WINTER15 | M27: Email | N27: 399.98
A28: ORD200026 | B28: 45357 | C28: C21944 | D28: Laptop | E28: 5 | F28: 59.55 | G28: 296 Main St | H28: Online | I28: Delivered | J28: TRK80276812 | K28: 6 | M28: Referral | N28: 297.75
A29: ORD200027 | B29: 45344 | C29: C97593 | D29: Printer | E29: 1 | F29: 472.74 | G29: 881 Main St | H29: Online | I29: Shipped | J29: TRK89117573 | K29: 6 | L29: WINTER15 | M29: Google | N29: 472.74
A30: ORD200028 | B30: 45251 | C30: C59823 | D30: Phone | E30: 4 | F30: 160.07 | G30: 568 Main St | H30: Online | I30: Pending | J30: TRK65895539 | K30: 5 | M30: Email | N30: 640.28
A31: ORD200029 | B31: 45555 | C31: C33260 | D31: Desk | E31: 3 | F31: 423.53 | G31: 930 Main St | H31: Credit Card | I31: Delivered | J31: TRK59744090 | K31: 6 | L31: SAVE10 | M31: Referral | N31: 1270.59
A32: ORD200030 | B32: 45738 | C32: C44267 | D32: Monitor | E32: 2 | F32: 426.7 | G32: 895 Main St | H32: Online | I32: Pending | J32: TRK54751444 | K32: 5 | L32: SAVE10 | M32: Referral | N32: 853.4
A33: ORD200031 | B33: 45107 | C33: C26445 | D33: Chair | E33: 3 | F33: 500.08 | G33: 996 Main St | H33: Debit Card | I33: Returned | J33: TRK31229981 | K33: 6 | M33: Facebook | N33: 1500.24
A34: ORD200032 | B34: 45047 | C34: C12388 | D34: Tablet | E34: 5 | F34: 536.72 | G34: 830 Main St | H34: Cash | I34: Delivered | J34: TRK99261395 | K34: 10 | M34: Email | N34: 2683.6
A35: ORD200033 | B35: 45082 | C35: C52184 | D35: Chair | E35: 1 | F35: 162.77 | G35: 912 Main St | H35: Online | I35: Cancelled | J35: TRK73312471 | K35: 4 | L35: WINTER15 | M35: Facebook | N35: 162.77
A36: ORD200034 | B36: 44933 | C36: C67195 | D36: Chair | E36: 4 | F36: 576.52 | G36: 926 Main St | H36: Credit Card | I36: Pending | J36: TRK55467915 | K36: 5 | L36: WINTER15 | M36: Facebook | N36: 2306.08
A37: ORD200035 | B37: 45633 | C37: C50304 | D37: Monitor | E37: 2 | F37: 465.15 | G37: 128 Main St | H37: Online | I37: Shipped | J37: TRK46850888 | K37: 2 | L37: SAVE10 | M37: Facebook | N37: 930.3
A38: ORD200036 | B38: 45785 | C38: C59337 | D38: Laptop | E38: 2 | F38: 534.43 | G38: 465 Main St | H38: Debit Card | I38: Pending | J38: TRK50961250 | K38: 5 | M38: Facebook | N38: 1068.86
A39: ORD200037 | B39: 45579 | C39: C10054 | D39: Laptop | E39: 2 | F39: 76.74 | G39: 409 Main St | H39: Cash | I39: Returned | J39: TRK94005261 | K39: 7 | L39: SAVE10 | M39: Instagram | N39: 153.48
A40: ORD200038 | B40: 45645 | C40: C15924 | D40: Laptop | E40: 1 | F40: 245.89 | G40: 549 Main St | H40: Debit Card | I40: Delivered | J40: TRK14835975 | K40: 3 | L40: SAVE10 | M40: Google | N40: 245.89
A41: ORD200039 | B41: 45715 | C41: C96664 | D41: Printer | E41: 3 | F41: 256.46 | G41: 666 Main St | H41: Credit Card | I41: Delivered | J41: TRK85508960 | K41: 4 | L41: SAVE10 | M41: Referral | N41: 769.38
A42: ORD200040 | B42: 45158 | C42: C84766 | D42: Desk | E42: 2 | F42: 344.02 | G42: 267 Main St | H42: Online | I42: Delivered | J42: TRK78967923 | K42: 4 | L42: FREESHIP | M42: Instagram | N42: 688.04
A43: ORD200041 | B43: 45265 | C43: C20212 | D43: Monitor | E43: 3 | F43: 611.45 | G43: 657 Main St | H43: Gift Card | I43: Pending | J43: TRK69733327 | K43: 4 | L43: FREESHIP | M43: Instagram | N43: 1834.35
A44: ORD200042 | B44: 45418 | C44: C28712 | D44: Printer | E44: 2 | F44: 151.66 | G44: 980 Main St | H44: Cash | I44: Cancelled | J44: TRK40772558 | K44: 6 | M44: Instagram | N44: 303.32
A45: ORD200043 | B45: 45274 | C45: C60572 | D45: Chair | E45: 3 | F45: 499.21 | G45: 871 Main St | H45: Online | I45: Cancelled | J45: TRK20351666 | K45: 8 | M45: Instagram | N45: 1497.63
A46: ORD200044 | B46: 45768 | C46: C73225 | D46: Phone | E46: 2 | F46: 550.18 | G46: 996 Main St | H46: Gift Card | I46: Returned | J46: TRK73848522 | K46: 3 | L46: FREESHIP | M46: Referral | N46: 1100.36
A47: ORD200045 | B47: 45332 | C47: C17388 | D47: Chair | E47: 1 | F47: 317.25 | G47: 157 Main St | H47: Debit Card | I47: Returned | J47: TRK47077395 | K47: 1 | L47: SAVE10 | M47: Facebook | N47: 317.25
A48: ORD200046 | B48: 45469 | C48: C43212 | D48: Monitor | E48: 4 | F48: 550.14 | G48: 223 Main St | H48: Debit Card | I48: Pending | J48: TRK25100762 | K48: 4 | L48: FREESHIP | M48: Instagram | N48: 2200.56
A49: ORD200047 | B49: 45126 | C49: C38134 | D49: Desk | E49: 2 | F49: 209.94 | G49: 323 Main St | H49: Credit Card | I49: Returned | J49: TRK42450754 | K49: 3 | L49: FREESHIP | M49: Email | N49: 419.88
A50: ORD200048 | B50: 45164 | C50: C12408 | D50: Monitor | E50: 2 | F50: 80.77 | G50: 464 Main St | H50: Debit Card | I50: Shipped | J50: TRK38938858 | K50: 4 | M50: Google | N50: 161.54
A51: ORD200049 | B51: 45206 | C51: C11985 | D51: Printer | E51: 1 | F51: 30.44 | G51: 633 Main St | H51: Credit Card | I51: Shipped | J51: TRK53272402 | K51: 1 | L51: SAVE10 | M51: Email | N51: 30.44
A52: ORD200050 | B52: 45138 | C52: C96494 | D52: Tablet | E52: 1 | F52: 179.22 | G52: 446 Main St | H52: Online | I52: Cancelled | J52: TRK14675049 | K52: 6 | L52: FREESHIP | M52: Instagram | N52: 179.22
A53: ORD200051 | B53: 45656 | C53: C36778 | D53: Tablet | E53: 1 | F53: 388.33 | G53: 434 Main St | H53: Cash | I53: Returned | J53: TRK67610289 | K53: 2 | L53: SAVE10 | M53: Facebook | N53: 388.33
A54: ORD200052 | B54: 45543 | C54: C30513 | D54: Tablet | E54: 1 | F54: 586.44 | G54: 232 Main St | H54: Online | I54: Returned | J54: TRK64320429 | K54: 5 | L54: SAVE10 | M54: Facebook | N54: 586.44
A55: ORD200053 | B55: 45430 | C55: C67551 | D55: Phone | E55: 4 | F55: 488.78 | G55: 512 Main St | H55: Online | I55: Returned | J55: TRK94992552 | K55: 5 | L55: FREESHIP | M55: Google | N55: 1955.12
A56: ORD200054 | B56: 45743 | C56: C48120 | D56: Chair | E56: 1 | F56: 280.25 | G56: 623 Main St | H56: Online | I56: Pending | J56: TRK11014449 | K56: 5 | L56: WINTER15 | M56: Email | N56: 280.25
A57: ORD200055 | B57: 45832 | C57: C95984 | D57: Printer | E57: 3 | F57: 344.4 | G57: 565 Main St | H57: Online | I57: Cancelled | J57: TRK67434829 | K57: 3 | M57: Facebook | N57: 1033.2
A58: ORD200056 | B58: 45067 | C58: C54298 | D58: Tablet | E58: 3 | F58: 479.21 | G58: 566 Main St | H58: Cash | I58: Cancelled | J58: TRK62902341 | K58: 5 | L58: WINTER15 | M58: Referral | N58: 1437.63
A59: ORD200057 | B59: 44948 | C59: C88036 | D59: Printer | E59: 5 | F59: 314.27 | G59: 842 Main St | H59: Cash | I59: Returned | J59: TRK52470128 | K59: 6 | L59: SAVE10 | M59: Instagram | N59: 1571.35
A60: ORD200058 | B60: 44941 | C60: C60190 | D60: Phone | E60: 4 | F60: 474.69 | G60: 202 Main St | H60: Gift Card | I60: Cancelled | J60: TRK70857868 | K60: 6 | L60: SAVE10 | M60: Google | N60: 1898.76
A61: ORD200059 | B61: 45546 | C61: C97603 | D61: Chair | E61: 4 | F61: 593.27 | G61: 811 Main St | H61: Online | I61: Shipped | J61: TRK47055028 | K61: 5 | M61: Facebook | N61: 2373.08
A62: ORD200060 | B62: 45525 | C62: C39256 | D62: Desk | E62: 1 | F62: 417.1 | G62: 634 Main St | H62: Debit Card | I62: Returned | J62: TRK23412025 | K62: 3 | L62: FREESHIP | M62: Referral | N62: 417.1
A63: ORD200061 | B63: 45375 | C63: C61618 | D63: Desk | E63: 4 | F63: 122.2 | G63: 104 Main St | H63: Cash | I63: Delivered | J63: TRK43458485 | K63: 7 | L63: FREESHIP | M63: Facebook | N63: 488.8
A64: ORD200062 | B64: 45160 | C64: C36497 | D64: Desk | E64: 2 | F64: 43.15 | G64: 691 Main St | H64: Debit Card | I64: Pending | J64: TRK12102911 | K64: 3 | L64: WINTER15 | M64: Email | N64: 86.3
A65: ORD200063 | B65: 45690 | C65: C96695 | D65: Chair | E65: 1 | F65: 564.86 | G65: 813 Main St | H65: Debit Card | I65: Shipped | J65: TRK64283851 | K65: 6 | L65: WINTER15 | M65: Referral | N65: 564.86
A66: ORD200064 | B66: 45833 | C66: C49720 | D66: Printer | E66: 3 | F66: 130.61 | G66: 752 Main St | H66: Debit Card | I66: Cancelled | J66: TRK55785217 | K66: 4 | L66: FREESHIP | M66: Facebook | N66: 391.83
A67: ORD200065 | B67: 45290 | C67: C97735 | D67: Monitor | E67: 5 | F67: 81.7 | G67: 385 Main St | H67: Credit Card | I67: Delivered | J67: TRK13743703 | K67: 6 | M67: Instagram | N67: 408.5
A68: ORD200066 | B68: 45611 | C68: C18104 | D68: Chair | E68: 5 | F68: 127.18 | G68: 715 Main St | H68: Cash | I68: Cancelled | J68: TRK15488568 | K68: 9 | L68: SAVE10 | M68: Referral | N68: 635.9
A69: ORD200067 | B69: 45635 | C69: C25587 | D69: Printer | E69: 4 | F69: 12.1 | G69: 440 Main St | H69: Debit Card | I69: Cancelled | J69: TRK55105323 | K69: 8 | M69: Google | N69: 48.4
A70: ORD200068 | B70: 45271 | C70: C41598 | D70: Chair | E70: 3 | F70: 490.92 | G70: 709 Main St | H70: Credit Card | I70: Pending | J70: TRK81665940 | K70: 5 | L70: FREESHIP | M70: Email | N70: 1472.76
A71: ORD200069 | B71: 45057 | C71: C43338 | D71: Monitor | E71: 3 | F71: 478.65 | G71: 552 Main St | H71: Online | I71: Shipped | J71: TRK35241775 | K71: 4 | M71: Referral | N71: 1435.95
A72: ORD200070 | B72: 45072 | C72: C25123 | D72: Desk | E72: 1 | F72: 629.21 | G72: 384 Main St | H72: Gift Card | I72: Pending | J72: TRK27812282 | K72: 2 | L72: FREESHIP | M72: Instagram | N72: 629.21
A73: ORD200071 | B73: 45818 | C73: C37454 | D73: Monitor | E73: 3 | F73: 434.45 | G73: 923 Main St | H73: Credit Card | I73: Pending | J73: TRK28252730 | K73: 4 | M73: Referral | N73: 1303.35
A74: ORD200072 | B74: 45648 | C74: C19451 | D74: Tablet | E74: 4 | F74: 589.44 | G74: 942 Main St | H74: Gift Card | I74: Returned | J74: TRK87787793 | K74: 5 | M74: Facebook | N74: 2357.76
A75: ORD200073 | B75: 45049 | C75: C17269 | D75: Monitor | E75: 4 | F75: 433.45 | G75: 129 Main St | H75: Gift Card | I75: Cancelled | J75: TRK79608389 | K75: 4 | M75: Facebook | N75: 1733.8
A76: ORD200074 | B76: 45101 | C76: C25382 | D76: Phone | E76: 5 | F76: 90.87 | G76: 622 Main St | H76: Cash | I76: Pending | J76: TRK64691287 | K76: 5 | M76: Instagram | N76: 454.35
A77: ORD200075 | B77: 45195 | C77: C80651 | D77: Tablet | E77: 3 | F77: 398.17 | G77: 917 Main St | H77: Debit Card | I77: Delivered | J77: TRK14846720 | K77: 5 | L77: SAVE10 | M77: Email | N77: 1194.51
A78: ORD200076 | B78: 45382 | C78: C58638 | D78: Laptop | E78: 4 | F78: 382.88 | G78: 239 Main St | H78: Cash | I78: Cancelled | J78: TRK38224871 | K78: 6 | L78: WINTER15 | M78: Email | N78: 1531.52
A79: ORD200077 | B79: 45436 | C79: C50121 | D79: Phone | E79: 1 | F79: 583.18 | G79: 348 Main St | H79: Credit Card | I79: Returned | J79: TRK79810059 | K79: 5 | M79: Google | N79: 583.18
A80: ORD200078 | B80: 45510 | C80: C32029 | D80: Printer | E80: 4 | F80: 175.36 | G80: 146 Main St | H80: Debit Card | I80: Delivered | J80: TRK68535532 | K80: 4 | L80: FREESHIP | M80: Instagram | N80: 701.44
A81: ORD200079 | B81: 45726 | C81: C76700 | D81: Tablet | E81: 2 | F81: 311.91 | G81: 103 Main St | H81: Online | I81: Shipped | J81: TRK13036341 | K81: 2 | M81: Facebook | N81: 623.82
A82: ORD200080 | B82: 45104 | C82: C29041 | D82: Phone | E82: 3 | F82: 589.56 | G82: 591 Main St | H82: Online | I82: Returned | J82: TRK28840655 | K82: 6 | M82: Facebook | N82: 1768.68
A83: ORD200081 | B83: 45085 | C83: C29314 | D83: Monitor | E83: 2 | F83: 394.3 | G83: 496 Main St | H83: Cash | I83: Shipped | J83: TRK59876213 | K83: 6 | L83: FREESHIP | M83: Email | N83: 788.6
A84: ORD200082 | B84: 45296 | C84: C65799 | D84: Tablet | E84: 4 | F84: 565.2 | G84: 971 Main St | H84: Debit Card | I84: Shipped | J84: TRK66906607 | K84: 9 | L84: SAVE10 | M84: Google | N84: 2260.8
A85: ORD200083 | B85: 45160 | C85: C15681 | D85: Laptop | E85: 4 | F85: 540.41 | G85: 989 Main St | H85: Credit Card | I85: Cancelled | J85: TRK75112172 | K85: 6 | M85: Referral | N85: 2161.64
A86: ORD200084 | B86: 45166 | C86: C64160 | D86: Monitor | E86: 2 | F86: 165.49 | G86: 967 Main St | H86: Online | I86: Shipped | J86: TRK34121529 | K86: 4 | L86: WINTER15 | M86: Instagram | N86: 330.98
A87: ORD200085 | B87: 45544 | C87: C14553 | D87: Tablet | E87: 3 | F87: 146.73 | G87: 768 Main St | H87: Cash | I87: Delivered | J87: TRK93538334 | K87: 8 | L87: FREESHIP | M87: Email | N87: 440.19
A88: ORD200086 | B88: 45462 | C88: C88205 | D88: Printer | E88: 5 | F88: 643.03 | G88: 447 Main St | H88: Online | I88: Cancelled | J88: TRK93504166 | K88: 5 | L88: FREESHIP | M88: Referral | N88: 3215.15
A89: ORD200087 | B89: 45575 | C89: C91245 | D89: Tablet | E89: 3 | F89: 225.11 | G89: 915 Main St | H89: Cash | I89: Shipped | J89: TRK46976391 | K89: 4 | L89: SAVE10 | M89: Facebook | N89: 675.33
A90: ORD200088 | B90: 45813 | C90: C75439 | D90: Desk | E90: 3 | F90: 114.81 | G90: 318 Main St | H90: Gift Card | I90: Cancelled | J90: TRK19831653 | K90: 7 | M90: Google | N90: 344.43
A91: ORD200089 | B91: 45713 | C91: C17181 | D91: Printer | E91: 5 | F91: 455.33 | G91: 291 Main St | H91: Credit Card | I91: Cancelled | J91: TRK78912978 | K91: 8 | L91: FREESHIP | M91: Google | N91: 2276.65
A92: ORD200090 | B92: 45187 | C92: C36540 | D92: Chair | E92: 4 | F92: 182.08 | G92: 611 Main St | H92: Gift Card | I92: Delivered | J92: TRK35828122 | K92: 4 | L92: SAVE10 | M92: Email | N92: 728.32
A93: ORD200091 | B93: 45000 | C93: C98216 | D93: Laptop | E93: 5 | F93: 492.75 | G93: 196 Main St | H93: Cash | I93: Shipped | J93: TRK40986666 | K93: 6 | L93: WINTER15 | M93: Referral | N93: 2463.75
A94: ORD200092 | B94: 45453 | C94: C29568 | D94: Printer | E94: 4 | F94: 48.61 | G94: 203 Main St | H94: Online | I94: Shipped | J94: TRK46531075 | K94: 7 | L94: FREESHIP | M94: Facebook | N94: 194.44
A95: ORD200093 | B95: 44940 | C95: C97262 | D95: Desk | E95: 4 | F95: 431.01 | G95: 837 Main St | H95: Credit Card | I95: Returned | J95: TRK65990229 | K95: 7 | M95: Referral | N95: 1724.04
A96: ORD200094 | B96: 44968 | C96: C79821 | D96: Chair | E96: 1 | F96: 531.18 | G96: 781 Main St | H96: Gift Card | I96: Returned | J96: TRK12780193 | K96: 6 | L96: WINTER15 | M96: Instagram | N96: 531.18
A97: ORD200095 | B97: 45009 | C97: C76761 | D97: Printer | E97: 4 | F97: 117.51 | G97: 839 Main St | H97: Debit Card | I97: Returned | J97: TRK60179774 | K97: 7 | M97: Referral | N97: 470.04
A98: ORD200096 | B98: 45444 | C98: C93007 | D98: Phone | E98: 2 | F98: 232.83 | G98: 103 Main St | H98: Gift Card | I98: Delivered | J98: TRK85696091 | K98: 7 | M98: Instagram | N98: 465.66
A99: ORD200097 | B99: 45678 | C99: C15624 | D99: Tablet | E99: 5 | F99: 619.52 | G99: 922 Main St | H99: Debit Card | I99: Pending | J99: TRK40621141 | K99: 9 | M99: Email | N99: 3097.6
A100: ORD200098 | B100: 44940 | C100: C70921 | D100: Printer | E100: 2 | F100: 228.54 | G100: 533 Main St | H100: Debit Card | I100: Pending | J100: TRK54983109 | K100: 3 | M100: Email | N100: 457.08
...

Sheet Customer Data
A1: Customer_ID | B1: Customer Name | C1: Gender | D1: Age | E1: City
A2: C72649 | B2: ="Customer_" & ROW() -> Customer_2 | C2: Male | D2: 40 | E2: Lagos
A3: C75739 | B3: ="Customer_" & ROW() -> Customer_3 | C3: Female | D3: 44 | E3: Abuja
A4: C81728 | B4: ="Customer_" & ROW() -> Customer_4 | C4: Female | D4: 25 | E4: Abuja
A5: C33540 | B5: ="Customer_" & ROW() -> Customer_5 | C5: Female | D5: 46 | E5: Enugu
A6: C81840 | B6: ="Customer_" & ROW() -> Customer_6 | C6: Male | D6: 55 | E6: Abuja
A7: C37249 | B7: ="Customer_" & ROW() -> Customer_7 | C7: Female | D7: 18 | E7: Port-Harcourt
A8: C83492 | B8: ="Customer_" & ROW() -> Customer_8 | C8: Female | D8: 33 | E8: Kano
A9: C41460 | B9: ="Customer_" & ROW() -> Customer_9 | C9: Female | D9: 59 | E9: Owerri
A10: C26817 | B10: ="Customer_" & ROW() -> Customer_10 | C10: Male | D10: 41 | E10: Port-Harcourt
A11: C31946 | B11: ="Customer_" & ROW() -> Customer_11 | C11: Female | D11: 56 | E11: Kano
A12: C43443 | B12: ="Customer_" & ROW() -> Customer_12 | C12: Female | D12: 21 | E12: Kano
A13: C93861 | B13: ="Customer_" & ROW() -> Customer_13 | C13: Female | D13: 19 | E13: Lagos
... A1201: C57502 | B1201: ="Customer_" & ROW() -> Customer_1201 | C1201: Male | D1201: 36 | E1201: Kano

Sheet Product Category
A1: Product | B1: Category
A2: Chair | B2: Furniture
A3: Desk | B3: Furniture
A4: Laptop | B4: Electronics
A5: Monitor | B5: Electronics
A6: Phone | B6: Electronics
A7: Printer | B7: Electronics
A8: Tablet | B8: Electronics

Sheet Coupons
A1: Coupon Code | B1: Discount
A2: WINTER15 | B2: 0.15
A3: SAVE10 | B3: 0.1
A4: FREESHIP | B4: 0
A5: NO COUPON | B5: 0

Sheet Clean Data
A1: OrderID | B1: Order_ID | C1: Date | D1: Order Date | E1: Order Year | F1: Order Month | G1: Order Day | H1: CustomerID | I1: Customer_ID | J1: Product | K1: PRODUCTS | L1: Quantity | M1: UnitPrice | N1: Unit_Price | O1: ShippingAddress | P1: Street Number | Q1: Street Name | R1: PaymentMethod | S1: Payment_Method | T1: OrderStatus | U1: Order_Status | V1: TrackingNumber | W1: Tracking_Number | X1: Items In Cart | Y1: CouponCode | Z1: Coupon_Code | AA1: Coupon Usage | AB1: ReferralSource | AC1: Referral_Source | AD1: TotalPrice | AE1: Total_Price | AF1: Revenue | AG1: Customer Name | AH1: Gender | AI1: Age | AJ1: City | AK1: Product Category | AL1: Discount | AM1: Discount Amount | AN1: Cost Per Unit | AO1: Total Cost Price | AP1: Net Revenue | AQ1: Profit | AR1: Profit Margin | AS1: KPI Summary
A2: ORD200000 | B2: =(RIGHT(A2, LEN(A2)-3))*1 -> 200000 | C2: 44930 | D2: 44930 | E2: =(TEXT(D2, "yyyy"))*1 -> 2023 | F2: =TEXT(D2, "mmmm") -> January | G2: =TEXT(D2, "dddd") -> Wednesday | H2: C72649 | I2: =(RIGHT(H2, LEN(H2)-1))*1 -> 72649 | J2: Monitor | K2: =TRIM(PROPER(J2)) -> Monitor | L2: 5 | M2: 570.62 | N2: =(TRIM(PROPER(M2)))*1 -> 570.62 | O2: 928 Main St | P2: =LEFT(O2, FIND(" ", O2)-1) -> 928 | Q2: =RIGHT(O2, LEN(O2) - FIND(" ", O2)) -> Main St | R2: Debit Card | S2: =TRIM(PROPER(R2)) -> Debit Card | T2: Shipped | U2: =TRIM(PROPER(T2)) -> Shipped | V2: TRK37947903 | W2: =RIGHT(V2, LEN(V2)-3) -> 37947903 | X2: 7 | Y2: SAVE10 | Z2: =TRIM(UPPER(IF(Y2="", "NO COUPON", Y2))) -> SAVE10 | AA2: =IF(Z2="NO COUPON","NO","YES") -> YES | AB2: Instagram | AC2: =TRIM(PROPER(AB2)) -> Instagram | AD2: 2853.1 | AE2: 2853.1 | AF2: =N2*L2 -> 2853.1 | AG2: =_xlfn.XLOOKUP(H2, 'Customer Data'!A2,'Customer Data'!B2) -> Customer_2 | AH2: =_xlfn.XLOOKUP(H2,'Customer Data'!A2,'Customer Data'!C2) -> Male | AI2: =_xlfn.XLOOKUP(H2,'Customer Data'!A2,'Customer Data'!D2) -> 40 | AJ2: =_xlfn.XLOOKUP(H2,'Customer Data'!A2,'Customer Data'!E2) -> Lagos | AK2: =VLOOKUP(K2,'Product Category'!A:B,2,FALSE) -> Electronics | AL2: =VLOOKUP(Z2,Coupons!A:B,2,FALSE) -> 0.1 | AM2: =AE2*AL2 -> 285.31 | AN2: =N2*0.7 -> 399.434 | AO2: =AN2*L2 -> 1997.17 | AP2: =AF2-AM2 -> 2567.79 | AQ2: =AP2-AO2 -> 570.62 | AR2: =AP2/AO2 -> 1.2857143 | AS2: TOTAL NET REVENUE | AT2: =SUM(AP2:AP1201) -> 1188905.4
A3: ORD200001 | B3: =(RIGHT(A3, LEN(A3)-3))*1 -> 200001 | C3: 45527 | D3: 45527 | E3: =(TEXT(D3, "yyyy"))*1 -> 2024 | F3: =TEXT(D3, "mmmm") -> August | G3: =TEXT(D3, "dddd") -> Friday | H3: C75739 | I3: =(RIGHT(H3, LEN(H3)-1))*1 -> 75739 | J3: Phone | K3: =TRIM(PROPER(J3)) -> Phone | L3: 2 | M3: 151.35 | N3: =(TRIM(PROPER(M3)))*1 -> 151.35 | O3: 823 Main St | P3: =LEFT(O3, FIND(" ", O3)-1) -> 823 | Q3: =RIGHT(O3, LEN(O3) - FIND(" ", O3)) -> Main St | R3: Online | S3: =TRIM(PROPER(R3)) -> Online | T3: Shipped | U3: =TRIM(PROPER(T3)) -> Shipped | V3: TRK91186779 | W3: =RIGHT(V3, LEN(V3)-3) -> 91186779 | X3: 3 | Y3: SAVE10 | Z3: =TRIM(UPPER(IF(Y3="", "NO COUPON", Y3))) -> SAVE10 | AA3: =IF(Z3="NO COUPON","NO","YES") -> YES | AB3: Referral | AC3: =TRIM(PROPER(AB3)) -> Referral | AD3: 302.7 | AE3: 302.7 | AF3: =N3*L3 -> 302.7 | AG3: =_xlfn.XLOOKUP(H3, 'Customer Data'!A3,'Customer Data'!B3) -> Customer_3 | AH3: =_xlfn.XLOOKUP(H3,'Customer Data'!A3,'Customer Data'!C3) -> Female | AI3: =_xlfn.XLOOKUP(H3,'Customer Data'!A3,'Customer Data'!D3) -> 44 | AJ3: =_xlfn.XLOOKUP(H3,'Customer Data'!A3,'Customer Data'!E3) -> Abuja | AK3: =VLOOKUP(K3,'Product Category'!A:B,2,FALSE) -> Electronics | AL3: =VLOOKUP(Z3,Coupons!A:B,2,FALSE) -> 0.1 | AM3: =AE3*AL3 -> 30.27 | AN3: =N3*0.7 -> 105.945 | AO3: =AN3*L3 -> 211.89 | AP3: =AF3-AM3 -> 272.43 | AQ3: =AP3-AO3 -> 60.54 | AR3: =AP3/AO3 -> 1.2857143 | AS3: TOTAL ORDERS | AT3: =COUNT(B2:B1201) -> 1200
A4: ORD200002 | B4: =(RIGHT(A4, LEN(A4)-3))*1 -> 200002 | C4: 45349 | D4: 45349 | E4: =(TEXT(D4, "yyyy"))*1 -> 2024 | F4: =TEXT(D4, "mmmm") -> February | G4: =TEXT(D4, "dddd") -> Tuesday | H4: C81728 | I4: =(RIGHT(H4, LEN(H4)-1))*1 -> 81728 | J4: Tablet | K4: =TRIM(PROPER(J4)) -> Tablet | L4: 5 | M4: 550.68 | N4: =(TRIM(PROPER(M4)))*1 -> 550.68 | O4: 512 Main St | P4: =LEFT(O4, FIND(" ", O4)-1) -> 512 | Q4: =RIGHT(O4, LEN(O4) - FIND(" ", O4)) -> Main St | R4: Credit Card | S4: =TRIM(PROPER(R4)) -> Credit Card | T4: Cancelled | U4: =TRIM(PROPER(T4)) -> Cancelled | V4: TRK42903982 | W4: =RIGHT(V4, LEN(V4)-3) -> 42903982 | X4: 8 | Y4: FREESHIP | Z4: =TRIM(UPPER(IF(Y4="", "NO COUPON", Y4))) -> FREESHIP | AA4: =IF(Z4="NO COUPON","NO","YES") -> YES | AB4: Email | AC4: =TRIM(PROPER(AB4)) -> Email | AD4: 2753.4 | AE4: 2753.4 | AF4: =N4*L4 -> 2753.4 | AG4: =_xlfn.XLOOKUP(H4, 'Customer Data'!A4,'Customer Data'!B4) -> Customer_4 | AH4: =_xlfn.XLOOKUP(H4,'Customer Data'!A4,'Customer Data'!C4) -> Female | AI4: =_xlfn.XLOOKUP(H4,'Customer Data'!A4,'Customer Data'!D4) -> 25 | AJ4: =_xlfn.XLOOKUP(H4,'Customer Data'!A4,'Customer Data'!E4) -> Abuja | AK4: =VLOOKUP(K4,'Product Category'!A:B,2,FALSE) -> Electronics | AL4: =VLOOKUP(Z4,Coupons!A:B,2,FALSE) -> 0 | AM4: =AE4*AL4 -> 0 | AN4: =N4*0.7 -> 385.476 | AO4: =AN4*L4 -> 1927.38 | AP4: =AF4-AM4 -> 2753.4 | AQ4: =AP4-AO4 -> 826.02 | AR4: =AP4/AO4 -> 1.4285714 | AS4: AVERAGE ORDER VALUE | AT4: =AVERAGE(AP2:AP1201) -> 990.75452
A5: ORD200003 | B5: =(RIGHT(A5, LEN(A5)-3))*1 -> 200003 | C5: 45214 | D5: 45214 | E5: =(TEXT(D5, "yyyy"))*1 -> 2023 | F5: =TEXT(D5, "mmmm") -> October | G5: =TEXT(D5, "dddd") -> Sunday | H5: C33540 | I5: =(RIGHT(H5, LEN(H5)-1))*1 -> 33540 | J5: Chair | K5: =TRIM(PROPER(J5)) -> Chair | L5: 1 | M5: 273.19 | N5: =(TRIM(PROPER(M5)))*1 -> 273.19 | O5: 275 Main St | P5: =LEFT(O5, FIND(" ", O5)-1) -> 275 | Q5: =RIGHT(O5, LEN(O5) - FIND(" ", O5)) -> Main St | R5: Debit Card | S5: =TRIM(PROPER(R5)) -> Debit Card | T5: Returned | U5: =TRIM(PROPER(T5)) -> Returned | V5: TRK62788070 | W5: =RIGHT(V5, LEN(V5)-3) -> 62788070 | X5: 5 | Y5: SAVE10 | Z5: =TRIM(UPPER(IF(Y5="", "NO COUPON", Y5))) -> SAVE10 | AA5: =IF(Z5="NO COUPON","NO","YES") -> YES | AB5: Facebook | AC5: =TRIM(PROPER(AB5)) -> Facebook | AD5: 273.19 | AE5: 273.19 | AF5: =N5*L5 -> 273.19 | AG5: =_xlfn.XLOOKUP(H5, 'Customer Data'!A5,'Customer Data'!B5) -> Customer_5 | AH5: =_xlfn.XLOOKUP(H5,'Customer Data'!A5,'Customer Data'!C5) -> Female | AI5: =_xlfn.XLOOKUP(H5,'Customer Data'!A5,'Customer Data'!D5) -> 46 | AJ5: =_xlfn.XLOOKUP(H5,'Customer Data'!A5,'Customer Data'!E5) -> Enugu | AK5: =VLOOKUP(K5,'Product Category'!A:B,2,FALSE) -> Furniture | AL5: =VLOOKUP(Z5,Coupons!A:B,2,FALSE) -> 0.1 | AM5: =AE5*AL5 -> 27.319 | AN5: =N5*0.7 -> 191.233 | AO5: =AN5*L5 -> 191.233 | AP5: =AF5-AM5 -> 245.871 | AQ5: =AP5-AO5 -> 54.638 | AR5: =AP5/AO5 -> 1.2857143 | AS5: TOTAL PROFIT | AT5: =SUM(AQ2:AQ1201) -> 303572.05
A6: ORD200004 | B6: =(RIGHT(A6, LEN(A6)-3))*1 -> 200004 | C6: 45785 | D6: 45785 | E6: =(TEXT(D6, "yyyy"))*1 -> 2025 | F6: =TEXT(D6, "mmmm") -> May | G6: =TEXT(D6, "dddd") -> Thursday | H6: C81840 | I6: =(RIGHT(H6, LEN(H6)-1))*1 -> 81840 | J6: Printer | K6: =TRIM(PROPER(J6)) -> Printer | L6: 4 | M6: 626.01 | N6: =(TRIM(PROPER(M6)))*1 -> 626.01 | O6: 668 Main St | P6: =LEFT(O6, FIND(" ", O6)-1) -> 668 | Q6: =RIGHT(O6, LEN(O6) - FIND(" ", O6)) -> Main St | R6: Online | S6: =TRIM(PROPER(R6)) -> Online | T6: Delivered | U6: =TRIM(PROPER(T6)) -> Delivered | V6: TRK29241424 | W6: =RIGHT(V6, LEN(V6)-3) -> 29241424 | X6: 8 | Y6: SAVE10 | Z6: =TRIM(UPPER(IF(Y6="", "NO COUPON", Y6))) -> SAVE10 | AA6: =IF(Z6="NO COUPON","NO","YES") -> YES | AB6: Email | AC6: =TRIM(PROPER(AB6)) -> Email | AD6: 2504.04 | AE6: 2504.04 | AF6: =N6*L6 -> 2504.04 | AG6: =_xlfn.XLOOKUP(H6, 'Customer Data'!A6,'Customer Data'!B6) -> Customer_6 | AH6: =_xlfn.XLOOKUP(H6,'Customer Data'!A6,'Customer Data'!C6) -> Male | AI6: =_xlfn.XLOOKUP(H6,'Customer Data'!A6,'Customer Data'!D6) -> 55 | AJ6: =_xlfn.XLOOKUP(H6,'Customer Data'!A6,'Customer Data'!E6) -> Abuja | AK6: =VLOOKUP(K6,'Product Category'!A:B,2,FALSE) -> Electronics | AL6: =VLOOKUP(Z6,Coupons!A:B,2,FALSE) -> 0.1 | AM6: =AE6*AL6 -> 250.404 | AN6: =N6*0.7 -> 438.207 | AO6: =AN6*L6 -> 1752.828 | AP6: =AF6-AM6 -> 2253.636 | AQ6: =AP6-AO6 -> 500.808 | AR6: =AP6/AO6 -> 1.2857143 | AS6: TOTAL PROFIT MARGIN | AT6: =AT5/AT2 -> 0.25533743
A7: ORD200005 | B7: =(RIGHT(A7, LEN(A7)-3))*1 -> 200005 | C7: 45222 | D7: 45222 | E7: =(TEXT(D7, "yyyy"))*1 -> 2023 | F7: =TEXT(D7, "mmmm") -> October | G7: =TEXT(D7, "dddd") -> Monday | H7: C37249 | I7: =(RIGHT(H7, LEN(H7)-1))*1 -> 37249 | J7: Phone | K7: =TRIM(PROPER(J7)) -> Phone | L7: 2 | M7: 245.86 | N7: =(TRIM(PROPER(M7)))*1 -> 245.86 | O7: 934 Main St | P7: =LEFT(O7, FIND(" ", O7)-1) -> 934 | Q7: =RIGHT(O7, LEN(O7) - FIND(" ", O7)) -> Main St | R7: Credit Card | S7: =TRIM(PROPER(R7)) -> Credit Card | T7: Shipped | U7: =TRIM(PROPER(T7)) -> Shipped | V7: TRK72976927 | W7: =RIGHT(V7, LEN(V7)-3) -> 72976927 | X7: 4 | Y7: SAVE10 | Z7: =TRIM(UPPER(IF(Y7="", "NO COUPON", Y7))) -> SAVE10 | AA7: =IF(Z7="NO COUPON","NO","YES") -> YES | AB7: Instagram | AC7: =TRIM(PROPER(AB7)) -> Instagram | AD7: 491.72 | AE7: 491.72 | AF7: =N7*L7 -> 491.72 | AG7: =_xlfn.XLOOKUP(H7, 'Customer Data'!A7,'Customer Data'!B7) -> Customer_7 | AH7: =_xlfn.XLOOKUP(H7,'Customer Data'!A7,'Customer Data'!C7) -> Female | AI7: =_xlfn.XLOOKUP(H7,'Customer Data'!A7,'Customer Data'!D7) -> 18 | AJ7: =_xlfn.XLOOKUP(H7,'Customer Data'!A7,'Customer Data'!E7) -> Port-Harcourt | AK7: =VLOOKUP(K7,'Product Category'!A:B,2,FALSE) -> Electronics | AL7: =VLOOKUP(Z7,Coupons!A:B,2,FALSE) -> 0.1 | AM7: =AE7*AL7 -> 49.172 | AN7: =N7*0.7 -> 172.102 | AO7: =AN7*L7 -> 344.204 | AP7: =AF7-AM7 -> 442.548 | AQ7: =AP7-AO7 -> 98.344 | AR7: =AP7/AO7 -> 1.2857143 | AS7: TOTAL CUSTOMERS | AT7: =COUNT(I2:I1201) -> 1200
A8: ORD200006 | B8: =(RIGHT(A8, LEN(A8)-3))*1 -> 200006 | C8: 45825 | D8: 45825 | E8: =(TEXT(D8, "yyyy"))*1 -> 2025 | F8: =TEXT(D8, "mmmm") -> June | G8: =TEXT(D8, "dddd") -> Tuesday | H8: C83492 | I8: =(RIGHT(H8, LEN(H8)-1))*1 -> 83492 | J8: Laptop | K8: =TRIM(PROPER(J8)) -> Laptop | L8: 1 | M8: 664.42 | N8: =(TRIM(PROPER(M8)))*1 -> 664.42 | O8: 986 Main St | P8: =LEFT(O8, FIND(" ", O8)-1) -> 986 | Q8: =RIGHT(O8, LEN(O8) - FIND(" ", O8)) -> Main St | R8: Gift Card | S8: =TRIM(PROPER(R8)) -> Gift Card | T8: Returned | U8: =TRIM(PROPER(T8)) -> Returned | V8: TRK96417362 | W8: =RIGHT(V8, LEN(V8)-3) -> 96417362 | X8: 6 | Y8: SAVE10 | Z8: =TRIM(UPPER(IF(Y8="", "NO COUPON", Y8))) -> SAVE10 | AA8: =IF(Z8="NO COUPON","NO","YES") -> YES | AB8: Facebook | AC8: =TRIM(PROPER(AB8)) -> Facebook | AD8: 664.42 | AE8: 664.42 | AF8: =N8*L8 -> 664.42 | AG8: =_xlfn.XLOOKUP(H8, 'Customer Data'!A8,'Customer Data'!B8) -> Customer_8 | AH8: =_xlfn.XLOOKUP(H8,'Customer Data'!A8,'Customer Data'!C8) -> Female | AI8: =_xlfn.XLOOKUP(H8,'Customer Data'!A8,'Customer Data'!D8) -> 33 | AJ8: =_xlfn.XLOOKUP(H8,'Customer Data'!A8,'Customer Data'!E8) -> Kano | AK8: =VLOOKUP(K8,'Product Category'!A:B,2,FALSE) -> Electronics | AL8: =VLOOKUP(Z8,Coupons!A:B,2,FALSE) -> 0.1 | AM8: =AE8*AL8 -> 66.442 | AN8: =N8*0.7 -> 465.094 | AO8: =AN8*L8 -> 465.094 | AP8: =AF8-AM8 -> 597.978 | AQ8: =AP8-AO8 -> 132.884 | AR8: =AP8/AO8 -> 1.2857143 | AS8: TOTAL DISCOUNT GIVEN | AT8: =SUM(AM2:AM1201) -> 75856.533
A9: ORD200007 | B9: =(RIGHT(A9, LEN(A9)-3))*1 -> 200007 | C9: 45058 | D9: 45058 | E9: =(TEXT(D9, "yyyy"))*1 -> 2023 | F9: =TEXT(D9, "mmmm") -> May | G9: =TEXT(D9, "dddd") -> Friday | H9: C41460 | I9: =(RIGHT(H9, LEN(H9)-1))*1 -> 41460 | J9: Monitor | K9: =TRIM(PROPER(J9)) -> Monitor | L9: 5 | M9: 149.55 | N9: =(TRIM(PROPER(M9)))*1 -> 149.55 | O9: 706 Main St | P9: =LEFT(O9, FIND(" ", O9)-1) -> 706 | Q9: =RIGHT(O9, LEN(O9) - FIND(" ", O9)) -> Main St | R9: Cash | S9: =TRIM(PROPER(R9)) -> Cash | T9: Shipped | U9: =TRIM(PROPER(T9)) -> Shipped | V9: TRK78809193 | W9: =RIGHT(V9, LEN(V9)-3) -> 78809193 | X9: 9 | Y9: FREESHIP | Z9: =TRIM(UPPER(IF(Y9="", "NO COUPON", Y9))) -> FREESHIP | AA9: =IF(Z9="NO COUPON","NO","YES") -> YES | AB9: Facebook | AC9: =TRIM(PROPER(AB9)) -> Facebook | AD9: 747.75 | AE9: 747.75 | AF9: =N9*L9 -> 747.75 | AG9: =_xlfn.XLOOKUP(H9, 'Customer Data'!A9,'Customer Data'!B9) -> Customer_9 | AH9: =_xlfn.XLOOKUP(H9,'Customer Data'!A9,'Customer Data'!C9) -> Female | AI9: =_xlfn.XLOOKUP(H9,'Customer Data'!A9,'Customer Data'!D9) -> 59 | AJ9: =_xlfn.XLOOKUP(H9,'Customer Data'!A9,'Customer Data'!E9) -> Owerri | AK9: =VLOOKUP(K9,'Product Category'!A:B,2,FALSE) -> Electronics | AL9: =VLOOKUP(Z9,Coupons!A:B,2,FALSE) -> 0 | AM9: =AE9*AL9 -> 0 | AN9: =N9*0.7 -> 104.685 | AO9: =AN9*L9 -> 523.425 | AP9: =AF9-AM9 -> 747.75 | AQ9: =AP9-AO9 -> 224.325 | AR9: =AP9/AO9 -> 1.4285714
A10: ORD200008 | B10: =(RIGHT(A10, LEN(A10)-3))*1 -> 200008 | C10: 45749 | D10: 45749 | E10: =(TEXT(D10, "yyyy"))*1 -> 2025 | F10: =TEXT(D10, "mmmm") -> April | G10: =TEXT(D10, "dddd") -> Wednesday | H10: C26817 | I10: =(RIGHT(H10, LEN(H10)-1))*1 -> 26817 | J10: Phone | K10: =TRIM(PROPER(J10)) -> Phone | L10: 2 | M10: 134.28 | N10: =(TRIM(PROPER(M10)))*1 -> 134.28 | O10: 904 Main St | P10: =LEFT(O10, FIND(" ", O10)-1) -> 904 | Q10: =RIGHT(O10, LEN(O10) - FIND(" ", O10)) -> Main St | R10: Gift Card | S10: =TRIM(PROPER(R10)) -> Gift Card | T10: Cancelled | U10: =TRIM(PROPER(T10)) -> Cancelled | V10: TRK61042692 | W10: =RIGHT(V10, LEN(V10)-3) -> 61042692 | X10: 2 | Z10: =TRIM(UPPER(IF(Y10="", "NO COUPON", Y10))) -> NO COUPON | AA10: =IF(Z10="NO COUPON","NO","YES") -> NO | AB10: Email | AC10: =TRIM(PROPER(AB10)) -> Email | AD10: 268.56 | AE10: 268.56 | AF10: =N10*L10 -> 268.56 | AG10: =_xlfn.XLOOKUP(H10, 'Customer Data'!A10,'Customer Data'!B10) -> Customer_10 | AH10: =_xlfn.XLOOKUP(H10,'Customer Data'!A10,'Customer Data'!C10) -> Male | AI10: =_xlfn.XLOOKUP(H10,'Customer Data'!A10,'Customer Data'!D10) -> 41 | AJ10: =_xlfn.XLOOKUP(H10,'Customer Data'!A10,'Customer Data'!E10) -> Port-Harcourt | AK10: =VLOOKUP(K10,'Product Category'!A:B,2,FALSE) -> Electronics | AL10: =VLOOKUP(Z10,Coupons!A:B,2,FALSE) -> 0 | AM10: =AE10*AL10 -> 0 | AN10: =N10*0.7 -> 93.996 | AO10: =AN10*L10 -> 187.992 | AP10: =AF10-AM10 -> 268.56 | AQ10: =AP10-AO10 -> 80.568 | AR10: =AP10/AO10 -> 1.4285714
A11: ORD200009 | B11: =(RIGHT(A11, LEN(A11)-3))*1 -> 200009 | C11: 45251 | D11: 45251 | E11: =(TEXT(D11, "yyyy"))*1 -> 2023 | F11: =TEXT(D11, "mmmm") -> November | G11: =TEXT(D11, "dddd") -> Tuesday | H11: C31946 | I11: =(RIGHT(H11, LEN(H11)-1))*1 -> 31946 | J11: Desk | K11: =TRIM(PROPER(J11)) -> Desk | L11: 4 | M11: 509.38 | N11: =(TRIM(PROPER(M11)))*1 -> 509.38 | O11: 102 Main St | P11: =LEFT(O11, FIND(" ", O11)-1) -> 102 | Q11: =RIGHT(O11, LEN(O11) - FIND(" ", O11)) -> Main St | R11: Credit Card | S11: =TRIM(PROPER(R11)) -> Credit Card | T11: Shipped | U11: =TRIM(PROPER(T11)) -> Shipped | V11: TRK33478363 | W11: =RIGHT(V11, LEN(V11)-3) -> 33478363 | X11: 6 | Y11: SAVE10 | Z11: =TRIM(UPPER(IF(Y11="", "NO COUPON", Y11))) -> SAVE10 | AA11: =IF(Z11="NO COUPON","NO","YES") -> YES | AB11: Google | AC11: =TRIM(PROPER(AB11)) -> Google | AD11: 2037.52 | AE11: 2037.52 | AF11: =N11*L11 -> 2037.52 | AG11: =_xlfn.XLOOKUP(H11, 'Customer Data'!A11,'Customer Data'!B11) -> Customer_11 | AH11: =_xlfn.XLOOKUP(H11,'Customer Data'!A11,'Customer Data'!C11) -> Female | AI11: =_xlfn.XLOOKUP(H11,'Customer Data'!A11,'Customer Data'!D11) -> 56 | AJ11: =_xlfn.XLOOKUP(H11,'Customer Data'!A11,'Customer Data'!E11) -> Kano | AK11: =VLOOKUP(K11,'Product Category'!A:B,2,FALSE) -> Furniture | AL11: =VLOOKUP(Z11,Coupons!A:B,2,FALSE) -> 0.1 | AM11: =AE11*AL11 -> 203.752 | AN11: =N11*0.7 -> 356.566 | AO11: =AN11*L11 -> 1426.264 | AP11: =AF11-AM11 -> 1833.768 | AQ11: =AP11-AO11 -> 407.504 | AR11: =AP11/AO11 -> 1.2857143
A12: ORD200010 | B12: =(RIGHT(A12, LEN(A12)-3))*1 -> 200010 | C12: 45289 | D12: 45289 | E12: =(TEXT(D12, "yyyy"))*1 -> 2023 | F12: =TEXT(D12, "mmmm") -> December | G12: =TEXT(D12, "dddd") -> Friday | H12: C43443 | I12: =(RIGHT(H12, LEN(H12)-1))*1 -> 43443 | J12: Tablet | K12: =TRIM(PROPER(J12)) -> Tablet | L12: 5 | M12: 625.97 | N12: =(TRIM(PROPER(M12)))*1 -> 625.97 | O12: 333 Main St | P12: =LEFT(O12, FIND(" ", O12)-1) -> 333 | Q12: =RIGHT(O12, LEN(O12) - FIND(" ", O12)) -> Main St | R12: Credit Card | S12: =TRIM(PROPER(R12)) -> Credit Card | T12: Returned | U12: =TRIM(PROPER(T12)) -> Returned | V12: TRK98859248 | W12: =RIGHT(V12, LEN(V12)-3) -> 98859248 | X12: 9 | Y12: WINTER15 | Z12: =TRIM(UPPER(IF(Y12="", "NO COUPON", Y12))) -> WINTER15 | AA12: =IF(Z12="NO COUPON","NO","YES") -> YES | AB12: Instagram | AC12: =TRIM(PROPER(AB12)) -> Instagram | AD12: 3129.85 | AE12: 3129.85 | AF12: =N12*L12 -> 3129.85 | AG12: =_xlfn.XLOOKUP(H12, 'Customer Data'!A12,'Customer Data'!B12) -> Customer_12 | AH12: =_xlfn.XLOOKUP(H12,'Customer Data'!A12,'Customer Data'!C12) -> Female | AI12: =_xlfn.XLOOKUP(H12,'Customer Data'!A12,'Customer Data'!D12) -> 21 | AJ12: =_xlfn.XLOOKUP(H12,'Customer Data'!A12,'Customer Data'!E12) -> Kano | AK12: =VLOOKUP(K12,'Product Category'!A:B,2,FALSE) -> Electronics | AL12: =VLOOKUP(Z12,Coupons!A:B,2,FALSE) -> 0.15 | AM12: =AE12*AL12 -> 469.4775 | AN12: =N12*0.7 -> 438.179 | AO12: =AN12*L12 -> 2190.895 | AP12: =AF12-AM12 -> 2660.3725 | AQ12: =AP12-AO12 -> 469.4775 | AR12: =AP12/AO12 -> 1.2142857
A13: ORD200011 | B13: =(RIGHT(A13, LEN(A13)-3))*1 -> 200011 | C13: 45339 | D13: 45339 | E13: =(TEXT(D13, "yyyy"))*1 -> 2024 | F13: =TEXT(D13, "mmmm") -> February | G13: =TEXT(D13, "dddd") -> Saturday | H13: C93861 | I13: =(RIGHT(H13, LEN(H13)-1))*1 -> 93861 | J13: Monitor | K13: =TRIM(PROPER(J13)) -> Monitor | L13: 3 | M13: 49.14 | N13: =(TRIM(PROPER(M13)))*1 -> 49.14 | O13: 831 Main St | P13: =LEFT(O13, FIND(" ", O13)-1) -> 831 | Q13: =RIGHT(O13, LEN(O13) - FIND(" ", O13)) -> Main St | R13: Online | S13: =TRIM(PROPER(R13)) -> Online | T13: Returned | U13: =TRIM(PROPER(T13)) -> Returned | V13: TRK48234646 | W13: =RIGHT(V13, LEN(V13)-3) -> 48234646 | X13: 7 | Y13: SAVE10 | Z13: =TRIM(UPPER(IF(Y13="", "NO COUPON", Y13))) -> SAVE10 | AA13: =IF(Z13="NO COUPON","NO","YES") -> YES | AB13: Email | AC13: =TRIM(PROPER(AB13)) -> Email | AD13: 147.42 | AE13: 147.42 | AF13: =N13*L13 -> 147.42 | AG13: =_xlfn.XLOOKUP(H13, 'Customer Data'!A13,'Customer Data'!B13) -> Customer_13 | AH13: =_xlfn.XLOOKUP(H13,'Customer Data'!A13,'Customer Data'!C13) -> Female | AI13: =_xlfn.XLOOKUP(H13,'Customer Data'!A13,'Customer Data'!D13) -> 19 | AJ13: =_xlfn.XLOOKUP(H13,'Customer Data'!A13,'Customer Data'!E13) -> Lagos | AK13: =VLOOKUP(K13,'Product Category'!A:B,2,FALSE) -> Electronics | AL13: =VLOOKUP(Z13,Coupons!A:B,2,FALSE) -> 0.1 | AM13: =AE13*AL13 -> 14.742 | AN13: =N13*0.7 -> 34.398 | AO13: =AN13*L13 -> 103.194 | AP13: =AF13-AM13 -> 132.678 | AQ13: =AP13-AO13 -> 29.484 | AR13: =AP13/AO13 -> 1.2857143
A14: ORD200012 | B14: =(RIGHT(A14, LEN(A14)-3))*1 -> 200012 | C14: 45580 | D14: 45580 | E14: =(TEXT(D14, "yyyy"))*1 -> 2024 | F14: =TEXT(D14, "mmmm") -> October | G14: =TEXT(D14, "dddd") -> Tuesday | H14: C38785 | I14: =(RIGHT(H14, LEN(H14)-1))*1 -> 38785 | J14: Monitor | K14: =TRIM(PROPER(J14)) -> Monitor | L14: 2 | M14: 180.5 | N14: =(TRIM(PROPER(M14)))*1 -> 180.5 | O14: 179 Main St | P14: =LEFT(O14, FIND(" ", O14)-1) -> 179 | Q14: =RIGHT(O14, LEN(O14) - FIND(" ", O14)) -> Main St | R14: Debit Card | S14: =TRIM(PROPER(R14)) -> Debit Card | T14: Pending | U14: =TRIM(PROPER(T14)) -> Pending | V14: TRK20419991 | W14: =RIGHT(V14, LEN(V14)-3) -> 20419991 | X14: 6 | Y14: FREESHIP | Z14: =TRIM(UPPER(IF(Y14="", "NO COUPON", Y14))) -> FREESHIP | AA14: =IF(Z14="NO COUPON","NO","YES") -> YES | AB14: Referral | AC14: =TRIM(PROPER(AB14)) -> Referral | AD14: 361 | AE14: 361 | AF14: =N14*L14 -> 361 | AG14: =_xlfn.XLOOKUP(H14, 'Customer Data'!A14,'Customer Data'!B14) -> Customer_14 | AH14: =_xlfn.XLOOKUP(H14,'Customer Data'!A14,'Customer Data'!C14) -> Female | AI14: =_xlfn.XLOOKUP(H14,'Customer Data'!A14,'Customer Data'!D14) -> 27 | AJ14: =_xlfn.XLOOKUP(H14,'Customer Data'!A14,'Customer Data'!E14) -> Enugu | AK14: =VLOOKUP(K14,'Product Category'!A:B,2,FALSE) -> Electronics | AL14: =VLOOKUP(Z14,Coupons!A:B,2,FALSE) -> 0 | AM14: =AE14*AL14 -> 0 | AN14: =N14*0.7 -> 126.35 | AO14: =AN14*L14 -> 252.7 | AP14: =AF14-AM14 -> 361 | AQ14: =AP14-AO14 -> 108.3 | AR14: =AP14/AO14 -> 1.4285714
A15: ORD200013 | B15: =(RIGHT(A15, LEN(A15)-3))*1 -> 200013 | C15: 45168 | D15: 45168 | E15: =(TEXT(D15, "yyyy"))*1 -> 2023 | F15: =TEXT(D15, "mmmm") -> August | G15: =TEXT(D15, "dddd") -> Wednesday | H15: C88348 | I15: =(RIGHT(H15, LEN(H15)-1))*1 -> 88348 | J15: Laptop | K15: =TRIM(PROPER(J15)) -> Laptop | L15: 3 | M15: 201.49 | N15: =(TRIM(PROPER(M15)))*1 -> 201.49 | O15: 903 Main St | P15: =LEFT(O15, FIND(" ", O15)-1) -> 903 | Q15: =RIGHT(O15, LEN(O15) - FIND(" ", O15)) -> Main St | R15: Credit Card | S15: =TRIM(PROPER(R15)) -> Credit Card | T15: Returned | U15: =TRIM(PROPER(T15)) -> Returned | V15: TRK81913874 | W15: =RIGHT(V15, LEN(V15)-3) -> 81913874 | X15: 4 | Y15: FREESHIP | Z15: =TRIM(UPPER(IF(Y15="", "NO COUPON", Y15))) -> FREESHIP | AA15: =IF(Z15="NO COUPON","NO","YES") -> YES | AB15: Facebook | AC15: =TRIM(PROPER(AB15)) -> Facebook | AD15: 604.47 | AE15: 604.47 | AF15: =N15*L15 -> 604.47 | AG15: =_xlfn.XLOOKUP(H15, 'Customer Data'!A15,'Customer Data'!B15) -> Customer_15 | AH15: =_xlfn.XLOOKUP(H15,'Customer Data'!A15,'Customer Data'!C15) -> Female | AI15: =_xlfn.XLOOKUP(H15,'Customer Data'!A15,'Customer Data'!D15) -> 40 | AJ15: =_xlfn.XLOOKUP(H15,'Customer Data'!A15,'Customer Data'!E15) -> Enugu | AK15: =VLOOKUP(K15,'Product Category'!A:B,2,FALSE) -> Electronics | AL15: =VLOOKUP(Z15,Coupons!A:B,2,FALSE) -> 0 | AM15: =AE15*AL15 -> 0 | AN15: =N15*0.7 -> 141.043 | AO15: =AN15*L15 -> 423.129 | AP15: =AF15-AM15 -> 604.47 | AQ15: =AP15-AO15 -> 181.341 | AR15: =AP15/AO15 -> 1.4285714
A16: ORD200014 | B16: =(RIGHT(A16, LEN(A16)-3))*1 -> 200014 | C16: 45012 | D16: 45012 | E16: =(TEXT(D16, "yyyy"))*1 -> 2023 | F16: =TEXT(D16, "mmmm") -> March | G16: =TEXT(D16, "dddd") -> Monday | H16: C98474 | I16: =(RIGHT(H16, LEN(H16)-1))*1 -> 98474 | J16: Tablet | K16: =TRIM(PROPER(J16)) -> Tablet | L16: 2 | M16: 393.33 | N16: =(TRIM(PROPER(M16)))*1 -> 393.33 | O16: 980 Main St | P16: =LEFT(O16, FIND(" ", O16)-1) -> 980 | Q16: =RIGHT(O16, LEN(O16) - FIND(" ", O16)) -> Main St | R16: Debit Card | S16: =TRIM(PROPER(R16)) -> Debit Card | T16: Pending | U16: =TRIM(PROPER(T16)) -> Pending | V16: TRK79186539 | W16: =RIGHT(V16, LEN(V16)-3) -> 79186539 | X16: 3 | Y16: SAVE10 | Z16: =TRIM(UPPER(IF(Y16="", "NO COUPON", Y16))) -> SAVE10 | AA16: =IF(Z16="NO COUPON","NO","YES") -> YES | AB16: Instagram | AC16: =TRIM(PROPER(AB16)) -> Instagram | AD16: 786.66 | AE16: 786.66 | AF16: =N16*L16 -> 786.66 | AG16: =_xlfn.XLOOKUP(H16, 'Customer Data'!A16,'Customer Data'!B16) -> Customer_16 | AH16: =_xlfn.XLOOKUP(H16,'Customer Data'!A16,'Customer Data'!C16) -> Male | AI16: =_xlfn.XLOOKUP(H16,'Customer Data'!A16,'Customer Data'!D16) -> 19 | AJ16: =_xlfn.XLOOKUP(H16,'Customer Data'!A16,'Customer Data'!E16) -> Owerri | AK16: =VLOOKUP(K16,'Product Category'!A:B,2,FALSE) -> Electronics | AL16: =VLOOKUP(Z16,Coupons!A:B,2,FALSE) -> 0.1 | AM16: =AE16*AL16 -> 78.666 | AN16: =N16*0.7 -> 275.331 | AO16: =AN16*L16 -> 550.662 | AP16: =AF16-AM16 -> 707.994 | AQ16: =AP16-AO16 -> 157.332 | AR16: =AP16/AO16 -> 1.2857143
A17: ORD200015 | B17: =(RIGHT(A17, LEN(A17)-3))*1 -> 200015 | C17: 45124 | D17: 45124 | E17: =(TEXT(D17, "yyyy"))*1 -> 2023 | F17: =TEXT(D17, "mmmm") -> July | G17: =TEXT(D17, "dddd") -> Monday | H17: C39416 | I17: =(RIGHT(H17, LEN(H17)-1))*1 -> 39416 | J17: Printer | K17: =TRIM(PROPER(J17)) -> Printer | L17: 1 | M17: 473.96 | N17: =(TRIM(PROPER(M17)))*1 -> 473.96 | O17: 942 Main St | P17: =LEFT(O17, FIND(" ", O17)-1) -> 942 | Q17: =RIGHT(O17, LEN(O17) - FIND(" ", O17)) -> Main St | R17: Cash | S17: =TRIM(PROPER(R17)) -> Cash | T17: Delivered | U17: =TRIM(PROPER(T17)) -> Delivered | V17: TRK54930938 | W17: =RIGHT(V17, LEN(V17)-3) -> 54930938 | X17: 3 | Z17: =TRIM(UPPER(IF(Y17="", "NO COUPON", Y17))) -> NO COUPON | AA17: =IF(Z17="NO COUPON","NO","YES") -> NO | AB17: Google | AC17: =TRIM(PROPER(AB17)) -> Google | AD17: 473.96 | AE17: 473.96 | AF17: =N17*L17 -> 473.96 | AG17: =_xlfn.XLOOKUP(H17, 'Customer Data'!A17,'Customer Data'!B17) -> Customer_17 | AH17: =_xlfn.XLOOKUP(H17,'Customer Data'!A17,'Customer Data'!C17) -> Female | AI17: =_xlfn.XLOOKUP(H17,'Customer Data'!A17,'Customer Data'!D17) -> 38 | AJ17: =_xlfn.XLOOKUP(H17,'Customer Data'!A17,'Customer Data'!E17) -> Kano | AK17: =VLOOKUP(K17,'Product Category'!A:B,2,FALSE) -> Electronics | AL17: =VLOOKUP(Z17,Coupons!A:B,2,FALSE) -> 0 | AM17: =AE17*AL17 -> 0 | AN17: =N17*0.7 -> 331.772 | AO17: =AN17*L17 -> 331.772 | AP17: =AF17-AM17 -> 473.96 | AQ17: =AP17-AO17 -> 142.188 | AR17: =AP17/AO17 -> 1.4285714
A18: ORD200016 | B18: =(RIGHT(A18, LEN(A18)-3))*1 -> 200016 | C18: 44950 | D18: 44950 | E18: =(TEXT(D18, "yyyy"))*1 -> 2023 | F18: =TEXT(D18, "mmmm") -> January | G18: =TEXT(D18, "dddd") -> Tuesday | H18: C28976 | I18: =(RIGHT(H18, LEN(H18)-1))*1 -> 28976 | J18: Printer | K18: =TRIM(PROPER(J18)) -> Printer | L18: 2 | M18: 533.81 | N18: =(TRIM(PROPER(M18)))*1 -> 533.81 | O18: 914 Main St | P18: =LEFT(O18, FIND(" ", O18)-1) -> 914 | Q18: =RIGHT(O18, LEN(O18) - FIND(" ", O18)) -> Main St | R18: Credit Card | S18: =TRIM(PROPER(R18)) -> Credit Card | T18: Pending | U18: =TRIM(PROPER(T18)) -> Pending | V18: TRK13194259 | W18: =RIGHT(V18, LEN(V18)-3) -> 13194259 | X18: 3 | Y18: FREESHIP | Z18: =TRIM(UPPER(IF(Y18="", "NO COUPON", Y18))) -> FREESHIP | AA18: =IF(Z18="NO COUPON","NO","YES") -> YES | AB18: Email | AC18: =TRIM(PROPER(AB18)) -> Email | AD18: 1067.62 | AE18: 1067.62 | AF18: =N18*L18 -> 1067.62 | AG18: =_xlfn.XLOOKUP(H18, 'Customer Data'!A18,'Customer Data'!B18) -> Customer_18 | AH18: =_xlfn.XLOOKUP(H18,'Customer Data'!A18,'Customer Data'!C18) -> Male | AI18: =_xlfn.XLOOKUP(H18,'Customer Data'!A18,'Customer Data'!D18) -> 51 | AJ18: =_xlfn.XLOOKUP(H18,'Customer Data'!A18,'Customer Data'!E18) -> Owerri | AK18: =VLOOKUP(K18,'Product Category'!A:B,2,FALSE) -> Electronics | AL18: =VLOOKUP(Z18,Coupons!A:B,2,FALSE) -> 0 | AM18: =AE18*AL18 -> 0 | AN18: =N18*0.7 -> 373.667 | AO18: =AN18*L18 -> 747.334 | AP18: =AF18-AM18 -> 1067.62 | AQ18: =AP18-AO18 -> 320.286 | AR18: =AP18/AO18 -> 1.4285714
A19: ORD200017 | B19: =(RIGHT(A19, LEN(A19)-3))*1 -> 200017 | C19: 45353 | D19: 45353 | E19: =(TEXT(D19, "yyyy"))*1 -> 2024 | F19: =TEXT(D19, "mmmm") -> March | G19: =TEXT(D19, "dddd") -> Saturday | H19: C60672 | I19: =(RIGHT(H19, LEN(H19)-1))*1 -> 60672 | J19: Tablet | K19: =TRIM(PROPER(J19)) -> Tablet | L19: 1 | M19: 423.4 | N19: =(TRIM(PROPER(M19)))*1 -> 423.4 | O19: 382 Main St | P19: =LEFT(O19, FIND(" ", O19)-1) -> 382 | Q19: =RIGHT(O19, LEN(O19) - FIND(" ", O19)) -> Main St | R19: Debit Card | S19: =TRIM(PROPER(R19)) -> Debit Card | T19: Shipped | U19: =TRIM(PROPER(T19)) -> Shipped | V19: TRK11972116 | W19: =RIGHT(V19, LEN(V19)-3) -> 11972116 | X19: 3 | Z19: =TRIM(UPPER(IF(Y19="", "NO COUPON", Y19))) -> NO COUPON | AA19: =IF(Z19="NO COUPON","NO","YES") -> NO | AB19: Referral | AC19: =TRIM(PROPER(AB19)) -> Referral | AD19: 423.4 | AE19: 423.4 | AF19: =N19*L19 -> 423.4 | AG19: =_xlfn.XLOOKUP(H19, 'Customer Data'!A19,'Customer Data'!B19) -> Customer_19 | AH19: =_xlfn.XLOOKUP(H19,'Customer Data'!A19,'Customer Data'!C19) -> Male | AI19: =_xlfn.XLOOKUP(H19,'Customer Data'!A19,'Customer Data'!D19) -> 37 | AJ19: =_xlfn.XLOOKUP(H19,'Customer Data'!A19,'Customer Data'!E19) -> Owerri | AK19: =VLOOKUP(K19,'Product Category'!A:B,2,FALSE) -> Electronics | AL19: =VLOOKUP(Z19,Coupons!A:B,2,FALSE) -> 0 | AM19: =AE19*AL19 -> 0 | AN19: =N19*0.7 -> 296.38 | AO19: =AN19*L19 -> 296.38 | AP19: =AF19-AM19 -> 423.4 | AQ19: =AP19-AO19 -> 127.02 | AR19: =AP19/AO19 -> 1.4285714
A20: ORD200018 | B20: =(RIGHT(A20, LEN(A20)-3))*1 -> 200018 | C20: 45742 | D20: 45742 | E20: =(TEXT(D20, "yyyy"))*1 -> 2025 | F20: =TEXT(D20, "mmmm") -> March | G20: =TEXT(D20, "dddd") -> Wednesday | H20: C84329 | I20: =(RIGHT(H20, LEN(H20)-1))*1 -> 84329 | J20: Desk | K20: =TRIM(PROPER(J20)) -> Desk | L20: 1 | M20: 431.44 | N20: =(TRIM(PROPER(M20)))*1 -> 431.44 | O20: 891 Main St | P20: =LEFT(O20, FIND(" ", O20)-1) -> 891 | Q20: =RIGHT(O20, LEN(O20) - FIND(" ", O20)) -> Main St | R20: Gift Card | S20: =TRIM(PROPER(R20)) -> Gift Card | T20: Pending | U20: =TRIM(PROPER(T20)) -> Pending | V20: TRK65191045 | W20: =RIGHT(V20, LEN(V20)-3) -> 65191045 | X20: 3 | Y20: SAVE10 | Z20: =TRIM(UPPER(IF(Y20="", "NO COUPON", Y20))) -> SAVE10 | AA20: =IF(Z20="NO COUPON","NO","YES") -> YES | AB20: Facebook | AC20: =TRIM(PROPER(AB20)) -> Facebook | AD20: 431.44 | AE20: 431.44 | AF20: =N20*L20 -> 431.44 | AG20: =_xlfn.XLOOKUP(H20, 'Customer Data'!A20,'Customer Data'!B20) -> Customer_20 | AH20: =_xlfn.XLOOKUP(H20,'Customer Data'!A20,'Customer Data'!C20) -> Female | AI20: =_xlfn.XLOOKUP(H20,'Customer Data'!A20,'Customer Data'!D20) -> 25 | AJ20: =_xlfn.XLOOKUP(H20,'Customer Data'!A20,'Customer Data'!E20) -> Owerri | AK20: =VLOOKUP(K20,'Product Category'!A:B,2,FALSE) -> Furniture | AL20: =VLOOKUP(Z20,Coupons!A:B,2,FALSE) -> 0.1 | AM20: =AE20*AL20 -> 43.144 | AN20: =N20*0.7 -> 302.008 | AO20: =AN20*L20 -> 302.008 | AP20: =AF20-AM20 -> 388.296 | AQ20: =AP20-AO20 -> 86.288 | AR20: =AP20/AO20 -> 1.2857143
A21: ORD200019 | B21: =(RIGHT(A21, LEN(A21)-3))*1 -> 200019 | C21: 44949 | D21: 44949 | E21: =(TEXT(D21, "yyyy"))*1 -> 2023 | F21: =TEXT(D21, "mmmm") -> January | G21: =TEXT(D21, "dddd") -> Monday | H21: C14552 | I21: =(RIGHT(H21, LEN(H21)-1))*1 -> 14552 | J21: Monitor | K21: =TRIM(PROPER(J21)) -> Monitor | L21: 5 | M21: 224 | N21: =(TRIM(PROPER(M21)))*1 -> 224 | O21: 273 Main St | P21: =LEFT(O21, FIND(" ", O21)-1) -> 273 | Q21: =RIGHT(O21, LEN(O21) - FIND(" ", O21)) -> Main St | R21: Cash | S21: =TRIM(PROPER(R21)) -> Cash | T21: Returned | U21: =TRIM(PROPER(T21)) -> Returned | V21: TRK59101365 | W21: =RIGHT(V21, LEN(V21)-3) -> 59101365 | X21: 9 | Y21: SAVE10 | Z21: =TRIM(UPPER(IF(Y21="", "NO COUPON", Y21))) -> SAVE10 | AA21: =IF(Z21="NO COUPON","NO","YES") -> YES | AB21: Google | AC21: =TRIM(PROPER(AB21)) -> Google | AD21: 1120 | AE21: 1120 | AF21: =N21*L21 -> 1120 | AG21: =_xlfn.XLOOKUP(H21, 'Customer Data'!A21,'Customer Data'!B21) -> Customer_21 | AH21: =_xlfn.XLOOKUP(H21,'Customer Data'!A21,'Customer Data'!C21) -> Female | AI21: =_xlfn.XLOOKUP(H21,'Customer Data'!A21,'Customer Data'!D21) -> 57 | AJ21: =_xlfn.XLOOKUP(H21,'Customer Data'!A21,'Customer Data'!E21) -> Abuja | AK21: =VLOOKUP(K21,'Product Category'!A:B,2,FALSE) -> Electronics | AL21: =VLOOKUP(Z21,Coupons!A:B,2,FALSE) -> 0.1 | AM21: =AE21*AL21 -> 112 | AN21: =N21*0.7 -> 156.8 | AO21: =AN21*L21 -> 784 | AP21: =AF21-AM21 -> 1008 | AQ21: =AP21-AO21 -> 224 | AR21: =AP21/AO21 -> 1.2857143
A22: ORD200020 | B22: =(RIGHT(A22, LEN(A22)-3))*1 -> 200020 | C22: 45054 | D22: 45054 | E22: =(TEXT(D22, "yyyy"))*1 -> 2023 | F22: =TEXT(D22, "mmmm") -> May | G22: =TEXT(D22, "dddd") -> Monday | H22: C54829 | I22: =(RIGHT(H22, LEN(H22)-1))*1 -> 54829 | J22: Chair | K22: =TRIM(PROPER(J22)) -> Chair | L22: 5 | M22: 62.51 | N22: =(TRIM(PROPER(M22)))*1 -> 62.51 | O22: 587 Main St | P22: =LEFT(O22, FIND(" ", O22)-1) -> 587 | Q22: =RIGHT(O22, LEN(O22) - FIND(" ", O22)) -> Main St | R22: Cash | S22: =TRIM(PROPER(R22)) -> Cash | T22: Pending | U22: =TRIM(PROPER(T22)) -> Pending | V22: TRK16718651 | W22: =RIGHT(V22, LEN(V22)-3) -> 16718651 | X22: 9 | Y22: WINTER15 | Z22: =TRIM(UPPER(IF(Y22="", "NO COUPON", Y22))) -> WINTER15 | AA22: =IF(Z22="NO COUPON","NO","YES") -> YES | AB22: Instagram | AC22: =TRIM(PROPER(AB22)) -> Instagram | AD22: 312.55 | AE22: 312.55 | AF22: =N22*L22 -> 312.55 | AG22: =_xlfn.XLOOKUP(H22, 'Customer Data'!A22,'Customer Data'!B22) -> Customer_22 | AH22: =_xlfn.XLOOKUP(H22,'Customer Data'!A22,'Customer Data'!C22) -> Female | AI22: =_xlfn.XLOOKUP(H22,'Customer Data'!A22,'Customer Data'!D22) -> 30 | AJ22: =_xlfn.XLOOKUP(H22,'Customer Data'!A22,'Customer Data'!E22) -> Owerri | AK22: =VLOOKUP(K22,'Product Category'!A:B,2,FALSE) -> Furniture | AL22: =VLOOKUP(Z22,Coupons!A:B,2,FALSE) -> 0.15 | AM22: =AE22*AL22 -> 46.8825 | AN22: =N22*0.7 -> 43.757 | AO22: =AN22*L22 -> 218.785 | AP22: =AF22-AM22 -> 265.6675 | AQ22: =AP22-AO22 -> 46.8825 | AR22: =AP22/AO22 -> 1.2142857
A23: ORD200021 | B23: =(RIGHT(A23, LEN(A23)-3))*1 -> 200021 | C23: 45613 | D23: 45613 | E23: =(TEXT(D23, "yyyy"))*1 -> 2024 | F23: =TEXT(D23, "mmmm") -> November | G23: =TEXT(D23, "dddd") -> Sunday | H23: C99023 | I23: =(RIGHT(H23, LEN(H23)-1))*1 -> 99023 | J23: Monitor | K23: =TRIM(PROPER(J23)) -> Monitor | L23: 4 | M23: 342.95 | N23: =(TRIM(PROPER(M23)))*1 -> 342.95 | O23: 569 Main St | P23: =LEFT(O23, FIND(" ", O23)-1) -> 569 | Q23: =RIGHT(O23, LEN(O23) - FIND(" ", O23)) -> Main St | R23: Cash | S23: =TRIM(PROPER(R23)) -> Cash | T23: Delivered | U23: =TRIM(PROPER(T23)) -> Delivered | V23: TRK52646983 | W23: =RIGHT(V23, LEN(V23)-3) -> 52646983 | X23: 6 | Z23: =TRIM(UPPER(IF(Y23="", "NO COUPON", Y23))) -> NO COUPON | AA23: =IF(Z23="NO COUPON","NO","YES") -> NO | AB23: Google | AC23: =TRIM(PROPER(AB23)) -> Google | AD23: 1371.8 | AE23: 1371.8 | AF23: =N23*L23 -> 1371.8 | AG23: =_xlfn.XLOOKUP(H23, 'Customer Data'!A23,'Customer Data'!B23) -> Customer_23 | AH23: =_xlfn.XLOOKUP(H23,'Customer Data'!A23,'Customer Data'!C23) -> Male | AI23: =_xlfn.XLOOKUP(H23,'Customer Data'!A23,'Customer Data'!D23) -> 57 | AJ23: =_xlfn.XLOOKUP(H23,'Customer Data'!A23,'Customer Data'!E23) -> Enugu | AK23: =VLOOKUP(K23,'Product Category'!A:B,2,FALSE) -> Electronics | AL23: =VLOOKUP(Z23,Coupons!A:B,2,FALSE) -> 0 | AM23: =AE23*AL23 -> 0 | AN23: =N23*0.7 -> 240.065 | AO23: =AN23*L23 -> 960.26 | AP23: =AF23-AM23 -> 1371.8 | AQ23: =AP23-AO23 -> 411.54 | AR23: =AP23/AO23 -> 1.4285714
A24: ORD200022 | B24: =(RIGHT(A24, LEN(A24)-3))*1 -> 200022 | C24: 44955 | D24: 44955 | E24: =(TEXT(D24, "yyyy"))*1 -> 2023 | F24: =TEXT(D24, "mmmm") -> January | G24: =TEXT(D24, "dddd") -> Sunday | H24: C34416 | I24: =(RIGHT(H24, LEN(H24)-1))*1 -> 34416 | J24: Monitor | K24: =TRIM(PROPER(J24)) -> Monitor | L24: 2 | M24: 49.62 | N24: =(TRIM(PROPER(M24)))*1 -> 49.62 | O24: 633 Main St | P24: =LEFT(O24, FIND(" ", O24)-1) -> 633 | Q24: =RIGHT(O24, LEN(O24) - FIND(" ", O24)) -> Main St | R24: Online | S24: =TRIM(PROPER(R24)) -> Online | T24: Pending | U24: =TRIM(PROPER(T24)) -> Pending | V24: TRK75937350 | W24: =RIGHT(V24, LEN(V24)-3) -> 75937350 | X24: 2 | Y24: SAVE10 | Z24: =TRIM(UPPER(IF(Y24="", "NO COUPON", Y24))) -> SAVE10 | AA24: =IF(Z24="NO COUPON","NO","YES") -> YES | AB24: Google | AC24: =TRIM(PROPER(AB24)) -> Google | AD24: 99.24 | AE24: 99.24 | AF24: =N24*L24 -> 99.24 | AG24: =_xlfn.XLOOKUP(H24, 'Customer Data'!A24,'Customer Data'!B24) -> Customer_24 | AH24: =_xlfn.XLOOKUP(H24,'Customer Data'!A24,'Customer Data'!C24) -> Male | AI24: =_xlfn.XLOOKUP(H24,'Customer Data'!A24,'Customer Data'!D24) -> 38 | AJ24: =_xlfn.XLOOKUP(H24,'Customer Data'!A24,'Customer Data'!E24) -> Enugu | AK24: =VLOOKUP(K24,'Product Category'!A:B,2,FALSE) -> Electronics | AL24: =VLOOKUP(Z24,Coupons!A:B,2,FALSE) -> 0.1 | AM24: =AE24*AL24 -> 9.924 | AN24: =N24*0.7 -> 34.734 | AO24: =AN24*L24 -> 69.468 | AP24: =AF24-AM24 -> 89.316 | AQ24: =AP24-AO24 -> 19.848 | AR24: =AP24/AO24 -> 1.2857143
A25: ORD200023 | B25: =(RIGHT(A25, LEN(A25)-3))*1 -> 200023 | C25: 45756 | D25: 45756 | E25: =(TEXT(D25, "yyyy"))*1 -> 2025 | F25: =TEXT(D25, "mmmm") -> April | G25: =TEXT(D25, "dddd") -> Wednesday | H25: C42372 | I25: =(RIGHT(H25, LEN(H25)-1))*1 -> 42372 | J25: Phone | K25: =TRIM(PROPER(J25)) -> Phone | L25: 4 | M25: 273.25 | N25: =(TRIM(PROPER(M25)))*1 -> 273.25 | O25: 755 Main St | P25: =LEFT(O25, FIND(" ", O25)-1) -> 755 | Q25: =RIGHT(O25, LEN(O25) - FIND(" ", O25)) -> Main St | R25: Debit Card | S25: =TRIM(PROPER(R25)) -> Debit Card | T25: Cancelled | U25: =TRIM(PROPER(T25)) -> Cancelled | V25: TRK36168083 | W25: =RIGHT(V25, LEN(V25)-3) -> 36168083 | X25: 5 | Y25: FREESHIP | Z25: =TRIM(UPPER(IF(Y25="", "NO COUPON", Y25))) -> FREESHIP | AA25: =IF(Z25="NO COUPON","NO","YES") -> YES | AB25: Referral | AC25: =TRIM(PROPER(AB25)) -> Referral | AD25: 1093 | AE25: 1093 | AF25: =N25*L25 -> 1093 | AG25: =_xlfn.XLOOKUP(H25, 'Customer Data'!A25,'Customer Data'!B25) -> Customer_25 | AH25: =_xlfn.XLOOKUP(H25,'Customer Data'!A25,'Customer Data'!C25) -> Male | AI25: =_xlfn.XLOOKUP(H25,'Customer Data'!A25,'Customer Data'!D25) -> 39 | AJ25: =_xlfn.XLOOKUP(H25,'Customer Data'!A25,'Customer Data'!E25) -> Abuja | AK25: =VLOOKUP(K25,'Product Category'!A:B,2,FALSE) -> Electronics | AL25: =VLOOKUP(Z25,Coupons!A:B,2,FALSE) -> 0 | AM25: =AE25*AL25 -> 0 | AN25: =N25*0.7 -> 191.275 | AO25: =AN25*L25 -> 765.1 | AP25: =AF25-AM25 -> 1093 | AQ25: =AP25-AO25 -> 327.9 | AR25: =AP25/AO25 -> 1.4285714
A26: ORD200024 | B26: =(RIGHT(A26, LEN(A26)-3))*1 -> 200024 | C26: 45595 | D26: 45595 | E26: =(TEXT(D26, "yyyy"))*1 -> 2024 | F26: =TEXT(D26, "mmmm") -> October | G26: =TEXT(D26, "dddd") -> Wednesday | H26: C17470 | I26: =(RIGHT(H26, LEN(H26)-1))*1 -> 17470 | J26: Laptop | K26: =TRIM(PROPER(J26)) -> Laptop | L26: 2 | M26: 230.95 | N26: =(TRIM(PROPER(M26)))*1 -> 230.95 | O26: 956 Main St | P26: =LEFT(O26, FIND(" ", O26)-1) -> 956 | Q26: =RIGHT(O26, LEN(O26) - FIND(" ", O26)) -> Main St | R26: Online | S26: =TRIM(PROPER(R26)) -> Online | T26: Delivered | U26: =TRIM(PROPER(T26)) -> Delivered | V26: TRK28775057 | W26: =RIGHT(V26, LEN(V26)-3) -> 28775057 | X26: 3 | Y26: WINTER15 | Z26: =TRIM(UPPER(IF(Y26="", "NO COUPON", Y26))) -> WINTER15 | AA26: =IF(Z26="NO COUPON","NO","YES") -> YES | AB26: Referral | AC26: =TRIM(PROPER(AB26)) -> Referral | AD26: 461.9 | AE26: 461.9 | AF26: =N26*L26 -> 461.9 | AG26: =_xlfn.XLOOKUP(H26, 'Customer Data'!A26,'Customer Data'!B26) -> Customer_26 | AH26: =_xlfn.XLOOKUP(H26,'Customer Data'!A26,'Customer Data'!C26) -> Male | AI26: =_xlfn.XLOOKUP(H26,'Customer Data'!A26,'Customer Data'!D26) -> 51 | AJ26: =_xlfn.XLOOKUP(H26,'Customer Data'!A26,'Customer Data'!E26) -> Kano | AK26: =VLOOKUP(K26,'Product Category'!A:B,2,FALSE) -> Electronics | AL26: =VLOOKUP(Z26,Coupons!A:B,2,FALSE) -> 0.15 | AM26: =AE26*AL26 -> 69.285 | AN26: =N26*0.7 -> 161.665 | AO26: =AN26*L26 -> 323.33 | AP26: =AF26-AM26 -> 392.615 | AQ26: =AP26-AO26 -> 69.285 | AR26: =AP26/AO26 -> 1.2142857
A27: ORD200025 | B27: =(RIGHT(A27, LEN(A27)-3))*1 -> 200025 | C27: 45497 | D27: 45497 | E27: =(TEXT(D27, "yyyy"))*1 -> 2024 | F27: =TEXT(D27, "mmmm") -> July | G27: =TEXT(D27, "dddd") -> Wednesday | H27: C42577 | I27: =(RIGHT(H27, LEN(H27)-1))*1 -> 42577 | J27: Monitor | K27: =TRIM(PROPER(J27)) -> Monitor | L27: 1 | M27: 399.98 | N27: =(TRIM(PROPER(M27)))*1 -> 399.98 | O27: 709 Main St | P27: =LEFT(O27, FIND(" ", O27)-1) -> 709 | Q27: =RIGHT(O27, LEN(O27) - FIND(" ", O27)) -> Main St | R27: Debit Card | S27: =TRIM(PROPER(R27)) -> Debit Card | T27: Delivered | U27: =TRIM(PROPER(T27)) -> Delivered | V27: TRK69423327 | W27: =RIGHT(V27, LEN(V27)-3) -> 69423327 | X27: 3 | Y27: WINTER15 | Z27: =TRIM(UPPER(IF(Y27="", "NO COUPON", Y27))) -> WINTER15 | AA27: =IF(Z27="NO COUPON","NO","YES") -> YES | AB27: Email | AC27: =TRIM(PROPER(AB27)) -> Email | AD27: 399.98 | AE27: 399.98 | AF27: =N27*L27 -> 399.98 | AG27: =_xlfn.XLOOKUP(H27, 'Customer Data'!A27,'Customer Data'!B27) -> Customer_27 | AH27: =_xlfn.XLOOKUP(H27,'Customer Data'!A27,'Customer Data'!C27) -> Female | AI27: =_xlfn.XLOOKUP(H27,'Customer Data'!A27,'Customer Data'!D27) -> 41 | AJ27: =_xlfn.XLOOKUP(H27,'Customer Data'!A27,'Customer Data'!E27) -> Port-Harcourt | AK27: =VLOOKUP(K27,'Product Category'!A:B,2,FALSE) -> Electronics | AL27: =VLOOKUP(Z27,Coupons!A:B,2,FALSE) -> 0.15 | AM27: =AE27*AL27 -> 59.997 | AN27: =N27*0.7 -> 279.986 | AO27: =AN27*L27 -> 279.986 | AP27: =AF27-AM27 -> 339.983 | AQ27: =AP27-AO27 -> 59.997 | AR27: =AP27/AO27 -> 1.2142857
A28: ORD200026 | B28: =(RIGHT(A28, LEN(A28)-3))*1 -> 200026 | C28: 45357 | D28: 45357 | E28: =(TEXT(D28, "yyyy"))*1 -> 2024 | F28: =TEXT(D28, "mmmm") -> March | G28: =TEXT(D28, "dddd") -> Wednesday | H28: C21944 | I28: =(RIGHT(H28, LEN(H28)-1))*1 -> 21944 | J28: Laptop | K28: =TRIM(PROPER(J28)) -> Laptop | L28: 5 | M28: 59.55 | N28: =(TRIM(PROPER(M28)))*1 -> 59.55 | O28: 296 Main St | P28: =LEFT(O28, FIND(" ", O28)-1) -> 296 | Q28: =RIGHT(O28, LEN(O28) - FIND(" ", O28)) -> Main St | R28: Online | S28: =TRIM(PROPER(R28)) -> Online | T28: Delivered | U28: =TRIM(PROPER(T28)) -> Delivered | V28: TRK80276812 | W28: =RIGHT(V28, LEN(V28)-3) -> 80276812 | X28: 6 | Z28: =TRIM(UPPER(IF(Y28="", "NO COUPON", Y28))) -> NO COUPON | AA28: =IF(Z28="NO COUPON","NO","YES") -> NO | AB28: Referral | AC28: =TRIM(PROPER(AB28)) -> Referral | AD28: 297.75 | AE28: 297.75 | AF28: =N28*L28 -> 297.75 | AG28: =_xlfn.XLOOKUP(H28, 'Customer Data'!A28,'Customer Data'!B28) -> Customer_28 | AH28: =_xlfn.XLOOKUP(H28,'Customer Data'!A28,'Customer Data'!C28) -> Female | AI28: =_xlfn.XLOOKUP(H28,'Customer Data'!A28,'Customer Data'!D28) -> 53 | AJ28: =_xlfn.XLOOKUP(H28,'Customer Data'!A28,'Customer Data'!E28) -> Abuja | AK28: =VLOOKUP(K28,'Product Category'!A:B,2,FALSE) -> Electronics | AL28: =VLOOKUP(Z28,Coupons!A:B,2,FALSE) -> 0 | AM28: =AE28*AL28 -> 0 | AN28: =N28*0.7 -> 41.685 | AO28: =AN28*L28 -> 208.425 | AP28: =AF28-AM28 -> 297.75 | AQ28: =AP28-AO28 -> 89.325 | AR28: =AP28/AO28 -> 1.4285714
A29: ORD200027 | B29: =(RIGHT(A29, LEN(A29)-3))*1 -> 200027 | C29: 45344 | D29: 45344 | E29: =(TEXT(D29, "yyyy"))*1 -> 2024 | F29: =TEXT(D29, "mmmm") -> February | G29: =TEXT(D29, "dddd") -> Thursday | H29: C97593 | I29: =(RIGHT(H29, LEN(H29)-1))*1 -> 97593 | J29: Printer | K29: =TRIM(PROPER(J29)) -> Printer | L29: 1 | M29: 472.74 | N29: =(TRIM(PROPER(M29)))*1 -> 472.74 | O29: 881 Main St | P29: =LEFT(O29, FIND(" ", O29)-1) -> 881 | Q29: =RIGHT(O29, LEN(O29) - FIND(" ", O29)) -> Main St | R29: Online | S29: =TRIM(PROPER(R29)) -> Online | T29: Shipped | U29: =TRIM(PROPER(T29)) -> Shipped | V29: TRK89117573 | W29: =RIGHT(V29, LEN(V29)-3) -> 89117573 | X29: 6 | Y29: WINTER15 | Z29: =TRIM(UPPER(IF(Y29="", "NO COUPON", Y29))) -> WINTER15 | AA29: =IF(Z29="NO COUPON","NO","YES") -> YES | AB29: Google | AC29: =TRIM(PROPER(AB29)) -> Google | AD29: 472.74 | AE29: 472.74 | AF29: =N29*L29 -> 472.74 | AG29: =_xlfn.XLOOKUP(H29, 'Customer Data'!A29,'Customer Data'!B29) -> Customer_29 | AH29: =_xlfn.XLOOKUP(H29,'Customer Data'!A29,'Customer Data'!C29) -> Female | AI29: =_xlfn.XLOOKUP(H29,'Customer Data'!A29,'Customer Data'!D29) -> 23 | AJ29: =_xlfn.XLOOKUP(H29,'Customer Data'!A29,'Customer Data'!E29) -> Port-Harcourt | AK29: =VLOOKUP(K29,'Product Category'!A:B,2,FALSE) -> Electronics | AL29: =VLOOKUP(Z29,Coupons!A:B,2,FALSE) -> 0.15 | AM29: =AE29*AL29 -> 70.911 | AN29: =N29*0.7 -> 330.918 | AO29: =AN29*L29 -> 330.918 | AP29: =AF29-AM29 -> 401.829 | AQ29: =AP29-AO29 -> 70.911 | AR29: =AP29/AO29 -> 1.2142857
A30: ORD200028 | B30: =(RIGHT(A30, LEN(A30)-3))*1 -> 200028 | C30: 45251 | D30: 45251 | E30: =(TEXT(D30, "yyyy"))*1 -> 2023 | F30: =TEXT(D30, "mmmm") -> November | G30: =TEXT(D30, "dddd") -> Tuesday | H30: C59823 | I30: =(RIGHT(H30, LEN(H30)-1))*1 -> 59823 | J30: Phone | K30: =TRIM(PROPER(J30)) -> Phone | L30: 4 | M30: 160.07 | N30: =(TRIM(PROPER(M30)))*1 -> 160.07 | O30: 568 Main St | P30: =LEFT(O30, FIND(" ", O30)-1) -> 568 | Q30: =RIGHT(O30, LEN(O30) - FIND(" ", O30)) -> Main St | R30: Online | S30: =TRIM(PROPER(R30)) -> Online | T30: Pending | U30: =TRIM(PROPER(T30)) -> Pending | V30: TRK65895539 | W30: =RIGHT(V30, LEN(V30)-3) -> 65895539 | X30: 5 | Z30: =TRIM(UPPER(IF(Y30="", "NO COUPON", Y30))) -> NO COUPON | AA30: =IF(Z30="NO COUPON","NO","YES") -> NO | AB30: Email | AC30: =TRIM(PROPER(AB30)) -> Email | AD30: 640.28 | AE30: 640.28 | AF30: =N30*L30 -> 640.28 | AG30: =_xlfn.XLOOKUP(H30, 'Customer Data'!A30,'Customer Data'!B30) -> Customer_30 | AH30: =_xlfn.XLOOKUP(H30,'Customer Data'!A30,'Customer Data'!C30) -> Female | AI30: =_xlfn.XLOOKUP(H30,'Customer Data'!A30,'Customer Data'!D30) -> 49 | AJ30: =_xlfn.XLOOKUP(H30,'Customer Data'!A30,'Customer Data'!E30) -> Abuja | AK30: =VLOOKUP(K30,'Product Category'!A:B,2,FALSE) -> Electronics | AL30: =VLOOKUP(Z30,Coupons!A:B,2,FALSE) -> 0 | AM30: =AE30*AL30 -> 0 | AN30: =N30*0.7 -> 112.049 | AO30: =AN30*L30 -> 448.196 | AP30: =AF30-AM30 -> 640.28 | AQ30: =AP30-AO30 -> 192.084 | AR30: =AP30/AO30 -> 1.4285714
A31: ORD200029 | B31: =(RIGHT(A31, LEN(A31)-3))*1 -> 200029 | C31: 45555 | D31: 45555 | E31: =(TEXT(D31, "yyyy"))*1 -> 2024 | F31: =TEXT(D31, "mmmm") -> September | G31: =TEXT(D31, "dddd") -> Friday | H31: C33260 | I31: =(RIGHT(H31, LEN(H31)-1))*1 -> 33260 | J31: Desk | K31: =TRIM(PROPER(J31)) -> Desk | L31: 3 | M31: 423.53 | N31: =(TRIM(PROPER(M31)))*1 -> 423.53 | O31: 930 Main St | P31: =LEFT(O31, FIND(" ", O31)-1) -> 930 | Q31: =RIGHT(O31, LEN(O31) - FIND(" ", O31)) -> Main St | R31: Credit Card | S31: =TRIM(PROPER(R31)) -> Credit Card | T31: Delivered | U31: =TRIM(PROPER(T31)) -> Delivered | V31: TRK59744090 | W31: =RIGHT(V31, LEN(V31)-3) -> 59744090 | X31: 6 | Y31: SAVE10 | Z31: =TRIM(UPPER(IF(Y31="", "NO COUPON", Y31))) -> SAVE10 | AA31: =IF(Z31="NO COUPON","NO","YES") -> YES | AB31: Referral | AC31: =TRIM(PROPER(AB31)) -> Referral | AD31: 1270.59 | AE31: 1270.59 | AF31: =N31*L31 -> 1270.59 | AG31: =_xlfn.XLOOKUP(H31, 'Customer Data'!A31,'Customer Data'!B31) -> Customer_31 | AH31: =_xlfn.XLOOKUP(H31,'Customer Data'!A31,'Customer Data'!C31) -> Male | AI31: =_xlfn.XLOOKUP(H31,'Customer Data'!A31,'Customer Data'!D31) -> 52 | AJ31: =_xlfn.XLOOKUP(H31,'Customer Data'!A31,'Customer Data'!E31) -> Lagos | AK31: =VLOOKUP(K31,'Product Category'!A:B,2,FALSE) -> Furniture | AL31: =VLOOKUP(Z31,Coupons!A:B,2,FALSE) -> 0.1 | AM31: =AE31*AL31 -> 127.059 | AN31: =N31*0.7 -> 296.471 | AO31: =AN31*L31 -> 889.413 | AP31: =AF31-AM31 -> 1143.531 | AQ31: =AP31-AO31 -> 254.118 | AR31: =AP31/AO31 -> 1.2857143
A32: ORD200030 | B32: =(RIGHT(A32, LEN(A32)-3))*1 -> 200030 | C32: 45738 | D32: 45738 | E32: =(TEXT(D32, "yyyy"))*1 -> 2025 | F32: =TEXT(D32, "mmmm") -> March | G32: =TEXT(D32, "dddd") -> Saturday | H32: C44267 | I32: =(RIGHT(H32, LEN(H32)-1))*1 -> 44267 | J32: Monitor | K32: =TRIM(PROPER(J32)) -> Monitor | L32: 2 | M32: 426.7 | N32: =(TRIM(PROPER(M32)))*1 -> 426.7 | O32: 895 Main St | P32: =LEFT(O32, FIND(" ", O32)-1) -> 895 | Q32: =RIGHT(O32, LEN(O32) - FIND(" ", O32)) -> Main St | R32: Online | S32: =TRIM(PROPER(R32)) -> Online | T32: Pending | U32: =TRIM(PROPER(T32)) -> Pending | V32: TRK54751444 | W32: =RIGHT(V32, LEN(V32)-3) -> 54751444 | X32: 5 | Y32: SAVE10 | Z32: =TRIM(UPPER(IF(Y32="", "NO COUPON", Y32))) -> SAVE10 | AA32: =IF(Z32="NO COUPON","NO","YES") -> YES | AB32: Referral | AC32: =TRIM(PROPER(AB32)) -> Referral | AD32: 853.4 | AE32: 853.4 | AF32: =N32*L32 -> 853.4 | AG32: =_xlfn.XLOOKUP(H32, 'Customer Data'!A32,'Customer Data'!B32) -> Customer_32 | AH32: =_xlfn.XLOOKUP(H32,'Customer Data'!A32,'Customer Data'!C32) -> Male | AI32: =_xlfn.XLOOKUP(H32,'Customer Data'!A32,'Customer Data'!D32) -> 52 | AJ32: =_xlfn.XLOOKUP(H32,'Customer Data'!A32,'Customer Data'!E32) -> Lagos | AK32: =VLOOKUP(K32,'Product Category'!A:B,2,FALSE) -> Electronics | AL32: =VLOOKUP(Z32,Coupons!A:B,2,FALSE) -> 0.1 | AM32: =AE32*AL32 -> 85.34 | AN32: =N32*0.7 -> 298.69 | AO32: =AN32*L32 -> 597.38 | AP32: =AF32-AM32 -> 768.06 | AQ32: =AP32-AO32 -> 170.68 | AR32: =AP32/AO32 -> 1.2857143
A33: ORD200031 | B33: =(RIGHT(A33, LEN(A33)-3))*1 -> 200031 | C33: 45107 | D33: 45107 | E33: =(TEXT(D33, "yyyy"))*1 -> 2023 | F33: =TEXT(D33, "mmmm") -> June | G33: =TEXT(D33, "dddd") -> Friday | H33: C26445 | I33: =(RIGHT(H33, LEN(H33)-1))*1 -> 26445 | J33: Chair | K33: =TRIM(PROPER(J33)) -> Chair | L33: 3 | M33: 500.08 | N33: =(TRIM(PROPER(M33)))*1 -> 500.08 | O33: 996 Main St | P33: =LEFT(O33, FIND(" ", O33)-1) -> 996 | Q33: =RIGHT(O33, LEN(O33) - FIND(" ", O33)) -> Main St | R33: Debit Card | S33: =TRIM(PROPER(R33)) -> Debit Card | T33: Returned | U33: =TRIM(PROPER(T33)) -> Returned | V33: TRK31229981 | W33: =RIGHT(V33, LEN(V33)-3) -> 31229981 | X33: 6 | Z33: =TRIM(UPPER(IF(Y33="", "NO COUPON", Y33))) -> NO COUPON | AA33: =IF(Z33="NO COUPON","NO","YES") -> NO | AB33: Facebook | AC33: =TRIM(PROPER(AB33)) -> Facebook | AD33: 1500.24 | AE33: 1500.24 | AF33: =N33*L33 -> 1500.24 | AG33: =_xlfn.XLOOKUP(H33, 'Customer Data'!A33,'Customer Data'!B33) -> Customer_33 | AH33: =_xlfn.XLOOKUP(H33,'Customer Data'!A33,'Customer Data'!C33) -> Female | AI33: =_xlfn.XLOOKUP(H33,'Customer Data'!A33,'Customer Data'!D33) -> 52 | AJ33: =_xlfn.XLOOKUP(H33,'Customer Data'!A33,'Customer Data'!E33) -> Port-Harcourt | AK33: =VLOOKUP(K33,'Product Category'!A:B,2,FALSE) -> Furniture | AL33: =VLOOKUP(Z33,Coupons!A:B,2,FALSE) -> 0 | AM33: =AE33*AL33 -> 0 | AN33: =N33*0.7 -> 350.056 | AO33: =AN33*L33 -> 1050.168 | AP33: =AF33-AM33 -> 1500.24 | AQ33: =AP33-AO33 -> 450.072 | AR33: =AP33/AO33 -> 1.4285714
A34: ORD200032 | B34: =(RIGHT(A34, LEN(A34)-3))*1 -> 200032 | C34: 45047 | D34: 45047 | E34: =(TEXT(D34, "yyyy"))*1 -> 2023 | F34: =TEXT(D34, "mmmm") -> May | G34: =TEXT(D34, "dddd") -> Monday | H34: C12388 | I34: =(RIGHT(H34, LEN(H34)-1))*1 -> 12388 | J34: Tablet | K34: =TRIM(PROPER(J34)) -> Tablet | L34: 5 | M34: 536.72 | N34: =(TRIM(PROPER(M34)))*1 -> 536.72 | O34: 830 Main St | P34: =LEFT(O34, FIND(" ", O34)-1) -> 830 | Q34: =RIGHT(O34, LEN(O34) - FIND(" ", O34)) -> Main St | R34: Cash | S34: =TRIM(PROPER(R34)) -> Cash | T34: Delivered | U34: =TRIM(PROPER(T34)) -> Delivered | V34: TRK99261395 | W34: =RIGHT(V34, LEN(V34)-3) -> 99261395 | X34: 10 | Z34: =TRIM(UPPER(IF(Y34="", "NO COUPON", Y34))) -> NO COUPON | AA34: =IF(Z34="NO COUPON","NO","YES") -> NO | AB34: Email | AC34: =TRIM(PROPER(AB34)) -> Email | AD34: 2683.6 | AE34: 2683.6 | AF34: =N34*L34 -> 2683.6 | AG34: =_xlfn.XLOOKUP(H34, 'Customer Data'!A34,'Customer Data'!B34) -> Customer_34 | AH34: =_xlfn.XLOOKUP(H34,'Customer Data'!A34,'Customer Data'!C34) -> Female | AI34: =_xlfn.XLOOKUP(H34,'Customer Data'!A34,'Customer Data'!D34) -> 26 | AJ34: =_xlfn.XLOOKUP(H34,'Customer Data'!A34,'Customer Data'!E34) -> Port-Harcourt | AK34: =VLOOKUP(K34,'Product Category'!A:B,2,FALSE) -> Electronics | AL34: =VLOOKUP(Z34,Coupons!A:B,2,FALSE) -> 0 | AM34: =AE34*AL34 -> 0 | AN34: =N34*0.7 -> 375.704 | AO34: =AN34*L34 -> 1878.52 | AP34: =AF34-AM34 -> 2683.6 | AQ34: =AP34-AO34 -> 805.08 | AR34: =AP34/AO34 -> 1.4285714
A35: ORD200033 | B35: =(RIGHT(A35, LEN(A35)-3))*1 -> 200033 | C35: 45082 | D35: 45082 | E35: =(TEXT(D35, "yyyy"))*1 -> 2023 | F35: =TEXT(D35, "mmmm") -> June | G35: =TEXT(D35, "dddd") -> Monday | H35: C52184 | I35: =(RIGHT(H35, LEN(H35)-1))*1 -> 52184 | J35: Chair | K35: =TRIM(PROPER(J35)) -> Chair | L35: 1 | M35: 162.77 | N35: =(TRIM(PROPER(M35)))*1 -> 162.77 | O35: 912 Main St | P35: =LEFT(O35, FIND(" ", O35)-1) -> 912 | Q35: =RIGHT(O35, LEN(O35) - FIND(" ", O35)) -> Main St | R35: Online | S35: =TRIM(PROPER(R35)) -> Online | T35: Cancelled | U35: =TRIM(PROPER(T35)) -> Cancelled | V35: TRK73312471 | W35: =RIGHT(V35, LEN(V35)-3) -> 73312471 | X35: 4 | Y35: WINTER15 | Z35: =TRIM(UPPER(IF(Y35="", "NO COUPON", Y35))) -> WINTER15 | AA35: =IF(Z35="NO COUPON","NO","YES") -> YES | AB35: Facebook | AC35: =TRIM(PROPER(AB35)) -> Facebook | AD35: 162.77 | AE35: 162.77 | AF35: =N35*L35 -> 162.77 | AG35: =_xlfn.XLOOKUP(H35, 'Customer Data'!A35,'Customer Data'!B35) -> Customer_35 | AH35: =_xlfn.XLOOKUP(H35,'Customer Data'!A35,'Customer Data'!C35) -> Female | AI35: =_xlfn.XLOOKUP(H35,'Customer Data'!A35,'Customer Data'!D35) -> 56 | AJ35: =_xlfn.XLOOKUP(H35,'Customer Data'!A35,'Customer Data'!E35) -> Owerri | AK35: =VLOOKUP(K35,'Product Category'!A:B,2,FALSE) -> Furniture | AL35: =VLOOKUP(Z35,Coupons!A:B,2,FALSE) -> 0.15 | AM35: =AE35*AL35 -> 24.4155 | AN35: =N35*0.7 -> 113.939 | AO35: =AN35*L35 -> 113.939 | AP35: =AF35-AM35 -> 138.3545 | AQ35: =AP35-AO35 -> 24.4155 | AR35: =AP35/AO35 -> 1.2142857
A36: ORD200034 | B36: =(RIGHT(A36, LEN(A36)-3))*1 -> 200034 | C36: 44933 | D36: 44933 | E36: =(TEXT(D36, "yyyy"))*1 -> 2023 | F36: =TEXT(D36, "mmmm") -> January | G36: =TEXT(D36, "dddd") -> Saturday | H36: C67195 | I36: =(RIGHT(H36, LEN(H36)-1))*1 -> 67195 | J36: Chair | K36: =TRIM(PROPER(J36)) -> Chair | L36: 4 | M36: 576.52 | N36: =(TRIM(PROPER(M36)))*1 -> 576.52 | O36: 926 Main St | P36: =LEFT(O36, FIND(" ", O36)-1) -> 926 | Q36: =RIGHT(O36, LEN(O36) - FIND(" ", O36)) -> Main St | R36: Credit Card | S36: =TRIM(PROPER(R36)) -> Credit Card | T36: Pending | U36: =TRIM(PROPER(T36)) -> Pending | V36: TRK55467915 | W36: =RIGHT(V36, LEN(V36)-3) -> 55467915 | X36: 5 | Y36: WINTER15 | Z36: =TRIM(UPPER(IF(Y36="", "NO COUPON", Y36))) -> WINTER15 | AA36: =IF(Z36="NO COUPON","NO","YES") -> YES | AB36: Facebook | AC36: =TRIM(PROPER(AB36)) -> Facebook | AD36: 2306.08 | AE36: 2306.08 | AF36: =N36*L36 -> 2306.08 | AG36: =_xlfn.XLOOKUP(H36, 'Customer Data'!A36,'Customer Data'!B36) -> Customer_36 | AH36: =_xlfn.XLOOKUP(H36,'Customer Data'!A36,'Customer Data'!C36) -> Male | AI36: =_xlfn.XLOOKUP(H36,'Customer Data'!A36,'Customer Data'!D36) -> 23 | AJ36: =_xlfn.XLOOKUP(H36,'Customer Data'!A36,'Customer Data'!E36) -> Owerri | AK36: =VLOOKUP(K36,'Product Category'!A:B,2,FALSE) -> Furniture | AL36: =VLOOKUP(Z36,Coupons!A:B,2,FALSE) -> 0.15 | AM36: =AE36*AL36 -> 345.912 | AN36: =N36*0.7 -> 403.564 | AO36: =AN36*L36 -> 1614.256 | AP36: =AF36-AM36 -> 1960.168 | AQ36: =AP36-AO36 -> 345.912 | AR36: =AP36/AO36 -> 1.2142857
A37: ORD200035 | B37: =(RIGHT(A37, LEN(A37)-3))*1 -> 200035 | C37: 45633 | D37: 45633 | E37: =(TEXT(D37, "yyyy"))*1 -> 2024 | F37: =TEXT(D37, "mmmm") -> December | G37: =TEXT(D37, "dddd") -> Saturday | H37: C50304 | I37: =(RIGHT(H37, LEN(H37)-1))*1 -> 50304 | J37: Monitor | K37: =TRIM(PROPER(J37)) -> Monitor | L37: 2 | M37: 465.15 | N37: =(TRIM(PROPER(M37)))*1 -> 465.15 | O37: 128 Main St | P37: =LEFT(O37, FIND(" ", O37)-1) -> 128 | Q37: =RIGHT(O37, LEN(O37) - FIND(" ", O37)) -> Main St | R37: Online | S37: =TRIM(PROPER(R37)) -> Online | T37: Shipped | U37: =TRIM(PROPER(T37)) -> Shipped | V37: TRK46850888 | W37: =RIGHT(V37, LEN(V37)-3) -> 46850888 | X37: 2 | Y37: SAVE10 | Z37: =TRIM(UPPER(IF(Y37="", "NO COUPON", Y37))) -> SAVE10 | AA37: =IF(Z37="NO COUPON","NO","YES") -> YES | AB37: Facebook | AC37: =TRIM(PROPER(AB37)) -> Facebook | AD37: 930.3 | AE37: 930.3 | AF37: =N37*L37 -> 930.3 | AG37: =_xlfn.XLOOKUP(H37, 'Customer Data'!A37,'Customer Data'!B37) -> Customer_37 | AH37: =_xlfn.XLOOKUP(H37,'Customer Data'!A37,'Customer Data'!C37) -> Female | AI37: =_xlfn.XLOOKUP(H37,'Customer Data'!A37,'Customer Data'!D37) -> 49 | AJ37: =_xlfn.XLOOKUP(H37,'Customer Data'!A37,'Customer Data'!E37) -> Kano | AK37: =VLOOKUP(K37,'Product Category'!A:B,2,FALSE) -> Electronics | AL37: =VLOOKUP(Z37,Coupons!A:B,2,FALSE) -> 0.1 | AM37: =AE37*AL37 -> 93.03 | AN37: =N37*0.7 -> 325.605 | AO37: =AN37*L37 -> 651.21 | AP37: =AF37-AM37 -> 837.27 | AQ37: =AP37-AO37 -> 186.06 | AR37: =AP37/AO37 -> 1.2857143
A38: ORD200036 | B38: =(RIGHT(A38, LEN(A38)-3))*1 -> 200036 | C38: 45785 | D38: 45785 | E38: =(TEXT(D38, "yyyy"))*1 -> 2025 | F38: =TEXT(D38, "mmmm") -> May | G38: =TEXT(D38, "dddd") -> Thursday | H38: C59337 | I38: =(RIGHT(H38, LEN(H38)-1))*1 -> 59337 | J38: Laptop | K38: =TRIM(PROPER(J38)) -> Laptop | L38: 2 | M38: 534.43 | N38: =(TRIM(PROPER(M38)))*1 -> 534.43 | O38: 465 Main St | P38: =LEFT(O38, FIND(" ", O38)-1) -> 465 | Q38: =RIGHT(O38, LEN(O38) - FIND(" ", O38)) -> Main St | R38: Debit Card | S38: =TRIM(PROPER(R38)) -> Debit Card | T38: Pending | U38: =TRIM(PROPER(T38)) -> Pending | V38: TRK50961250 | W38: =RIGHT(V38, LEN(V38)-3) -> 50961250 | X38: 5 | Z38: =TRIM(UPPER(IF(Y38="", "NO COUPON", Y38))) -> NO COUPON | AA38: =IF(Z38="NO COUPON","NO","YES") -> NO | AB38: Facebook | AC38: =TRIM(PROPER(AB38)) -> Facebook | AD38: 1068.86 | AE38: 1068.86 | AF38: =N38*L38 -> 1068.86 | AG38: =_xlfn.XLOOKUP(H38, 'Customer Data'!A38,'Customer Data'!B38) -> Customer_38 | AH38: =_xlfn.XLOOKUP(H38,'Customer Data'!A38,'Customer Data'!C38) -> Male | AI38: =_xlfn.XLOOKUP(H38,'Customer Data'!A38,'Customer Data'!D38) -> 43 | AJ38: =_xlfn.XLOOKUP(H38,'Customer Data'!A38,'Customer Data'!E38) -> Port-Harcourt | AK38: =VLOOKUP(K38,'Product Category'!A:B,2,FALSE) -> Electronics | AL38: =VLOOKUP(Z38,Coupons!A:B,2,FALSE) -> 0 | AM38: =AE38*AL38 -> 0 | AN38: =N38*0.7 -> 374.101 | AO38: =AN38*L38 -> 748.202 | AP38: =AF38-AM38 -> 1068.86 | AQ38: =AP38-AO38 -> 320.658 | AR38: =AP38/AO38 -> 1.4285714
A39: ORD200037 | B39: =(RIGHT(A39, LEN(A39)-3))*1 -> 200037 | C39: 45579 | D39: 45579 | E39: =(TEXT(D39, "yyyy"))*1 -> 2024 | F39: =TEXT(D39, "mmmm") -> October | G39: =TEXT(D39, "dddd") -> Monday | H39: C10054 | I39: =(RIGHT(H39, LEN(H39)-1))*1 -> 10054 | J39: Laptop | K39: =TRIM(PROPER(J39)) -> Laptop | L39: 2 | M39: 76.74 | N39: =(TRIM(PROPER(M39)))*1 -> 76.74 | O39: 409 Main St | P39: =LEFT(O39, FIND(" ", O39)-1) -> 409 | Q39: =RIGHT(O39, LEN(O39) - FIND(" ", O39)) -> Main St | R39: Cash | S39: =TRIM(PROPER(R39)) -> Cash | T39: Returned | U39: =TRIM(PROPER(T39)) -> Returned | V39: TRK94005261 | W39: =RIGHT(V39, LEN(V39)-3) -> 94005261 | X39: 7 | Y39: SAVE10 | Z39: =TRIM(UPPER(IF(Y39="", "NO COUPON", Y39))) -> SAVE10 | AA39: =IF(Z39="NO COUPON","NO","YES") -> YES | AB39: Instagram | AC39: =TRIM(PROPER(AB39)) -> Instagram | AD39: 153.48 | AE39: 153.48 | AF39: =N39*L39 -> 153.48 | AG39: =_xlfn.XLOOKUP(H39, 'Customer Data'!A39,'Customer Data'!B39) -> Customer_39 | AH39: =_xlfn.XLOOKUP(H39,'Customer Data'!A39,'Customer Data'!C39) -> Female | AI39: =_xlfn.XLOOKUP(H39,'Customer Data'!A39,'Customer Data'!D39) -> 54 | AJ39: =_xlfn.XLOOKUP(H39,'Customer Data'!A39,'Customer Data'!E39) -> Owerri | AK39: =VLOOKUP(K39,'Product Category'!A:B,2,FALSE) -> Electronics | AL39: =VLOOKUP(Z39,Coupons!A:B,2,FALSE) -> 0.1 | AM39: =AE39*AL39 -> 15.348 | AN39: =N39*0.7 -> 53.718 | AO39: =AN39*L39 -> 107.436 | AP39: =AF39-AM39 -> 138.132 | AQ39: =AP39-AO39 -> 30.696 | AR39: =AP39/AO39 -> 1.2857143
A40: ORD200038 | B40: =(RIGHT(A40, LEN(A40)-3))*1 -> 200038 | C40: 45645 | D40: 45645 | E40: =(TEXT(D40, "yyyy"))*1 -> 2024 | F40: =TEXT(D40, "mmmm") -> December | G40: =TEXT(D40, "dddd") -> Thursday | H40: C15924 | I40: =(RIGHT(H40, LEN(H40)-1))*1 -> 15924 | J40: Laptop | K40: =TRIM(PROPER(J40)) -> Laptop | L40: 1 | M40: 245.89 | N40: =(TRIM(PROPER(M40)))*1 -> 245.89 | O40: 549 Main St | P40: =LEFT(O40, FIND(" ", O40)-1) -> 549 | Q40: =RIGHT(O40, LEN(O40) - FIND(" ", O40)) -> Main St | R40: Debit Card | S40: =TRIM(PROPER(R40)) -> Debit Card | T40: Delivered | U40: =TRIM(PROPER(T40)) -> Delivered | V40: TRK14835975 | W40: =RIGHT(V40, LEN(V40)-3) -> 14835975 | X40: 3 | Y40: SAVE10 | Z40: =TRIM(UPPER(IF(Y40="", "NO COUPON", Y40))) -> SAVE10 | AA40: =IF(Z40="NO COUPON","NO","YES") -> YES | AB40: Google | AC40: =TRIM(PROPER(AB40)) -> Google | AD40: 245.89 | AE40: 245.89 | AF40: =N40*L40 -> 245.89 | AG40: =_xlfn.XLOOKUP(H40, 'Customer Data'!A40,'Customer Data'!B40) -> Customer_40 | AH40: =_xlfn.XLOOKUP(H40,'Customer Data'!A40,'Customer Data'!C40) -> Female | AI40: =_xlfn.XLOOKUP(H40,'Customer Data'!A40,'Customer Data'!D40) -> 40 | AJ40: =_xlfn.XLOOKUP(H40,'Customer Data'!A40,'Customer Data'!E40) -> Enugu | AK40: =VLOOKUP(K40,'Product Category'!A:B,2,FALSE) -> Electronics | AL40: =VLOOKUP(Z40,Coupons!A:B,2,FALSE) -> 0.1 | AM40: =AE40*AL40 -> 24.589 | AN40: =N40*0.7 -> 172.123 | AO40: =AN40*L40 -> 172.123 | AP40: =AF40-AM40 -> 221.301 | AQ40: =AP40-AO40 -> 49.178 | AR40: =AP40/AO40 -> 1.2857143
A41: ORD200039 | B41: =(RIGHT(A41, LEN(A41)-3))*1 -> 200039 | C41: 45715 | D41: 45715 | E41: =(TEXT(D41, "yyyy"))*1 -> 2025 | F41: =TEXT(D41, "mmmm") -> February | G41: =TEXT(D41, "dddd") -> Thursday | H41: C96664 | I41: =(RIGHT(H41, LEN(H41)-1))*1 -> 96664 | J41: Printer | K41: =TRIM(PROPER(J41)) -> Printer | L41: 3 | M41: 256.46 | N41: =(TRIM(PROPER(M41)))*1 -> 256.46 | O41: 666 Main St | P41: =LEFT(O41, FIND(" ", O41)-1) -> 666 | Q41: =RIGHT(O41, LEN(O41) - FIND(" ", O41)) -> Main St | R41: Credit Card | S41: =TRIM(PROPER(R41)) -> Credit Card | T41: Delivered | U41: =TRIM(PROPER(T41)) -> Delivered | V41: TRK85508960 | W41: =RIGHT(V41, LEN(V41)-3) -> 85508960 | X41: 4 | Y41: SAVE10 | Z41: =TRIM(UPPER(IF(Y41="", "NO COUPON", Y41))) -> SAVE10 | AA41: =IF(Z41="NO COUPON","NO","YES") -> YES | AB41: Referral | AC41: =TRIM(PROPER(AB41)) -> Referral | AD41: 769.38 | AE41: 769.38 | AF41: =N41*L41 -> 769.38 | AG41: =_xlfn.XLOOKUP(H41, 'Customer Data'!A41,'Customer Data'!B41) -> Customer_41 | AH41: =_xlfn.XLOOKUP(H41,'Customer Data'!A41,'Customer Data'!C41) -> Male | AI41: =_xlfn.XLOOKUP(H41,'Customer Data'!A41,'Customer Data'!D41) -> 24 | AJ41: =_xlfn.XLOOKUP(H41,'Customer Data'!A41,'Customer Data'!E41) -> Abuja | AK41: =VLOOKUP(K41,'Product Category'!A:B,2,FALSE) -> Electronics | AL41: =VLOOKUP(Z41,Coupons!A:B,2,FALSE) -> 0.1 | AM41: =AE41*AL41 -> 76.938 | AN41: =N41*0.7 -> 179.522 | AO41: =AN41*L41 -> 538.566 | AP41: =AF41-AM41 -> 692.442 | AQ41: =AP41-AO41 -> 153.876 | AR41: =AP41/AO41 -> 1.2857143
A42: ORD200040 | B42: =(RIGHT(A42, LEN(A42)-3))*1 -> 200040 | C42: 45158 | D42: 45158 | E42: =(TEXT(D42, "yyyy"))*1 -> 2023 | F42: =TEXT(D42, "mmmm") -> August | G42: =TEXT(D42, "dddd") -> Sunday | H42: C84766 | I42: =(RIGHT(H42, LEN(H42)-1))*1 -> 84766 | J42: Desk | K42: =TRIM(PROPER(J42)) -> Desk | L42: 2 | M42: 344.02 | N42: =(TRIM(PROPER(M42)))*1 -> 344.02 | O42: 267 Main St | P42: =LEFT(O42, FIND(" ", O42)-1) -> 267 | Q42: =RIGHT(O42, LEN(O42) - FIND(" ", O42)) -> Main St | R42: Online | S42: =TRIM(PROPER(R42)) -> Online | T42: Delivered | U42: =TRIM(PROPER(T42)) -> Delivered | V42: TRK78967923 | W42: =RIGHT(V42, LEN(V42)-3) -> 78967923 | X42: 4 | Y42: FREESHIP | Z42: =TRIM(UPPER(IF(Y42="", "NO COUPON", Y42))) -> FREESHIP | AA42: =IF(Z42="NO COUPON","NO","YES") -> YES | AB42: Instagram | AC42: =TRIM(PROPER(AB42)) -> Instagram | AD42: 688.04 | AE42: 688.04 | AF42: =N42*L42 -> 688.04 | AG42: =_xlfn.XLOOKUP(H42, 'Customer Data'!A42,'Customer Data'!B42) -> Customer_42 | AH42: =_xlfn.XLOOKUP(H42,'Customer Data'!A42,'Customer Data'!C42) -> Male | AI42: =_xlfn.XLOOKUP(H42,'Customer Data'!A42,'Customer Data'!D42) -> 58 | AJ42: =_xlfn.XLOOKUP(H42,'Customer Data'!A42,'Customer Data'!E42) -> Enugu | AK42: =VLOOKUP(K42,'Product Category'!A:B,2,FALSE) -> Furniture | AL42: =VLOOKUP(Z42,Coupons!A:B,2,FALSE) -> 0 | AM42: =AE42*AL42 -> 0 | AN42: =N42*0.7 -> 240.814 | AO42: =AN42*L42 -> 481.628 | AP42: =AF42-AM42 -> 688.04 | AQ42: =AP42-AO42 -> 206.412 | AR42: =AP42/AO42 -> 1.4285714
A43: ORD200041 | B43: =(RIGHT(A43, LEN(A43)-3))*1 -> 200041 | C43: 45265 | D43: 45265 | E43: =(TEXT(D43, "yyyy"))*1 -> 2023 | F43: =TEXT(D43, "mmmm") -> December | G43: =TEXT(D43, "dddd") -> Tuesday | H43: C20212 | I43: =(RIGHT(H43, LEN(H43)-1))*1 -> 20212 | J43: Monitor | K43: =TRIM(PROPER(J43)) -> Monitor | L43: 3 | M43: 611.45 | N43: =(TRIM(PROPER(M43)))*1 -> 611.45 | O43: 657 Main St | P43: =LEFT(O43, FIND(" ", O43)-1) -> 657 | Q43: =RIGHT(O43, LEN(O43) - FIND(" ", O43)) -> Main St | R43: Gift Card | S43: =TRIM(PROPER(R43)) -> Gift Card | T43: Pending | U43: =TRIM(PROPER(T43)) -> Pending | V43: TRK69733327 | W43: =RIGHT(V43, LEN(V43)-3) -> 69733327 | X43: 4 | Y43: FREESHIP | Z43: =TRIM(UPPER(IF(Y43="", "NO COUPON", Y43))) -> FREESHIP | AA43: =IF(Z43="NO COUPON","NO","YES") -> YES | AB43: Instagram | AC43: =TRIM(PROPER(AB43)) -> Instagram | AD43: 1834.35 | AE43: 1834.35 | AF43: =N43*L43 -> 1834.35 | AG43: =_xlfn.XLOOKUP(H43, 'Customer Data'!A43,'Customer Data'!B43) -> Customer_43 | AH43: =_xlfn.XLOOKUP(H43,'Customer Data'!A43,'Customer Data'!C43) -> Male | AI43: =_xlfn.XLOOKUP(H43,'Customer Data'!A43,'Customer Data'!D43) -> 37 | AJ43: =_xlfn.XLOOKUP(H43,'Customer Data'!A43,'Customer Data'!E43) -> Owerri | AK43: =VLOOKUP(K43,'Product Category'!A:B,2,FALSE) -> Electronics | AL43: =VLOOKUP(Z43,Coupons!A:B,2,FALSE) -> 0 | AM43: =AE43*AL43 -> 0 | AN43: =N43*0.7 -> 428.015 | AO43: =AN43*L43 -> 1284.045 | AP43: =AF43-AM43 -> 1834.35 | AQ43: =AP43-AO43 -> 550.305 | AR43: =AP43/AO43 -> 1.4285714
A44: ORD200042 | B44: =(RIGHT(A44, LEN(A44)-3))*1 -> 200042 | C44: 45418 | D44: 45418 | E44: =(TEXT(D44, "yyyy"))*1 -> 2024 | F44: =TEXT(D44, "mmmm") -> May | G44: =TEXT(D44, "dddd") -> Monday | H44: C28712 | I44: =(RIGHT(H44, LEN(H44)-1))*1 -> 28712 | J44: Printer | K44: =TRIM(PROPER(J44)) -> Printer | L44: 2 | M44: 151.66 | N44: =(TRIM(PROPER(M44)))*1 -> 151.66 | O44: 980 Main St | P44: =LEFT(O44, FIND(" ", O44)-1) -> 980 | Q44: =RIGHT(O44, LEN(O44) - FIND(" ", O44)) -> Main St | R44: Cash | S44: =TRIM(PROPER(R44)) -> Cash | T44: Cancelled | U44: =TRIM(PROPER(T44)) -> Cancelled | V44: TRK40772558 | W44: =RIGHT(V44, LEN(V44)-3) -> 40772558 | X44: 6 | Z44: =TRIM(UPPER(IF(Y44="", "NO COUPON", Y44))) -> NO COUPON | AA44: =IF(Z44="NO COUPON","NO","YES") -> NO | AB44: Instagram | AC44: =TRIM(PROPER(AB44)) -> Instagram | AD44: 303.32 | AE44: 303.32 | AF44: =N44*L44 -> 303.32 | AG44: =_xlfn.XLOOKUP(H44, 'Customer Data'!A44,'Customer Data'!B44) -> Customer_44 | AH44: =_xlfn.XLOOKUP(H44,'Customer Data'!A44,'Customer Data'!C44) -> Female | AI44: =_xlfn.XLOOKUP(H44,'Customer Data'!A44,'Customer Data'!D44) -> 23 | AJ44: =_xlfn.XLOOKUP(H44,'Customer Data'!A44,'Customer Data'!E44) -> Port-Harcourt | AK44: =VLOOKUP(K44,'Product Category'!A:B,2,FALSE) -> Electronics | AL44: =VLOOKUP(Z44,Coupons!A:B,2,FALSE) -> 0 | AM44: =AE44*AL44 -> 0 | AN44: =N44*0.7 -> 106.162 | AO44: =AN44*L44 -> 212.324 | AP44: =AF44-AM44 -> 303.32 | AQ44: =AP44-AO44 -> 90.996 | AR44: =AP44/AO44 -> 1.4285714
A45: ORD200043 | B45: =(RIGHT(A45, LEN(A45)-3))*1 -> 200043 | C45: 45274 | D45: 45274 | E45: =(TEXT(D45, "yyyy"))*1 -> 2023 | F45: =TEXT(D45, "mmmm") -> December | G45: =TEXT(D45, "dddd") -> Thursday | H45: C60572 | I45: =(RIGHT(H45, LEN(H45)-1))*1 -> 60572 | J45: Chair | K45: =TRIM(PROPER(J45)) -> Chair | L45: 3 | M45: 499.21 | N45: =(TRIM(PROPER(M45)))*1 -> 499.21 | O45: 871 Main St | P45: =LEFT(O45, FIND(" ", O45)-1) -> 871 | Q45: =RIGHT(O45, LEN(O45) - FIND(" ", O45)) -> Main St | R45: Online | S45: =TRIM(PROPER(R45)) -> Online | T45: Cancelled | U45: =TRIM(PROPER(T45)) -> Cancelled | V45: TRK20351666 | W45: =RIGHT(V45, LEN(V45)-3) -> 20351666 | X45: 8 | Z45: =TRIM(UPPER(IF(Y45="", "NO COUPON", Y45))) -> NO COUPON | AA45: =IF(Z45="NO COUPON","NO","YES") -> NO | AB45: Instagram | AC45: =TRIM(PROPER(AB45)) -> Instagram | AD45: 1497.63 | AE45: 1497.63 | AF45: =N45*L45 -> 1497.63 | AG45: =_xlfn.XLOOKUP(H45, 'Customer Data'!A45,'Customer Data'!B45) -> Customer_45 | AH45: =_xlfn.XLOOKUP(H45,'Customer Data'!A45,'Customer Data'!C45) -> Male | AI45: =_xlfn.XLOOKUP(H45,'Customer Data'!A45,'Customer Data'!D45) -> 56 | AJ45: =_xlfn.XLOOKUP(H45,'Customer Data'!A45,'Customer Data'!E45) -> Kano | AK45: =VLOOKUP(K45,'Product Category'!A:B,2,FALSE) -> Furniture | AL45: =VLOOKUP(Z45,Coupons!A:B,2,FALSE) -> 0 | AM45: =AE45*AL45 -> 0 | AN45: =N45*0.7 -> 349.447 | AO45: =AN45*L45 -> 1048.341 | AP45: =AF45-AM45 -> 1497.63 | AQ45: =AP45-AO45 -> 449.289 | AR45: =AP45/AO45 -> 1.4285714
A46: ORD200044 | B46: =(RIGHT(A46, LEN(A46)-3))*1 -> 200044 | C46: 45768 | D46: 45768 | E46: =(TEXT(D46, "yyyy"))*1 -> 2025 | F46: =TEXT(D46, "mmmm") -> April | G46: =TEXT(D46, "dddd") -> Monday | H46: C73225 | I46: =(RIGHT(H46, LEN(H46)-1))*1 -> 73225 | J46: Phone | K46: =TRIM(PROPER(J46)) -> Phone | L46: 2 | M46: 550.18 | N46: =(TRIM(PROPER(M46)))*1 -> 550.18 | O46: 996 Main St | P46: =LEFT(O46, FIND(" ", O46)-1) -> 996 | Q46: =RIGHT(O46, LEN(O46) - FIND(" ", O46)) -> Main St | R46: Gift Card | S46: =TRIM(PROPER(R46)) -> Gift Card | T46: Returned | U46: =TRIM(PROPER(T46)) -> Returned | V46: TRK73848522 | W46: =RIGHT(V46, LEN(V46)-3) -> 73848522 | X46: 3 | Y46: FREESHIP | Z46: =TRIM(UPPER(IF(Y46="", "NO COUPON", Y46))) -> FREESHIP | AA46: =IF(Z46="NO COUPON","NO","YES") -> YES | AB46: Referral | AC46: =TRIM(PROPER(AB46)) -> Referral | AD46: 1100.36 | AE46: 1100.36 | AF46: =N46*L46 -> 1100.36 | AG46: =_xlfn.XLOOKUP(H46, 'Customer Data'!A46,'Customer Data'!B46) -> Customer_46 | AH46: =_xlfn.XLOOKUP(H46,'Customer Data'!A46,'Customer Data'!C46) -> Female | AI46: =_xlfn.XLOOKUP(H46,'Customer Data'!A46,'Customer Data'!D46) -> 31 | AJ46: =_xlfn.XLOOKUP(H46,'Customer Data'!A46,'Customer Data'!E46) -> Kano | AK46: =VLOOKUP(K46,'Product Category'!A:B,2,FALSE) -> Electronics | AL46: =VLOOKUP(Z46,Coupons!A:B,2,FALSE) -> 0 | AM46: =AE46*AL46 -> 0 | AN46: =N46*0.7 -> 385.126 | AO46: =AN46*L46 -> 770.252 | AP46: =AF46-AM46 -> 1100.36 | AQ46: =AP46-AO46 -> 330.108 | AR46: =AP46/AO46 -> 1.4285714
A47: ORD200045 | B47: =(RIGHT(A47, LEN(A47)-3))*1 -> 200045 | C47: 45332 | D47: 45332 | E47: =(TEXT(D47, "yyyy"))*1 -> 2024 | F47: =TEXT(D47, "mmmm") -> February | G47: =TEXT(D47, "dddd") -> Saturday | H47: C17388 | I47: =(RIGHT(H47, LEN(H47)-1))*1 -> 17388 | J47: Chair | K47: =TRIM(PROPER(J47)) -> Chair | L47: 1 | M47: 317.25 | N47: =(TRIM(PROPER(M47)))*1 -> 317.25 | O47: 157 Main St | P47: =LEFT(O47, FIND(" ", O47)-1) -> 157 | Q47: =RIGHT(O47, LEN(O47) - FIND(" ", O47)) -> Main St | R47: Debit Card | S47: =TRIM(PROPER(R47)) -> Debit Card | T47: Returned | U47: =TRIM(PROPER(T47)) -> Returned | V47: TRK47077395 | W47: =RIGHT(V47, LEN(V47)-3) -> 47077395 | X47: 1 | Y47: SAVE10 | Z47: =TRIM(UPPER(IF(Y47="", "NO COUPON", Y47))) -> SAVE10 | AA47: =IF(Z47="NO COUPON","NO","YES") -> YES | AB47: Facebook | AC47: =TRIM(PROPER(AB47)) -> Facebook | AD47: 317.25 | AE47: 317.25 | AF47: =N47*L47 -> 317.25 | AG47: =_xlfn.XLOOKUP(H47, 'Customer Data'!A47,'Customer Data'!B47) -> Customer_47 | AH47: =_xlfn.XLOOKUP(H47,'Customer Data'!A47,'Customer Data'!C47) -> Female | AI47: =_xlfn.XLOOKUP(H47,'Customer Data'!A47,'Customer Data'!D47) -> 18 | AJ47: =_xlfn.XLOOKUP(H47,'Customer Data'!A47,'Customer Data'!E47) -> Enugu | AK47: =VLOOKUP(K47,'Product Category'!A:B,2,FALSE) -> Furniture | AL47: =VLOOKUP(Z47,Coupons!A:B,2,FALSE) -> 0.1 | AM47: =AE47*AL47 -> 31.725 | AN47: =N47*0.7 -> 222.075 | AO47: =AN47*L47 -> 222.075 | AP47: =AF47-AM47 -> 285.525 | AQ47: =AP47-AO47 -> 63.45 | AR47: =AP47/AO47 -> 1.2857143
A48: ORD200046 | B48: =(RIGHT(A48, LEN(A48)-3))*1 -> 200046 | C48: 45469 | D48: 45469 | E48: =(TEXT(D48, "yyyy"))*1 -> 2024 | F48: =TEXT(D48, "mmmm") -> June | G48: =TEXT(D48, "dddd") -> Wednesday | H48: C43212 | I48: =(RIGHT(H48, LEN(H48)-1))*1 -> 43212 | J48: Monitor | K48: =TRIM(PROPER(J48)) -> Monitor | L48: 4 | M48: 550.14 | N48: =(TRIM(PROPER(M48)))*1 -> 550.14 | O48: 223 Main St | P48: =LEFT(O48, FIND(" ", O48)-1) -> 223 | Q48: =RIGHT(O48, LEN(O48) - FIND(" ", O48)) -> Main St | R48: Debit Card | S48: =TRIM(PROPER(R48)) -> Debit Card | T48: Pending | U48: =TRIM(PROPER(T48)) -> Pending | V48: TRK25100762 | W48: =RIGHT(V48, LEN(V48)-3) -> 25100762 | X48: 4 | Y48: FREESHIP | Z48: =TRIM(UPPER(IF(Y48="", "NO COUPON", Y48))) -> FREESHIP | AA48: =IF(Z48="NO COUPON","NO","YES") -> YES | AB48: Instagram | AC48: =TRIM(PROPER(AB48)) -> Instagram | AD48: 2200.56 | AE48: 2200.56 | AF48: =N48*L48 -> 2200.56 | AG48: =_xlfn.XLOOKUP(H48, 'Customer Data'!A48,'Customer Data'!B48) -> Customer_48 | AH48: =_xlfn.XLOOKUP(H48,'Customer Data'!A48,'Customer Data'!C48) -> Female | AI48: =_xlfn.XLOOKUP(H48,'Customer Data'!A48,'Customer Data'!D48) -> 46 | AJ48: =_xlfn.XLOOKUP(H48,'Customer Data'!A48,'Customer Data'!E48) -> Enugu | AK48: =VLOOKUP(K48,'Product Category'!A:B,2,FALSE) -> Electronics | AL48: =VLOOKUP(Z48,Coupons!A:B,2,FALSE) -> 0 | AM48: =AE48*AL48 -> 0 | AN48: =N48*0.7 -> 385.098 | AO48: =AN48*L48 -> 1540.392 | AP48: =AF48-AM48 -> 2200.56 | AQ48: =AP48-AO48 -> 660.168 | AR48: =AP48/AO48 -> 1.4285714
A49: ORD200047 | B49: =(RIGHT(A49, LEN(A49)-3))*1 -> 200047 | C49: 45126 | D49: 45126 | E49: =(TEXT(D49, "yyyy"))*1 -> 2023 | F49: =TEXT(D49, "mmmm") -> July | G49: =TEXT(D49, "dddd") -> Wednesday | H49: C38134 | I49: =(RIGHT(H49, LEN(H49)-1))*1 -> 38134 | J49: Desk | K49: =TRIM(PROPER(J49)) -> Desk | L49: 2 | M49: 209.94 | N49: =(TRIM(PROPER(M49)))*1 -> 209.94 | O49: 323 Main St | P49: =LEFT(O49, FIND(" ", O49)-1) -> 323 | Q49: =RIGHT(O49, LEN(O49) - FIND(" ", O49)) -> Main St | R49: Credit Card | S49: =TRIM(PROPER(R49)) -> Credit Card | T49: Returned | U49: =TRIM(PROPER(T49)) -> Returned | V49: TRK42450754 | W49: =RIGHT(V49, LEN(V49)-3) -> 42450754 | X49: 3 | Y49: FREESHIP | Z49: =TRIM(UPPER(IF(Y49="", "NO COUPON", Y49))) -> FREESHIP | AA49: =IF(Z49="NO COUPON","NO","YES") -> YES | AB49: Email | AC49: =TRIM(PROPER(AB49)) -> Email | AD49: 419.88 | AE49: 419.88 | AF49: =N49*L49 -> 419.88 | AG49: =_xlfn.XLOOKUP(H49, 'Customer Data'!A49,'Customer Data'!B49) -> Customer_49 | AH49: =_xlfn.XLOOKUP(H49,'Customer Data'!A49,'Customer Data'!C49) -> Female | AI49: =_xlfn.XLOOKUP(H49,'Customer Data'!A49,'Customer Data'!D49) -> 40 | AJ49: =_xlfn.XLOOKUP(H49,'Customer Data'!A49,'Customer Data'!E49) -> Kano | AK49: =VLOOKUP(K49,'Product Category'!A:B,2,FALSE) -> Furniture | AL49: =VLOOKUP(Z49,Coupons!A:B,2,FALSE) -> 0 | AM49: =AE49*AL49 -> 0 | AN49: =N49*0.7 -> 146.958 | AO49: =AN49*L49 -> 293.916 | AP49: =AF49-AM49 -> 419.88 | AQ49: =AP49-AO49 -> 125.964 | AR49: =AP49/AO49 -> 1.4285714
A50: ORD200048 | B50: =(RIGHT(A50, LEN(A50)-3))*1 -> 200048 | C50: 45164 | D50: 45164 | E50: =(TEXT(D50, "yyyy"))*1 -> 2023 | F50: =TEXT(D50, "mmmm") -> August | G50: =TEXT(D50, "dddd") -> Saturday | H50: C12408 | I50: =(RIGHT(H50, LEN(H50)-1))*1 -> 12408 | J50: Monitor | K50: =TRIM(PROPER(J50)) -> Monitor | L50: 2 | M50: 80.77 | N50: =(TRIM(PROPER(M50)))*1 -> 80.77 | O50: 464 Main St | P50: =LEFT(O50, FIND(" ", O50)-1) -> 464 | Q50: =RIGHT(O50, LEN(O50) - FIND(" ", O50)) -> Main St | R50: Debit Card | S50: =TRIM(PROPER(R50)) -> Debit Card | T50: Shipped | U50: =TRIM(PROPER(T50)) -> Shipped | V50: TRK38938858 | W50: =RIGHT(V50, LEN(V50)-3) -> 38938858 | X50: 4 | Z50: =TRIM(UPPER(IF(Y50="", "NO COUPON", Y50))) -> NO COUPON | AA50: =IF(Z50="NO COUPON","NO","YES") -> NO | AB50: Google | AC50: =TRIM(PROPER(AB50)) -> Google | AD50: 161.54 | AE50: 161.54 | AF50: =N50*L50 -> 161.54 | AG50: =_xlfn.XLOOKUP(H50, 'Customer Data'!A50,'Customer Data'!B50) -> Customer_50 | AH50: =_xlfn.XLOOKUP(H50,'Customer Data'!A50,'Customer Data'!C50) -> Male | AI50: =_xlfn.XLOOKUP(H50,'Customer Data'!A50,'Customer Data'!D50) -> 19 | AJ50: =_xlfn.XLOOKUP(H50,'Customer Data'!A50,'Customer Data'!E50) -> Owerri | AK50: =VLOOKUP(K50,'Product Category'!A:B,2,FALSE) -> Electronics | AL50: =VLOOKUP(Z50,Coupons!A:B,2,FALSE) -> 0 | AM50: =AE50*AL50 -> 0 | AN50: =N50*0.7 -> 56.539 | AO50: =AN50*L50 -> 113.078 | AP50: =AF50-AM50 -> 161.54 | AQ50: =AP50-AO50 -> 48.462 | AR50: =AP50/AO50 -> 1.4285714
A51: ORD200049 | B51: =(RIGHT(A51, LEN(A51)-3))*1 -> 200049 | C51: 45206 | D51: 45206 | E51: =(TEXT(D51, "yyyy"))*1 -> 2023 | F51: =TEXT(D51, "mmmm") -> October | G51: =TEXT(D51, "dddd") -> Saturday | H51: C11985 | I51: =(RIGHT(H51, LEN(H51)-1))*1 -> 11985 | J51: Printer | K51: =TRIM(PROPER(J51)) -> Printer | L51: 1 | M51: 30.44 | N51: =(TRIM(PROPER(M51)))*1 -> 30.44 | O51: 633 Main St | P51: =LEFT(O51, FIND(" ", O51)-1) -> 633 | Q51: =RIGHT(O51, LEN(O51) - FIND(" ", O51)) -> Main St | R51: Credit Card | S51: =TRIM(PROPER(R51)) -> Credit Card | T51: Shipped | U51: =TRIM(PROPER(T51)) -> Shipped | V51: TRK53272402 | W51: =RIGHT(V51, LEN(V51)-3) -> 53272402 | X51: 1 | Y51: SAVE10 | Z51: =TRIM(UPPER(IF(Y51="", "NO COUPON", Y51))) -> SAVE10 | AA51: =IF(Z51="NO COUPON","NO","YES") -> YES | AB51: Email | AC51: =TRIM(PROPER(AB51)) -> Email | AD51: 30.44 | AE51: 30.44 | AF51: =N51*L51 -> 30.44 | AG51: =_xlfn.XLOOKUP(H51, 'Customer Data'!A51,'Customer Data'!B51) -> Customer_51 | AH51: =_xlfn.XLOOKUP(H51,'Customer Data'!A51,'Customer Data'!C51) -> Male | AI51: =_xlfn.XLOOKUP(H51,'Customer Data'!A51,'Customer Data'!D51) -> 45 | AJ51: =_xlfn.XLOOKUP(H51,'Customer Data'!A51,'Customer Data'!E51) -> Lagos | AK51: =VLOOKUP(K51,'Product Category'!A:B,2,FALSE) -> Electronics | AL51: =VLOOKUP(Z51,Coupons!A:B,2,FALSE) -> 0.1 | AM51: =AE51*AL51 -> 3.044 | AN51: =N51*0.7 -> 21.308 | AO51: =AN51*L51 -> 21.308 | AP51: =AF51-AM51 -> 27.396 | AQ51: =AP51-AO51 -> 6.088 | AR51: =AP51/AO51 -> 1.2857143
A52: ORD200050 | B52: =(RIGHT(A52, LEN(A52)-3))*1 -> 200050 | C52: 45138 | D52: 45138 | E52: =(TEXT(D52, "yyyy"))*1 -> 2023 | F52: =TEXT(D52, "mmmm") -> July | G52: =TEXT(D52, "dddd") -> Monday | H52: C96494 | I52: =(RIGHT(H52, LEN(H52)-1))*1 -> 96494 | J52: Tablet | K52: =TRIM(PROPER(J52)) -> Tablet | L52: 1 | M52: 179.22 | N52: =(TRIM(PROPER(M52)))*1 -> 179.22 | O52: 446 Main St | P52: =LEFT(O52, FIND(" ", O52)-1) -> 446 | Q52: =RIGHT(O52, LEN(O52) - FIND(" ", O52)) -> Main St | R52: Online | S52: =TRIM(PROPER(R52)) -> Online | T52: Cancelled | U52: =TRIM(PROPER(T52)) -> Cancelled | V52: TRK14675049 | W52: =RIGHT(V52, LEN(V52)-3) -> 14675049 | X52: 6 | Y52: FREESHIP | Z52: =TRIM(UPPER(IF(Y52="", "NO COUPON", Y52))) -> FREESHIP | AA52: =IF(Z52="NO COUPON","NO","YES") -> YES | AB52: Instagram | AC52: =TRIM(PROPER(AB52)) -> Instagram | AD52: 179.22 | AE52: 179.22 | AF52: =N52*L52 -> 179.22 | AG52: =_xlfn.XLOOKUP(H52, 'Customer Data'!A52,'Customer Data'!B52) -> Customer_52 | AH52: =_xlfn.XLOOKUP(H52,'Customer Data'!A52,'Customer Data'!C52) -> Male | AI52: =_xlfn.XLOOKUP(H52,'Customer Data'!A52,'Customer Data'!D52) -> 37 | AJ52: =_xlfn.XLOOKUP(H52,'Customer Data'!A52,'Customer Data'!E52) -> Enugu | AK52: =VLOOKUP(K52,'Product Category'!A:B,2,FALSE) -> Electronics | AL52: =VLOOKUP(Z52,Coupons!A:B,2,FALSE) -> 0 | AM52: =AE52*AL52 -> 0 | AN52: =N52*0.7 -> 125.454 | AO52: =AN52*L52 -> 125.454 | AP52: =AF52-AM52 -> 179.22 | AQ52: =AP52-AO52 -> 53.766 | AR52: =AP52/AO52 -> 1.4285714
A53: ORD200051 | B53: =(RIGHT(A53, LEN(A53)-3))*1 -> 200051 | C53: 45656 | D53: 45656 | E53: =(TEXT(D53, "yyyy"))*1 -> 2024 | F53: =TEXT(D53, "mmmm") -> December | G53: =TEXT(D53, "dddd") -> Monday | H53: C36778 | I53: =(RIGHT(H53, LEN(H53)-1))*1 -> 36778 | J53: Tablet | K53: =TRIM(PROPER(J53)) -> Tablet | L53: 1 | M53: 388.33 | N53: =(TRIM(PROPER(M53)))*1 -> 388.33 | O53: 434 Main St | P53: =LEFT(O53, FIND(" ", O53)-1) -> 434 | Q53: =RIGHT(O53, LEN(O53) - FIND(" ", O53)) -> Main St | R53: Cash | S53: =TRIM(PROPER(R53)) -> Cash | T53: Returned | U53: =TRIM(PROPER(T53)) -> Returned | V53: TRK67610289 | W53: =RIGHT(V53, LEN(V53)-3) -> 67610289 | X53: 2 | Y53: SAVE10 | Z53: =TRIM(UPPER(IF(Y53="", "NO COUPON", Y53))) -> SAVE10 | AA53: =IF(Z53="NO COUPON","NO","YES") -> YES | AB53: Facebook | AC53: =TRIM(PROPER(AB53)) -> Facebook | AD53: 388.33 | AE53: 388.33 | AF53: =N53*L53 -> 388.33 | AG53: =_xlfn.XLOOKUP(H53, 'Customer Data'!A53,'Customer Data'!B53) -> Customer_53 | AH53: =_xlfn.XLOOKUP(H53,'Customer Data'!A53,'Customer Data'!C53) -> Female | AI53: =_xlfn.XLOOKUP(H53,'Customer Data'!A53,'Customer Data'!D53) -> 57 | AJ53: =_xlfn.XLOOKUP(H53,'Customer Data'!A53,'Customer Data'!E53) -> Enugu | AK53: =VLOOKUP(K53,'Product Category'!A:B,2,FALSE) -> Electronics | AL53: =VLOOKUP(Z53,Coupons!A:B,2,FALSE) -> 0.1 | AM53: =AE53*AL53 -> 38.833 | AN53: =N53*0.7 -> 271.831 | AO53: =AN53*L53 -> 271.831 | AP53: =AF53-AM53 -> 349.497 | AQ53: =AP53-AO53 -> 77.666 | AR53: =AP53/AO53 -> 1.2857143
A54: ORD200052 | B54: =(RIGHT(A54, LEN(A54)-3))*1 -> 200052 | C54: 45543 | D54: 45543 | E54: =(TEXT(D54, "yyyy"))*1 -> 2024 | F54: =TEXT(D54, "mmmm") -> September | G54: =TEXT(D54, "dddd") -> Sunday | H54: C30513 | I54: =(RIGHT(H54, LEN(H54)-1))*1 -> 30513 | J54: Tablet | K54: =TRIM(PROPER(J54)) -> Tablet | L54: 1 | M54: 586.44 | N54: =(TRIM(PROPER(M54)))*1 -> 586.44 | O54: 232 Main St | P54: =LEFT(O54, FIND(" ", O54)-1) -> 232 | Q54: =RIGHT(O54, LEN(O54) - FIND(" ", O54)) -> Main St | R54: Online | S54: =TRIM(PROPER(R54)) -> Online | T54: Returned | U54: =TRIM(PROPER(T54)) -> Returned | V54: TRK64320429 | W54: =RIGHT(V54, LEN(V54)-3) -> 64320429 | X54: 5 | Y54: SAVE10 | Z54: =TRIM(UPPER(IF(Y54="", "NO COUPON", Y54))) -> SAVE10 | AA54: =IF(Z54="NO COUPON","NO","YES") -> YES | AB54: Facebook | AC54: =TRIM(PROPER(AB54)) -> Facebook | AD54: 586.44 | AE54: 586.44 | AF54: =N54*L54 -> 586.44 | AG54: =_xlfn.XLOOKUP(H54, 'Customer Data'!A54,'Customer Data'!B54) -> Customer_54 | AH54: =_xlfn.XLOOKUP(H54,'Customer Data'!A54,'Customer Data'!C54) -> Female | AI54: =_xlfn.XLOOKUP(H54,'Customer Data'!A54,'Customer Data'!D54) -> 18 | AJ54: =_xlfn.XLOOKUP(H54,'Customer Data'!A54,'Customer Data'!E54) -> Abuja | AK54: =VLOOKUP(K54,'Product Category'!A:B,2,FALSE) -> Electronics | AL54: =VLOOKUP(Z54,Coupons!A:B,2,FALSE) -> 0.1 | AM54: =AE54*AL54 -> 58.644 | AN54: =N54*0.7 -> 410.508 | AO54: =AN54*L54 -> 410.508 | AP54: =AF54-AM54 -> 527.796 | AQ54: =AP54-AO54 -> 117.288 | AR54: =AP54/AO54 -> 1.2857143
A55: ORD200053 | B55: =(RIGHT(A55, LEN(A55)-3))*1 -> 200053 | C55: 45430 | D55: 45430 | E55: =(TEXT(D55, "yyyy"))*1 -> 2024 | F55: =TEXT(D55, "mmmm") -> May | G55: =TEXT(D55, "dddd") -> Saturday | H55: C67551 | I55: =(RIGHT(H55, LEN(H55)-1))*1 -> 67551 | J55: Phone | K55: =TRIM(PROPER(J55)) -> Phone | L55: 4 | M55: 488.78 | N55: =(TRIM(PROPER(M55)))*1 -> 488.78 | O55: 512 Main St | P55: =LEFT(O55, FIND(" ", O55)-1) -> 512 | Q55: =RIGHT(O55, LEN(O55) - FIND(" ", O55)) -> Main St | R55: Online | S55: =TRIM(PROPER(R55)) -> Online | T55: Returned | U55: =TRIM(PROPER(T55)) -> Returned | V55: TRK94992552 | W55: =RIGHT(V55, LEN(V55)-3) -> 94992552 | X55: 5 | Y55: FREESHIP | Z55: =TRIM(UPPER(IF(Y55="", "NO COUPON", Y55))) -> FREESHIP | AA55: =IF(Z55="NO COUPON","NO","YES") -> YES | AB55: Google | AC55: =TRIM(PROPER(AB55)) -> Google | AD55: 1955.12 | AE55: 1955.12 | AF55: =N55*L55 -> 1955.12 | AG55: =_xlfn.XLOOKUP(H55, 'Customer Data'!A55,'Customer Data'!B55) -> Customer_55 | AH55: =_xlfn.XLOOKUP(H55,'Customer Data'!A55,'Customer Data'!C55) -> Male | AI55: =_xlfn.XLOOKUP(H55,'Customer Data'!A55,'Customer Data'!D55) -> 56 | AJ55: =_xlfn.XLOOKUP(H55,'Customer Data'!A55,'Customer Data'!E55) -> Port-Harcourt | AK55: =VLOOKUP(K55,'Product Category'!A:B,2,FALSE) -> Electronics | AL55: =VLOOKUP(Z55,Coupons!A:B,2,FALSE) -> 0 | AM55: =AE55*AL55 -> 0 | AN55: =N55*0.7 -> 342.146 | AO55: =AN55*L55 -> 1368.584 | AP55: =AF55-AM55 -> 1955.12 | AQ55: =AP55-AO55 -> 586.536 | AR55: =AP55/AO55 -> 1.4285714
A56: ORD200054 | B56: =(RIGHT(A56, LEN(A56)-3))*1 -> 200054 | C56: 45743 | D56: 45743 | E56: =(TEXT(D56, "yyyy"))*1 -> 2025 | F56: =TEXT(D56, "mmmm") -> March | G56: =TEXT(D56, "dddd") -> Thursday | H56: C48120 | I56: =(RIGHT(H56, LEN(H56)-1))*1 -> 48120 | J56: Chair | K56: =TRIM(PROPER(J56)) -> Chair | L56: 1 | M56: 280.25 | N56: =(TRIM(PROPER(M56)))*1 -> 280.25 | O56: 623 Main St | P56: =LEFT(O56, FIND(" ", O56)-1) -> 623 | Q56: =RIGHT(O56, LEN(O56) - FIND(" ", O56)) -> Main St | R56: Online | S56: =TRIM(PROPER(R56)) -> Online | T56: Pending | U56: =TRIM(PROPER(T56)) -> Pending | V56: TRK11014449 | W56: =RIGHT(V56, LEN(V56)-3) -> 11014449 | X56: 5 | Y56: WINTER15 | Z56: =TRIM(UPPER(IF(Y56="", "NO COUPON", Y56))) -> WINTER15 | AA56: =IF(Z56="NO COUPON","NO","YES") -> YES | AB56: Email | AC56: =TRIM(PROPER(AB56)) -> Email | AD56: 280.25 | AE56: 280.25 | AF56: =N56*L56 -> 280.25 | AG56: =_xlfn.XLOOKUP(H56, 'Customer Data'!A56,'Customer Data'!B56) -> Customer_56 | AH56: =_xlfn.XLOOKUP(H56,'Customer Data'!A56,'Customer Data'!C56) -> Female | AI56: =_xlfn.XLOOKUP(H56,'Customer Data'!A56,'Customer Data'!D56) -> 29 | AJ56: =_xlfn.XLOOKUP(H56,'Customer Data'!A56,'Customer Data'!E56) -> Enugu | AK56: =VLOOKUP(K56,'Product Category'!A:B,2,FALSE) -> Furniture | AL56: =VLOOKUP(Z56,Coupons!A:B,2,FALSE) -> 0.15 | AM56: =AE56*AL56 -> 42.0375 | AN56: =N56*0.7 -> 196.175 | AO56: =AN56*L56 -> 196.175 | AP56: =AF56-AM56 -> 238.2125 | AQ56: =AP56-AO56 -> 42.0375 | AR56: =AP56/AO56 -> 1.2142857
A57: ORD200055 | B57: =(RIGHT(A57, LEN(A57)-3))*1 -> 200055 | C57: 45832 | D57: 45832 | E57: =(TEXT(D57, "yyyy"))*1 -> 2025 | F57: =TEXT(D57, "mmmm") -> June | G57: =TEXT(D57, "dddd") -> Tuesday | H57: C95984 | I57: =(RIGHT(H57, LEN(H57)-1))*1 -> 95984 | J57: Printer | K57: =TRIM(PROPER(J57)) -> Printer | L57: 3 | M57: 344.4 | N57: =(TRIM(PROPER(M57)))*1 -> 344.4 | O57: 565 Main St | P57: =LEFT(O57, FIND(" ", O57)-1) -> 565 | Q57: =RIGHT(O57, LEN(O57) - FIND(" ", O57)) -> Main St | R57: Online | S57: =TRIM(PROPER(R57)) -> Online | T57: Cancelled | U57: =TRIM(PROPER(T57)) -> Cancelled | V57: TRK67434829 | W57: =RIGHT(V57, LEN(V57)-3) -> 67434829 | X57: 3 | Z57: =TRIM(UPPER(IF(Y57="", "NO COUPON", Y57))) -> NO COUPON | AA57: =IF(Z57="NO COUPON","NO","YES") -> NO | AB57: Facebook | AC57: =TRIM(PROPER(AB57)) -> Facebook | AD57: 1033.2 | AE57: 1033.2 | AF57: =N57*L57 -> 1033.2 | AG57: =_xlfn.XLOOKUP(H57, 'Customer Data'!A57,'Customer Data'!B57) -> Customer_57 | AH57: =_xlfn.XLOOKUP(H57,'Customer Data'!A57,'Customer Data'!C57) -> Male | AI57: =_xlfn.XLOOKUP(H57,'Customer Data'!A57,'Customer Data'!D57) -> 25 | AJ57: =_xlfn.XLOOKUP(H57,'Customer Data'!A57,'Customer Data'!E57) -> Lagos | AK57: =VLOOKUP(K57,'Product Category'!A:B,2,FALSE) -> Electronics | AL57: =VLOOKUP(Z57,Coupons!A:B,2,FALSE) -> 0 | AM57: =AE57*AL57 -> 0 | AN57: =N57*0.7 -> 241.08 | AO57: =AN57*L57 -> 723.24 | AP57: =AF57-AM57 -> 1033.2 | AQ57: =AP57-AO57 -> 309.96 | AR57: =AP57/AO57 -> 1.4285714
A58: ORD200056 | B58: =(RIGHT(A58, LEN(A58)-3))*1 -> 200056 | C58: 45067 | D58: 45067 | E58: =(TEXT(D58, "yyyy"))*1 -> 2023 | F58: =TEXT(D58, "mmmm") -> May | G58: =TEXT(D58, "dddd") -> Sunday | H58: C54298 | I58: =(RIGHT(H58, LEN(H58)-1))*1 -> 54298 | J58: Tablet | K58: =TRIM(PROPER(J58)) -> Tablet | L58: 3 | M58: 479.21 | N58: =(TRIM(PROPER(M58)))*1 -> 479.21 | O58: 566 Main St | P58: =LEFT(O58, FIND(" ", O58)-1) -> 566 | Q58: =RIGHT(O58, LEN(O58) - FIND(" ", O58)) -> Main St | R58: Cash | S58: =TRIM(PROPER(R58)) -> Cash | T58: Cancelled | U58: =TRIM(PROPER(T58)) -> Cancelled | V58: TRK62902341 | W58: =RIGHT(V58, LEN(V58)-3) -> 62902341 | X58: 5 | Y58: WINTER15 | Z58: =TRIM(UPPER(IF(Y58="", "NO COUPON", Y58))) -> WINTER15 | AA58: =IF(Z58="NO COUPON","NO","YES") -> YES | AB58: Referral | AC58: =TRIM(PROPER(AB58)) -> Referral | AD58: 1437.63 | AE58: 1437.63 | AF58: =N58*L58 -> 1437.63 | AG58: =_xlfn.XLOOKUP(H58, 'Customer Data'!A58,'Customer Data'!B58) -> Customer_58 | AH58: =_xlfn.XLOOKUP(H58,'Customer Data'!A58,'Customer Data'!C58) -> Female | AI58: =_xlfn.XLOOKUP(H58,'Customer Data'!A58,'Customer Data'!D58) -> 38 | AJ58: =_xlfn.XLOOKUP(H58,'Customer Data'!A58,'Customer Data'!E58) -> Enugu | AK58: =VLOOKUP(K58,'Product Category'!A:B,2,FALSE) -> Electronics | AL58: =VLOOKUP(Z58,Coupons!A:B,2,FALSE) -> 0.15 | AM58: =AE58*AL58 -> 215.6445 | AN58: =N58*0.7 -> 335.447 | AO58: =AN58*L58 -> 1006.341 | AP58: =AF58-AM58 -> 1221.9855 | AQ58: =AP58-AO58 -> 215.6445 | AR58: =AP58/AO58 -> 1.2142857
A59: ORD200057 | B59: =(RIGHT(A59, LEN(A59)-3))*1 -> 200057 | C59: 44948 | D59: 44948 | E59: =(TEXT(D59, "yyyy"))*1 -> 2023 | F59: =TEXT(D59, "mmmm") -> January | G59: =TEXT(D59, "dddd") -> Sunday | H59: C88036 | I59: =(RIGHT(H59, LEN(H59)-1))*1 -> 88036 | J59: Printer | K59: =TRIM(PROPER(J59)) -> Printer | L59: 5 | M59: 314.27 | N59: =(TRIM(PROPER(M59)))*1 -> 314.27 | O59: 842 Main St | P59: =LEFT(O59, FIND(" ", O59)-1) -> 842 | Q59: =RIGHT(O59, LEN(O59) - FIND(" ", O59)) -> Main St | R59: Cash | S59: =TRIM(PROPER(R59)) -> Cash | T59: Returned | U59: =TRIM(PROPER(T59)) -> Returned | V59: TRK52470128 | W59: =RIGHT(V59, LEN(V59)-3) -> 52470128 | X59: 6 | Y59: SAVE10 | Z59: =TRIM(UPPER(IF(Y59="", "NO COUPON", Y59))) -> SAVE10 | AA59: =IF(Z59="NO COUPON","NO","YES") -> YES | AB59: Instagram | AC59: =TRIM(PROPER(AB59)) -> Instagram | AD59: 1571.35 | AE59: 1571.35 | AF59: =N59*L59 -> 1571.35 | AG59: =_xlfn.XLOOKUP(H59, 'Customer Data'!A59,'Customer Data'!B59) -> Customer_59 | AH59: =_xlfn.XLOOKUP(H59,'Customer Data'!A59,'Customer Data'!C59) -> Male | AI59: =_xlfn.XLOOKUP(H59,'Customer Data'!A59,'Customer Data'!D59) -> 49 | AJ59: =_xlfn.XLOOKUP(H59,'Customer Data'!A59,'Customer Data'!E59) -> Port-Harcourt | AK59: =VLOOKUP(K59,'Product Category'!A:B,2,FALSE) -> Electronics | AL59: =VLOOKUP(Z59,Coupons!A:B,2,FALSE) -> 0.1 | AM59: =AE59*AL59 -> 157.135 | AN59: =N59*0.7 -> 219.989 | AO59: =AN59*L59 -> 1099.945 | AP59: =AF59-AM59 -> 1414.215 | AQ59: =AP59-AO59 -> 314.27 | AR59: =AP59/AO59 -> 1.2857143
A60: ORD200058 | B60: =(RIGHT(A60, LEN(A60)-3))*1 -> 200058 | C60: 44941 | D60: 44941 | E60: =(TEXT(D60, "yyyy"))*1 -> 2023 | F60: =TEXT(D60, "mmmm") -> January | G60: =TEXT(D60, "dddd") -> Sunday | H60: C60190 | I60: =(RIGHT(H60, LEN(H60)-1))*1 -> 60190 | J60: Phone | K60: =TRIM(PROPER(J60)) -> Phone | L60: 4 | M60: 474.69 | N60: =(TRIM(PROPER(M60)))*1 -> 474.69 | O60: 202 Main St | P60: =LEFT(O60, FIND(" ", O60)-1) -> 202 | Q60: =RIGHT(O60, LEN(O60) - FIND(" ", O60)) -> Main St | R60: Gift Card | S60: =TRIM(PROPER(R60)) -> Gift Card | T60: Cancelled | U60: =TRIM(PROPER(T60)) -> Cancelled | V60: TRK70857868 | W60: =RIGHT(V60, LEN(V60)-3) -> 70857868 | X60: 6 | Y60: SAVE10 | Z60: =TRIM(UPPER(IF(Y60="", "NO COUPON", Y60))) -> SAVE10 | AA60: =IF(Z60="NO COUPON","NO","YES") -> YES | AB60: Google | AC60: =TRIM(PROPER(AB60)) -> Google | AD60: 1898.76 | AE60: 1898.76 | AF60: =N60*L60 -> 1898.76 | AG60: =_xlfn.XLOOKUP(H60, 'Customer Data'!A60,'Customer Data'!B60) -> Customer_60 | AH60: =_xlfn.XLOOKUP(H60,'Customer Data'!A60,'Customer Data'!C60) -> Female | AI60: =_xlfn.XLOOKUP(H60,'Customer Data'!A60,'Customer Data'!D60) -> 36 | AJ60: =_xlfn.XLOOKUP(H60,'Customer Data'!A60,'Customer Data'!E60) -> Lagos | AK60: =VLOOKUP(K60,'Product Category'!A:B,2,FALSE) -> Electronics | AL60: =VLOOKUP(Z60,Coupons!A:B,2,FALSE) -> 0.1 | AM60: =AE60*AL60 -> 189.876 | AN60: =N60*0.7 -> 332.283 | AO60: =AN60*L60 -> 1329.132 | AP60: =AF60-AM60 -> 1708.884 | AQ60: =AP60-AO60 -> 379.752 | AR60: =AP60/AO60 -> 1.2857143
A61: ORD200059 | B61: =(RIGHT(A61, LEN(A61)-3))*1 -> 200059 | C61: 45546 | D61: 45546 | E61: =(TEXT(D61, "yyyy"))*1 -> 2024 | F61: =TEXT(D61, "mmmm") -> September | G61: =TEXT(D61, "dddd") -> Wednesday | H61: C97603 | I61: =(RIGHT(H61, LEN(H61)-1))*1 -> 97603 | J61: Chair | K61: =TRIM(PROPER(J61)) -> Chair | L61: 4 | M61: 593.27 | N61: =(TRIM(PROPER(M61)))*1 -> 593.27 | O61: 811 Main St | P61: =LEFT(O61, FIND(" ", O61)-1) -> 811 | Q61: =RIGHT(O61, LEN(O61) - FIND(" ", O61)) -> Main St | R61: Online | S61: =TRIM(PROPER(R61)) -> Online | T61: Shipped | U61: =TRIM(PROPER(T61)) -> Shipped | V61: TRK47055028 | W61: =RIGHT(V61, LEN(V61)-3) -> 47055028 | X61: 5 | Z61: =TRIM(UPPER(IF(Y61="", "NO COUPON", Y61))) -> NO COUPON | AA61: =IF(Z61="NO COUPON","NO","YES") -> NO | AB61: Facebook | AC61: =TRIM(PROPER(AB61)) -> Facebook | AD61: 2373.08 | AE61: 2373.08 | AF61: =N61*L61 -> 2373.08 | AG61: =_xlfn.XLOOKUP(H61, 'Customer Data'!A61,'Customer Data'!B61) -> Customer_61 | AH61: =_xlfn.XLOOKUP(H61,'Customer Data'!A61,'Customer Data'!C61) -> Male | AI61: =_xlfn.XLOOKUP(H61,'Customer Data'!A61,'Customer Data'!D61) -> 48 | AJ61: =_xlfn.XLOOKUP(H61,'Customer Data'!A61,'Customer Data'!E61) -> Lagos | AK61: =VLOOKUP(K61,'Product Category'!A:B,2,FALSE) -> Furniture | AL61: =VLOOKUP(Z61,Coupons!A:B,2,FALSE) -> 0 | AM61: =AE61*AL61 -> 0 | AN61: =N61*0.7 -> 415.289 | AO61: =AN61*L61 -> 1661.156 | AP61: =AF61-AM61 -> 2373.08 | AQ61: =AP61-AO61 -> 711.924 | AR61: =AP61/AO61 -> 1.4285714
A62: ORD200060 | B62: =(RIGHT(A62, LEN(A62)-3))*1 -> 200060 | C62: 45525 | D62: 45525 | E62: =(TEXT(D62, "yyyy"))*1 -> 2024 | F62: =TEXT(D62, "mmmm") -> August | G62: =TEXT(D62, "dddd") -> Wednesday | H62: C39256 | I62: =(RIGHT(H62, LEN(H62)-1))*1 -> 39256 | J62: Desk | K62: =TRIM(PROPER(J62)) -> Desk | L62: 1 | M62: 417.1 | N62: =(TRIM(PROPER(M62)))*1 -> 417.1 | O62: 634 Main St | P62: =LEFT(O62, FIND(" ", O62)-1) -> 634 | Q62: =RIGHT(O62, LEN(O62) - FIND(" ", O62)) -> Main St | R62: Debit Card | S62: =TRIM(PROPER(R62)) -> Debit Card | T62: Returned | U62: =TRIM(PROPER(T62)) -> Returned | V62: TRK23412025 | W62: =RIGHT(V62, LEN(V62)-3) -> 23412025 | X62: 3 | Y62: FREESHIP | Z62: =TRIM(UPPER(IF(Y62="", "NO COUPON", Y62))) -> FREESHIP | AA62: =IF(Z62="NO COUPON","NO","YES") -> YES | AB62: Referral | AC62: =TRIM(PROPER(AB62)) -> Referral | AD62: 417.1 | AE62: 417.1 | AF62: =N62*L62 -> 417.1 | AG62: =_xlfn.XLOOKUP(H62, 'Customer Data'!A62,'Customer Data'!B62) -> Customer_62 | AH62: =_xlfn.XLOOKUP(H62,'Customer Data'!A62,'Customer Data'!C62) -> Female | AI62: =_xlfn.XLOOKUP(H62,'Customer Data'!A62,'Customer Data'!D62) -> 37 | AJ62: =_xlfn.XLOOKUP(H62,'Customer Data'!A62,'Customer Data'!E62) -> Abuja | AK62: =VLOOKUP(K62,'Product Category'!A:B,2,FALSE) -> Furniture | AL62: =VLOOKUP(Z62,Coupons!A:B,2,FALSE) -> 0 | AM62: =AE62*AL62 -> 0 | AN62: =N62*0.7 -> 291.97 | AO62: =AN62*L62 -> 291.97 | AP62: =AF62-AM62 -> 417.1 | AQ62: =AP62-AO62 -> 125.13 | AR62: =AP62/AO62 -> 1.4285714
A63: ORD200061 | B63: =(RIGHT(A63, LEN(A63)-3))*1 -> 200061 | C63: 45375 | D63: 45375 | E63: =(TEXT(D63, "yyyy"))*1 -> 2024 | F63: =TEXT(D63, "mmmm") -> March | G63: =TEXT(D63, "dddd") -> Sunday | H63: C61618 | I63: =(RIGHT(H63, LEN(H63)-1))*1 -> 61618 | J63: Desk | K63: =TRIM(PROPER(J63)) -> Desk | L63: 4 | M63: 122.2 | N63: =(TRIM(PROPER(M63)))*1 -> 122.2 | O63: 104 Main St | P63: =LEFT(O63, FIND(" ", O63)-1) -> 104 | Q63: =RIGHT(O63, LEN(O63) - FIND(" ", O63)) -> Main St | R63: Cash | S63: =TRIM(PROPER(R63)) -> Cash | T63: Delivered | U63: =TRIM(PROPER(T63)) -> Delivered | V63: TRK43458485 | W63: =RIGHT(V63, LEN(V63)-3) -> 43458485 | X63: 7 | Y63: FREESHIP | Z63: =TRIM(UPPER(IF(Y63="", "NO COUPON", Y63))) -> FREESHIP | AA63: =IF(Z63="NO COUPON","NO","YES") -> YES | AB63: Facebook | AC63: =TRIM(PROPER(AB63)) -> Facebook | AD63: 488.8 | AE63: 488.8 | AF63: =N63*L63 -> 488.8 | AG63: =_xlfn.XLOOKUP(H63, 'Customer Data'!A63,'Customer Data'!B63) -> Customer_63 | AH63: =_xlfn.XLOOKUP(H63,'Customer Data'!A63,'Customer Data'!C63) -> Male | AI63: =_xlfn.XLOOKUP(H63,'Customer Data'!A63,'Customer Data'!D63) -> 22 | AJ63: =_xlfn.XLOOKUP(H63,'Customer Data'!A63,'Customer Data'!E63) -> Lagos | AK63: =VLOOKUP(K63,'Product Category'!A:B,2,FALSE) -> Furniture | AL63: =VLOOKUP(Z63,Coupons!A:B,2,FALSE) -> 0 | AM63: =AE63*AL63 -> 0 | AN63: =N63*0.7 -> 85.54 | AO63: =AN63*L63 -> 342.16 | AP63: =AF63-AM63 -> 488.8 | AQ63: =AP63-AO63 -> 146.64 | AR63: =AP63/AO63 -> 1.4285714
A64: ORD200062 | B64: =(RIGHT(A64, LEN(A64)-3))*1 -> 200062 | C64: 45160 | D64: 45160 | E64: =(TEXT(D64, "yyyy"))*1 -> 2023 | F64: =TEXT(D64, "mmmm") -> August | G64: =TEXT(D64, "dddd") -> Tuesday | H64: C36497 | I64: =(RIGHT(H64, LEN(H64)-1))*1 -> 36497 | J64: Desk | K64: =TRIM(PROPER(J64)) -> Desk | L64: 2 | M64: 43.15 | N64: =(TRIM(PROPER(M64)))*1 -> 43.15 | O64: 691 Main St | P64: =LEFT(O64, FIND(" ", O64)-1) -> 691 | Q64: =RIGHT(O64, LEN(O64) - FIND(" ", O64)) -> Main St | R64: Debit Card | S64: =TRIM(PROPER(R64)) -> Debit Card | T64: Pending | U64: =TRIM(PROPER(T64)) -> Pending | V64: TRK12102911 | W64: =RIGHT(V64, LEN(V64)-3) -> 12102911 | X64: 3 | Y64: WINTER15 | Z64: =TRIM(UPPER(IF(Y64="", "NO COUPON", Y64))) -> WINTER15 | AA64: =IF(Z64="NO COUPON","NO","YES") -> YES | AB64: Email | AC64: =TRIM(PROPER(AB64)) -> Email | AD64: 86.3 | AE64: 86.3 | AF64: =N64*L64 -> 86.3 | AG64: =_xlfn.XLOOKUP(H64, 'Customer Data'!A64,'Customer Data'!B64) -> Customer_64 | AH64: =_xlfn.XLOOKUP(H64,'Customer Data'!A64,'Customer Data'!C64) -> Female | AI64: =_xlfn.XLOOKUP(H64,'Customer Data'!A64,'Customer Data'!D64) -> 46 | AJ64: =_xlfn.XLOOKUP(H64,'Customer Data'!A64,'Customer Data'!E64) -> Enugu | AK64: =VLOOKUP(K64,'Product Category'!A:B,2,FALSE) -> Furniture | AL64: =VLOOKUP(Z64,Coupons!A:B,2,FALSE) -> 0.15 | AM64: =AE64*AL64 -> 12.945 | AN64: =N64*0.7 -> 30.205 | AO64: =AN64*L64 -> 60.41 | AP64: =AF64-AM64 -> 73.355 | AQ64: =AP64-AO64 -> 12.945 | AR64: =AP64/AO64 -> 1.2142857
A65: ORD200063 | B65: =(RIGHT(A65, LEN(A65)-3))*1 -> 200063 | C65: 45690 | D65: 45690 | E65: =(TEXT(D65, "yyyy"))*1 -> 2025 | F65: =TEXT(D65, "mmmm") -> February | G65: =TEXT(D65, "dddd") -> Sunday | H65: C96695 | I65: =(RIGHT(H65, LEN(H65)-1))*1 -> 96695 | J65: Chair | K65: =TRIM(PROPER(J65)) -> Chair | L65: 1 | M65: 564.86 | N65: =(TRIM(PROPER(M65)))*1 -> 564.86 | O65: 813 Main St | P65: =LEFT(O65, FIND(" ", O65)-1) -> 813 | Q65: =RIGHT(O65, LEN(O65) - FIND(" ", O65)) -> Main St | R65: Debit Card | S65: =TRIM(PROPER(R65)) -> Debit Card | T65: Shipped | U65: =TRIM(PROPER(T65)) -> Shipped | V65: TRK64283851 | W65: =RIGHT(V65, LEN(V65)-3) -> 64283851 | X65: 6 | Y65: WINTER15 | Z65: =TRIM(UPPER(IF(Y65="", "NO COUPON", Y65))) -> WINTER15 | AA65: =IF(Z65="NO COUPON","NO","YES") -> YES | AB65: Referral | AC65: =TRIM(PROPER(AB65)) -> Referral | AD65: 564.86 | AE65: 564.86 | AF65: =N65*L65 -> 564.86 | AG65: =_xlfn.XLOOKUP(H65, 'Customer Data'!A65,'Customer Data'!B65) -> Customer_65 | AH65: =_xlfn.XLOOKUP(H65,'Customer Data'!A65,'Customer Data'!C65) -> Female | AI65: =_xlfn.XLOOKUP(H65,'Customer Data'!A65,'Customer Data'!D65) -> 25 | AJ65: =_xlfn.XLOOKUP(H65,'Customer Data'!A65,'Customer Data'!E65) -> Abuja | AK65: =VLOOKUP(K65,'Product Category'!A:B,2,FALSE) -> Furniture | AL65: =VLOOKUP(Z65,Coupons!A:B,2,FALSE) -> 0.15 | AM65: =AE65*AL65 -> 84.729 | AN65: =N65*0.7 -> 395.402 | AO65: =AN65*L65 -> 395.402 | AP65: =AF65-AM65 -> 480.131 | AQ65: =AP65-AO65 -> 84.729 | AR65: =AP65/AO65 -> 1.2142857
A66: ORD200064 | B66: =(RIGHT(A66, LEN(A66)-3))*1 -> 200064 | C66: 45833 | D66: 45833 | E66: =(TEXT(D66, "yyyy"))*1 -> 2025 | F66: =TEXT(D66, "mmmm") -> June | G66: =TEXT(D66, "dddd") -> Wednesday | H66: C49720 | I66: =(RIGHT(H66, LEN(H66)-1))*1 -> 49720 | J66: Printer | K66: =TRIM(PROPER(J66)) -> Printer | L66: 3 | M66: 130.61 | N66: =(TRIM(PROPER(M66)))*1 -> 130.61 | O66: 752 Main St | P66: =LEFT(O66, FIND(" ", O66)-1) -> 752 | Q66: =RIGHT(O66, LEN(O66) - FIND(" ", O66)) -> Main St | R66: Debit Card | S66: =TRIM(PROPER(R66)) -> Debit Card | T66: Cancelled | U66: =TRIM(PROPER(T66)) -> Cancelled | V66: TRK55785217 | W66: =RIGHT(V66, LEN(V66)-3) -> 55785217 | X66: 4 | Y66: FREESHIP | Z66: =TRIM(UPPER(IF(Y66="", "NO COUPON", Y66))) -> FREESHIP | AA66: =IF(Z66="NO COUPON","NO","YES") -> YES | AB66: Facebook | AC66: =TRIM(PROPER(AB66)) -> Facebook | AD66: 391.83 | AE66: 391.83 | AF66: =N66*L66 -> 391.83 | AG66: =_xlfn.XLOOKUP(H66, 'Customer Data'!A66,'Customer Data'!B66) -> Customer_66 | AH66: =_xlfn.XLOOKUP(H66,'Customer Data'!A66,'Customer Data'!C66) -> Male | AI66: =_xlfn.XLOOKUP(H66,'Customer Data'!A66,'Customer Data'!D66) -> 48 | AJ66: =_xlfn.XLOOKUP(H66,'Customer Data'!A66,'Customer Data'!E66) -> Port-Harcourt | AK66: =VLOOKUP(K66,'Product Category'!A:B,2,FALSE) -> Electronics | AL66: =VLOOKUP(Z66,Coupons!A:B,2,FALSE) -> 0 | AM66: =AE66*AL66 -> 0 | AN66: =N66*0.7 -> 91.427 | AO66: =AN66*L66 -> 274.281 | AP66: =AF66-AM66 -> 391.83 | AQ66: =AP66-AO66 -> 117.549 | AR66: =AP66/AO66 -> 1.4285714
A67: ORD200065 | B67: =(RIGHT(A67, LEN(A67)-3))*1 -> 200065 | C67: 45290 | D67: 45290 | E67: =(TEXT(D67, "yyyy"))*1 -> 2023 | F67: =TEXT(D67, "mmmm") -> December | G67: =TEXT(D67, "dddd") -> Saturday | H67: C97735 | I67: =(RIGHT(H67, LEN(H67)-1))*1 -> 97735 | J67: Monitor | K67: =TRIM(PROPER(J67)) -> Monitor | L67: 5 | M67: 81.7 | N67: =(TRIM(PROPER(M67)))*1 -> 81.7 | O67: 385 Main St | P67: =LEFT(O67, FIND(" ", O67)-1) -> 385 | Q67: =RIGHT(O67, LEN(O67) - FIND(" ", O67)) -> Main St | R67: Credit Card | S67: =TRIM(PROPER(R67)) -> Credit Card | T67: Delivered | U67: =TRIM(PROPER(T67)) -> Delivered | V67: TRK13743703 | W67: =RIGHT(V67, LEN(V67)-3) -> 13743703 | X67: 6 | Z67: =TRIM(UPPER(IF(Y67="", "NO COUPON", Y67))) -> NO COUPON | AA67: =IF(Z67="NO COUPON","NO","YES") -> NO | AB67: Instagram | AC67: =TRIM(PROPER(AB67)) -> Instagram | AD67: 408.5 | AE67: 408.5 | AF67: =N67*L67 -> 408.5 | AG67: =_xlfn.XLOOKUP(H67, 'Customer Data'!A67,'Customer Data'!B67) -> Customer_67 | AH67: =_xlfn.XLOOKUP(H67,'Customer Data'!A67,'Customer Data'!C67) -> Male | AI67: =_xlfn.XLOOKUP(H67,'Customer Data'!A67,'Customer Data'!D67) -> 52 | AJ67: =_xlfn.XLOOKUP(H67,'Customer Data'!A67,'Customer Data'!E67) -> Port-Harcourt | AK67: =VLOOKUP(K67,'Product Category'!A:B,2,FALSE) -> Electronics | AL67: =VLOOKUP(Z67,Coupons!A:B,2,FALSE) -> 0 | AM67: =AE67*AL67 -> 0 | AN67: =N67*0.7 -> 57.19 | AO67: =AN67*L67 -> 285.95 | AP67: =AF67-AM67 -> 408.5 | AQ67: =AP67-AO67 -> 122.55 | AR67: =AP67/AO67 -> 1.4285714
A68: ORD200066 | B68: =(RIGHT(A68, LEN(A68)-3))*1 -> 200066 | C68: 45611 | D68: 45611 | E68: =(TEXT(D68, "yyyy"))*1 -> 2024 | F68: =TEXT(D68, "mmmm") -> November | G68: =TEXT(D68, "dddd") -> Friday | H68: C18104 | I68: =(RIGHT(H68, LEN(H68)-1))*1 -> 18104 | J68: Chair | K68: =TRIM(PROPER(J68)) -> Chair | L68: 5 | M68: 127.18 | N68: =(TRIM(PROPER(M68)))*1 -> 127.18 | O68: 715 Main St | P68: =LEFT(O68, FIND(" ", O68)-1) -> 715 | Q68: =RIGHT(O68, LEN(O68) - FIND(" ", O68)) -> Main St | R68: Cash | S68: =TRIM(PROPER(R68)) -> Cash | T68: Cancelled | U68: =TRIM(PROPER(T68)) -> Cancelled | V68: TRK15488568 | W68: =RIGHT(V68, LEN(V68)-3) -> 15488568 | X68: 9 | Y68: SAVE10 | Z68: =TRIM(UPPER(IF(Y68="", "NO COUPON", Y68))) -> SAVE10 | AA68: =IF(Z68="NO COUPON","NO","YES") -> YES | AB68: Referral | AC68: =TRIM(PROPER(AB68)) -> Referral | AD68: 635.9 | AE68: 635.9 | AF68: =N68*L68 -> 635.9 | AG68: =_xlfn.XLOOKUP(H68, 'Customer Data'!A68,'Customer Data'!B68) -> Customer_68 | AH68: =_xlfn.XLOOKUP(H68,'Customer Data'!A68,'Customer Data'!C68) -> Male | AI68: =_xlfn.XLOOKUP(H68,'Customer Data'!A68,'Customer Data'!D68) -> 53 | AJ68: =_xlfn.XLOOKUP(H68,'Customer Data'!A68,'Customer Data'!E68) -> Lagos | AK68: =VLOOKUP(K68,'Product Category'!A:B,2,FALSE) -> Furniture | AL68: =VLOOKUP(Z68,Coupons!A:B,2,FALSE) -> 0.1 | AM68: =AE68*AL68 -> 63.59 | AN68: =N68*0.7 -> 89.026 | AO68: =AN68*L68 -> 445.13 | AP68: =AF68-AM68 -> 572.31 | AQ68: =AP68-AO68 -> 127.18 | AR68: =AP68/AO68 -> 1.2857143
A69: ORD200067 | B69: =(RIGHT(A69, LEN(A69)-3))*1 -> 200067 | C69: 45635 | D69: 45635 | E69: =(TEXT(D69, "yyyy"))*1 -> 2024 | F69: =TEXT(D69, "mmmm") -> December | G69: =TEXT(D69, "dddd") -> Monday | H69: C25587 | I69: =(RIGHT(H69, LEN(H69)-1))*1 -> 25587 | J69: Printer | K69: =TRIM(PROPER(J69)) -> Printer | L69: 4 | M69: 12.1 | N69: =(TRIM(PROPER(M69)))*1 -> 12.1 | O69: 440 Main St | P69: =LEFT(O69, FIND(" ", O69)-1) -> 440 | Q69: =RIGHT(O69, LEN(O69) - FIND(" ", O69)) -> Main St | R69: Debit Card | S69: =TRIM(PROPER(R69)) -> Debit Card | T69: Cancelled | U69: =TRIM(PROPER(T69)) -> Cancelled | V69: TRK55105323 | W69: =RIGHT(V69, LEN(V69)-3) -> 55105323 | X69: 8 | Z69: =TRIM(UPPER(IF(Y69="", "NO COUPON", Y69))) -> NO COUPON | AA69: =IF(Z69="NO COUPON","NO","YES") -> NO | AB69: Google | AC69: =TRIM(PROPER(AB69)) -> Google | AD69: 48.4 | AE69: 48.4 | AF69: =N69*L69 -> 48.4 | AG69: =_xlfn.XLOOKUP(H69, 'Customer Data'!A69,'Customer Data'!B69) -> Customer_69 | AH69: =_xlfn.XLOOKUP(H69,'Customer Data'!A69,'Customer Data'!C69) -> Female | AI69: =_xlfn.XLOOKUP(H69,'Customer Data'!A69,'Customer Data'!D69) -> 44 | AJ69: =_xlfn.XLOOKUP(H69,'Customer Data'!A69,'Customer Data'!E69) -> Port-Harcourt | AK69: =VLOOKUP(K69,'Product Category'!A:B,2,FALSE) -> Electronics | AL69: =VLOOKUP(Z69,Coupons!A:B,2,FALSE) -> 0 | AM69: =AE69*AL69 -> 0 | AN69: =N69*0.7 -> 8.47 | AO69: =AN69*L69 -> 33.88 | AP69: =AF69-AM69 -> 48.4 | AQ69: =AP69-AO69 -> 14.52 | AR69: =AP69/AO69 -> 1.4285714
A70: ORD200068 | B70: =(RIGHT(A70, LEN(A70)-3))*1 -> 200068 | C70: 45271 | D70: 45271 | E70: =(TEXT(D70, "yyyy"))*1 -> 2023 | F70: =TEXT(D70, "mmmm") -> December | G70: =TEXT(D70, "dddd") -> Monday | H70: C41598 | I70: =(RIGHT(H70, LEN(H70)-1))*1 -> 41598 | J70: Chair | K70: =TRIM(PROPER(J70)) -> Chair | L70: 3 | M70: 490.92 | N70: =(TRIM(PROPER(M70)))*1 -> 490.92 | O70: 709 Main St | P70: =LEFT(O70, FIND(" ", O70)-1) -> 709 | Q70: =RIGHT(O70, LEN(O70) - FIND(" ", O70)) -> Main St | R70: Credit Card | S70: =TRIM(PROPER(R70)) -> Credit Card | T70: Pending | U70: =TRIM(PROPER(T70)) -> Pending | V70: TRK81665940 | W70: =RIGHT(V70, LEN(V70)-3) -> 81665940 | X70: 5 | Y70: FREESHIP | Z70: =TRIM(UPPER(IF(Y70="", "NO COUPON", Y70))) -> FREESHIP | AA70: =IF(Z70="NO COUPON","NO","YES") -> YES | AB70: Email | AC70: =TRIM(PROPER(AB70)) -> Email | AD70: 1472.76 | AE70: 1472.76 | AF70: =N70*L70 -> 1472.76 | AG70: =_xlfn.XLOOKUP(H70, 'Customer Data'!A70,'Customer Data'!B70) -> Customer_70 | AH70: =_xlfn.XLOOKUP(H70,'Customer Data'!A70,'Customer Data'!C70) -> Male | AI70: =_xlfn.XLOOKUP(H70,'Customer Data'!A70,'Customer Data'!D70) -> 42 | AJ70: =_xlfn.XLOOKUP(H70,'Customer Data'!A70,'Customer Data'!E70) -> Abuja | AK70: =VLOOKUP(K70,'Product Category'!A:B,2,FALSE) -> Furniture | AL70: =VLOOKUP(Z70,Coupons!A:B,2,FALSE) -> 0 | AM70: =AE70*AL70 -> 0 | AN70: =N70*0.7 -> 343.644 | AO70: =AN70*L70 -> 1030.932 | AP70: =AF70-AM70 -> 1472.76 | AQ70: =AP70-AO70 -> 441.828 | AR70: =AP70/AO70 -> 1.4285714
A71: ORD200069 | B71: =(RIGHT(A71, LEN(A71)-3))*1 -> 200069 | C71: 45057 | D71: 45057 | E71: =(TEXT(D71, "yyyy"))*1 -> 2023 | F71: =TEXT(D71, "mmmm") -> May | G71: =TEXT(D71, "dddd") -> Thursday | H71: C43338 | I71: =(RIGHT(H71, LEN(H71)-1))*1 -> 43338 | J71: Monitor | K71: =TRIM(PROPER(J71)) -> Monitor | L71: 3 | M71: 478.65 | N71: =(TRIM(PROPER(M71)))*1 -> 478.65 | O71: 552 Main St | P71: =LEFT(O71, FIND(" ", O71)-1) -> 552 | Q71: =RIGHT(O71, LEN(O71) - FIND(" ", O71)) -> Main St | R71: Online | S71: =TRIM(PROPER(R71)) -> Online | T71: Shipped | U71: =TRIM(PROPER(T71)) -> Shipped | V71: TRK35241775 | W71: =RIGHT(V71, LEN(V71)-3) -> 35241775 | X71: 4 | Z71: =TRIM(UPPER(IF(Y71="", "NO COUPON", Y71))) -> NO COUPON | AA71: =IF(Z71="NO COUPON","NO","YES") -> NO | AB71: Referral | AC71: =TRIM(PROPER(AB71)) -> Referral | AD71: 1435.95 | AE71: 1435.95 | AF71: =N71*L71 -> 1435.95 | AG71: =_xlfn.XLOOKUP(H71, 'Customer Data'!A71,'Customer Data'!B71) -> Customer_71 | AH71: =_xlfn.XLOOKUP(H71,'Customer Data'!A71,'Customer Data'!C71) -> Female | AI71: =_xlfn.XLOOKUP(H71,'Customer Data'!A71,'Customer Data'!D71) -> 32 | AJ71: =_xlfn.XLOOKUP(H71,'Customer Data'!A71,'Customer Data'!E71) -> Enugu | AK71: =VLOOKUP(K71,'Product Category'!A:B,2,FALSE) -> Electronics | AL71: =VLOOKUP(Z71,Coupons!A:B,2,FALSE) -> 0 | AM71: =AE71*AL71 -> 0 | AN71: =N71*0.7 -> 335.055 | AO71: =AN71*L71 -> 1005.165 | AP71: =AF71-AM71 -> 1435.95 | AQ71: =AP71-AO71 -> 430.785 | AR71: =AP71/AO71 -> 1.4285714
A72: ORD200070 | B72: =(RIGHT(A72, LEN(A72)-3))*1 -> 200070 | C72: 45072 | D72: 45072 | E72: =(TEXT(D72, "yyyy"))*1 -> 2023 | F72: =TEXT(D72, "mmmm") -> May | G72: =TEXT(D72, "dddd") -> Friday | H72: C25123 | I72: =(RIGHT(H72, LEN(H72)-1))*1 -> 25123 | J72: Desk | K72: =TRIM(PROPER(J72)) -> Desk | L72: 1 | M72: 629.21 | N72: =(TRIM(PROPER(M72)))*1 -> 629.21 | O72: 384 Main St | P72: =LEFT(O72, FIND(" ", O72)-1) -> 384 | Q72: =RIGHT(O72, LEN(O72) - FIND(" ", O72)) -> Main St | R72: Gift Card | S72: =TRIM(PROPER(R72)) -> Gift Card | T72: Pending | U72: =TRIM(PROPER(T72)) -> Pending | V72: TRK27812282 | W72: =RIGHT(V72, LEN(V72)-3) -> 27812282 | X72: 2 | Y72: FREESHIP | Z72: =TRIM(UPPER(IF(Y72="", "NO COUPON", Y72))) -> FREESHIP | AA72: =IF(Z72="NO COUPON","NO","YES") -> YES | AB72: Instagram | AC72: =TRIM(PROPER(AB72)) -> Instagram | AD72: 629.21 | AE72: 629.21 | AF72: =N72*L72 -> 629.21 | AG72: =_xlfn.XLOOKUP(H72, 'Customer Data'!A72,'Customer Data'!B72) -> Customer_72 | AH72: =_xlfn.XLOOKUP(H72,'Customer Data'!A72,'Customer Data'!C72) -> Male | AI72: =_xlfn.XLOOKUP(H72,'Customer Data'!A72,'Customer Data'!D72) -> 20 | AJ72: =_xlfn.XLOOKUP(H72,'Customer Data'!A72,'Customer Data'!E72) -> Enugu | AK72: =VLOOKUP(K72,'Product Category'!A:B,2,FALSE) -> Furniture | AL72: =VLOOKUP(Z72,Coupons!A:B,2,FALSE) -> 0 | AM72: =AE72*AL72 -> 0 | AN72: =N72*0.7 -> 440.447 | AO72: =AN72*L72 -> 440.447 | AP72: =AF72-AM72 -> 629.21 | AQ72: =AP72-AO72 -> 188.763 | AR72: =AP72/AO72 -> 1.4285714
A73: ORD200071 | B73: =(RIGHT(A73, LEN(A73)-3))*1 -> 200071 | C73: 45818 | D73: 45818 | E73: =(TEXT(D73, "yyyy"))*1 -> 2025 | F73: =TEXT(D73, "mmmm") -> June | G73: =TEXT(D73, "dddd") -> Tuesday | H73: C37454 | I73: =(RIGHT(H73, LEN(H73)-1))*1 -> 37454 | J73: Monitor | K73: =TRIM(PROPER(J73)) -> Monitor | L73: 3 | M73: 434.45 | N73: =(TRIM(PROPER(M73)))*1 -> 434.45 | O73: 923 Main St | P73: =LEFT(O73, FIND(" ", O73)-1) -> 923 | Q73: =RIGHT(O73, LEN(O73) - FIND(" ", O73)) -> Main St | R73: Credit Card | S73: =TRIM(PROPER(R73)) -> Credit Card | T73: Pending | U73: =TRIM(PROPER(T73)) -> Pending | V73: TRK28252730 | W73: =RIGHT(V73, LEN(V73)-3) -> 28252730 | X73: 4 | Z73: =TRIM(UPPER(IF(Y73="", "NO COUPON", Y73))) -> NO COUPON | AA73: =IF(Z73="NO COUPON","NO","YES") -> NO | AB73: Referral | AC73: =TRIM(PROPER(AB73)) -> Referral | AD73: 1303.35 | AE73: 1303.35 | AF73: =N73*L73 -> 1303.35 | AG73: =_xlfn.XLOOKUP(H73, 'Customer Data'!A73,'Customer Data'!B73) -> Customer_73 | AH73: =_xlfn.XLOOKUP(H73,'Customer Data'!A73,'Customer Data'!C73) -> Female | AI73: =_xlfn.XLOOKUP(H73,'Customer Data'!A73,'Customer Data'!D73) -> 34 | AJ73: =_xlfn.XLOOKUP(H73,'Customer Data'!A73,'Customer Data'!E73) -> Lagos | AK73: =VLOOKUP(K73,'Product Category'!A:B,2,FALSE) -> Electronics | AL73: =VLOOKUP(Z73,Coupons!A:B,2,FALSE) -> 0 | AM73: =AE73*AL73 -> 0 | AN73: =N73*0.7 -> 304.115 | AO73: =AN73*L73 -> 912.345 | AP73: =AF73-AM73 -> 1303.35 | AQ73: =AP73-AO73 -> 391.005 | AR73: =AP73/AO73 -> 1.4285714
A74: ORD200072 | B74: =(RIGHT(A74, LEN(A74)-3))*1 -> 200072 | C74: 45648 | D74: 45648 | E74: =(TEXT(D74, "yyyy"))*1 -> 2024 | F74: =TEXT(D74, "mmmm") -> December | G74: =TEXT(D74, "dddd") -> Sunday | H74: C19451 | I74: =(RIGHT(H74, LEN(H74)-1))*1 -> 19451 | J74: Tablet | K74: =TRIM(PROPER(J74)) -> Tablet | L74: 4 | M74: 589.44 | N74: =(TRIM(PROPER(M74)))*1 -> 589.44 | O74: 942 Main St | P74: =LEFT(O74, FIND(" ", O74)-1) -> 942 | Q74: =RIGHT(O74, LEN(O74) - FIND(" ", O74)) -> Main St | R74: Gift Card | S74: =TRIM(PROPER(R74)) -> Gift Card | T74: Returned | U74: =TRIM(PROPER(T74)) -> Returned | V74: TRK87787793 | W74: =RIGHT(V74, LEN(V74)-3) -> 87787793 | X74: 5 | Z74: =TRIM(UPPER(IF(Y74="", "NO COUPON", Y74))) -> NO COUPON | AA74: =IF(Z74="NO COUPON","NO","YES") -> NO | AB74: Facebook | AC74: =TRIM(PROPER(AB74)) -> Facebook | AD74: 2357.76 | AE74: 2357.76 | AF74: =N74*L74 -> 2357.76 | AG74: =_xlfn.XLOOKUP(H74, 'Customer Data'!A74,'Customer Data'!B74) -> Customer_74 | AH74: =_xlfn.XLOOKUP(H74,'Customer Data'!A74,'Customer Data'!C74) -> Male | AI74: =_xlfn.XLOOKUP(H74,'Customer Data'!A74,'Customer Data'!D74) -> 50 | AJ74: =_xlfn.XLOOKUP(H74,'Customer Data'!A74,'Customer Data'!E74) -> Kano | AK74: =VLOOKUP(K74,'Product Category'!A:B,2,FALSE) -> Electronics | AL74: =VLOOKUP(Z74,Coupons!A:B,2,FALSE) -> 0 | AM74: =AE74*AL74 -> 0 | AN74: =N74*0.7 -> 412.608 | AO74: =AN74*L74 -> 1650.432 | AP74: =AF74-AM74 -> 2357.76 | AQ74: =AP74-AO74 -> 707.328 | AR74: =AP74/AO74 -> 1.4285714
A75: ORD200073 | B75: =(RIGHT(A75, LEN(A75)-3))*1 -> 200073 | C75: 45049 | D75: 45049 | E75: =(TEXT(D75, "yyyy"))*1 -> 2023 | F75: =TEXT(D75, "mmmm") -> May | G75: =TEXT(D75, "dddd") -> Wednesday | H75: C17269 | I75: =(RIGHT(H75, LEN(H75)-1))*1 -> 17269 | J75: Monitor | K75: =TRIM(PROPER(J75)) -> Monitor | L75: 4 | M75: 433.45 | N75: =(TRIM(PROPER(M75)))*1 -> 433.45 | O75: 129 Main St | P75: =LEFT(O75, FIND(" ", O75)-1) -> 129 | Q75: =RIGHT(O75, LEN(O75) - FIND(" ", O75)) -> Main St | R75: Gift Card | S75: =TRIM(PROPER(R75)) -> Gift Card | T75: Cancelled | U75: =TRIM(PROPER(T75)) -> Cancelled | V75: TRK79608389 | W75: =RIGHT(V75, LEN(V75)-3) -> 79608389 | X75: 4 | Z75: =TRIM(UPPER(IF(Y75="", "NO COUPON", Y75))) -> NO COUPON | AA75: =IF(Z75="NO COUPON","NO","YES") -> NO | AB75: Facebook | AC75: =TRIM(PROPER(AB75)) -> Facebook | AD75: 1733.8 | AE75: 1733.8 | AF75: =N75*L75 -> 1733.8 | AG75: =_xlfn.XLOOKUP(H75, 'Customer Data'!A75,'Customer Data'!B75) -> Customer_75 | AH75: =_xlfn.XLOOKUP(H75,'Customer Data'!A75,'Customer Data'!C75) -> Male | AI75: =_xlfn.XLOOKUP(H75,'Customer Data'!A75,'Customer Data'!D75) -> 38 | AJ75: =_xlfn.XLOOKUP(H75,'Customer Data'!A75,'Customer Data'!E75) -> Lagos | AK75: =VLOOKUP(K75,'Product Category'!A:B,2,FALSE) -> Electronics | AL75: =VLOOKUP(Z75,Coupons!A:B,2,FALSE) -> 0 | AM75: =AE75*AL75 -> 0 | AN75: =N75*0.7 -> 303.415 | AO75: =AN75*L75 -> 1213.66 | AP75: =AF75-AM75 -> 1733.8 | AQ75: =AP75-AO75 -> 520.14 | AR75: =AP75/AO75 -> 1.4285714
A76: ORD200074 | B76: =(RIGHT(A76, LEN(A76)-3))*1 -> 200074 | C76: 45101 | D76: 45101 | E76: =(TEXT(D76, "yyyy"))*1 -> 2023 | F76: =TEXT(D76, "mmmm") -> June | G76: =TEXT(D76, "dddd") -> Saturday | H76: C25382 | I76: =(RIGHT(H76, LEN(H76)-1))*1 -> 25382 | J76: Phone | K76: =TRIM(PROPER(J76)) -> Phone | L76: 5 | M76: 90.87 | N76: =(TRIM(PROPER(M76)))*1 -> 90.87 | O76: 622 Main St | P76: =LEFT(O76, FIND(" ", O76)-1) -> 622 | Q76: =RIGHT(O76, LEN(O76) - FIND(" ", O76)) -> Main St | R76: Cash | S76: =TRIM(PROPER(R76)) -> Cash | T76: Pending | U76: =TRIM(PROPER(T76)) -> Pending | V76: TRK64691287 | W76: =RIGHT(V76, LEN(V76)-3) -> 64691287 | X76: 5 | Z76: =TRIM(UPPER(IF(Y76="", "NO COUPON", Y76))) -> NO COUPON | AA76: =IF(Z76="NO COUPON","NO","YES") -> NO | AB76: Instagram | AC76: =TRIM(PROPER(AB76)) -> Instagram | AD76: 454.35 | AE76: 454.35 | AF76: =N76*L76 -> 454.35 | AG76: =_xlfn.XLOOKUP(H76, 'Customer Data'!A76,'Customer Data'!B76) -> Customer_76 | AH76: =_xlfn.XLOOKUP(H76,'Customer Data'!A76,'Customer Data'!C76) -> Male | AI76: =_xlfn.XLOOKUP(H76,'Customer Data'!A76,'Customer Data'!D76) -> 32 | AJ76: =_xlfn.XLOOKUP(H76,'Customer Data'!A76,'Customer Data'!E76) -> Abuja | AK76: =VLOOKUP(K76,'Product Category'!A:B,2,FALSE) -> Electronics | AL76: =VLOOKUP(Z76,Coupons!A:B,2,FALSE) -> 0 | AM76: =AE76*AL76 -> 0 | AN76: =N76*0.7 -> 63.609 | AO76: =AN76*L76 -> 318.045 | AP76: =AF76-AM76 -> 454.35 | AQ76: =AP76-AO76 -> 136.305 | AR76: =AP76/AO76 -> 1.4285714
A77: ORD200075 | B77: =(RIGHT(A77, LEN(A77)-3))*1 -> 200075 | C77: 45195 | D77: 45195 | E77: =(TEXT(D77, "yyyy"))*1 -> 2023 | F77: =TEXT(D77, "mmmm") -> September | G77: =TEXT(D77, "dddd") -> Tuesday | H77: C80651 | I77: =(RIGHT(H77, LEN(H77)-1))*1 -> 80651 | J77: Tablet | K77: =TRIM(PROPER(J77)) -> Tablet | L77: 3 | M77: 398.17 | N77: =(TRIM(PROPER(M77)))*1 -> 398.17 | O77: 917 Main St | P77: =LEFT(O77, FIND(" ", O77)-1) -> 917 | Q77: =RIGHT(O77, LEN(O77) - FIND(" ", O77)) -> Main St | R77: Debit Card | S77: =TRIM(PROPER(R77)) -> Debit Card | T77: Delivered | U77: =TRIM(PROPER(T77)) -> Delivered | V77: TRK14846720 | W77: =RIGHT(V77, LEN(V77)-3) -> 14846720 | X77: 5 | Y77: SAVE10 | Z77: =TRIM(UPPER(IF(Y77="", "NO COUPON", Y77))) -> SAVE10 | AA77: =IF(Z77="NO COUPON","NO","YES") -> YES | AB77: Email | AC77: =TRIM(PROPER(AB77)) -> Email | AD77: 1194.51 | AE77: 1194.51 | AF77: =N77*L77 -> 1194.51 | AG77: =_xlfn.XLOOKUP(H77, 'Customer Data'!A77,'Customer Data'!B77) -> Customer_77 | AH77: =_xlfn.XLOOKUP(H77,'Customer Data'!A77,'Customer Data'!C77) -> Female | AI77: =_xlfn.XLOOKUP(H77,'Customer Data'!A77,'Customer Data'!D77) -> 53 | AJ77: =_xlfn.XLOOKUP(H77,'Customer Data'!A77,'Customer Data'!E77) -> Lagos | AK77: =VLOOKUP(K77,'Product Category'!A:B,2,FALSE) -> Electronics | AL77: =VLOOKUP(Z77,Coupons!A:B,2,FALSE) -> 0.1 | AM77: =AE77*AL77 -> 119.451 | AN77: =N77*0.7 -> 278.719 | AO77: =AN77*L77 -> 836.157 | AP77: =AF77-AM77 -> 1075.059 | AQ77: =AP77-AO77 -> 238.902 | AR77: =AP77/AO77 -> 1.2857143
A78: ORD200076 | B78: =(RIGHT(A78, LEN(A78)-3))*1 -> 200076 | C78: 45382 | D78: 45382 | E78: =(TEXT(D78, "yyyy"))*1 -> 2024 | F78: =TEXT(D78, "mmmm") -> March | G78: =TEXT(D78, "dddd") -> Sunday | H78: C58638 | I78: =(RIGHT(H78, LEN(H78)-1))*1 -> 58638 | J78: Laptop | K78: =TRIM(PROPER(J78)) -> Laptop | L78: 4 | M78: 382.88 | N78: =(TRIM(PROPER(M78)))*1 -> 382.88 | O78: 239 Main St | P78: =LEFT(O78, FIND(" ", O78)-1) -> 239 | Q78: =RIGHT(O78, LEN(O78) - FIND(" ", O78)) -> Main St | R78: Cash | S78: =TRIM(PROPER(R78)) -> Cash | T78: Cancelled | U78: =TRIM(PROPER(T78)) -> Cancelled | V78: TRK38224871 | W78: =RIGHT(V78, LEN(V78)-3) -> 38224871 | X78: 6 | Y78: WINTER15 | Z78: =TRIM(UPPER(IF(Y78="", "NO COUPON", Y78))) -> WINTER15 | AA78: =IF(Z78="NO COUPON","NO","YES") -> YES | AB78: Email | AC78: =TRIM(PROPER(AB78)) -> Email | AD78: 1531.52 | AE78: 1531.52 | AF78: =N78*L78 -> 1531.52 | AG78: =_xlfn.XLOOKUP(H78, 'Customer Data'!A78,'Customer Data'!B78) -> Customer_78 | AH78: =_xlfn.XLOOKUP(H78,'Customer Data'!A78,'Customer Data'!C78) -> Female | AI78: =_xlfn.XLOOKUP(H78,'Customer Data'!A78,'Customer Data'!D78) -> 28 | AJ78: =_xlfn.XLOOKUP(H78,'Customer Data'!A78,'Customer Data'!E78) -> Lagos | AK78: =VLOOKUP(K78,'Product Category'!A:B,2,FALSE) -> Electronics | AL78: =VLOOKUP(Z78,Coupons!A:B,2,FALSE) -> 0.15 | AM78: =AE78*AL78 -> 229.728 | AN78: =N78*0.7 -> 268.016 | AO78: =AN78*L78 -> 1072.064 | AP78: =AF78-AM78 -> 1301.792 | AQ78: =AP78-AO78 -> 229.728 | AR78: =AP78/AO78 -> 1.2142857
A79: ORD200077 | B79: =(RIGHT(A79, LEN(A79)-3))*1 -> 200077 | C79: 45436 | D79: 45436 | E79: =(TEXT(D79, "yyyy"))*1 -> 2024 | F79: =TEXT(D79, "mmmm") -> May | G79: =TEXT(D79, "dddd") -> Friday | H79: C50121 | I79: =(RIGHT(H79, LEN(H79)-1))*1 -> 50121 | J79: Phone | K79: =TRIM(PROPER(J79)) -> Phone | L79: 1 | M79: 583.18 | N79: =(TRIM(PROPER(M79)))*1 -> 583.18 | O79: 348 Main St | P79: =LEFT(O79, FIND(" ", O79)-1) -> 348 | Q79: =RIGHT(O79, LEN(O79) - FIND(" ", O79)) -> Main St | R79: Credit Card | S79: =TRIM(PROPER(R79)) -> Credit Card | T79: Returned | U79: =TRIM(PROPER(T79)) -> Returned | V79: TRK79810059 | W79: =RIGHT(V79, LEN(V79)-3) -> 79810059 | X79: 5 | Z79: =TRIM(UPPER(IF(Y79="", "NO COUPON", Y79))) -> NO COUPON | AA79: =IF(Z79="NO COUPON","NO","YES") -> NO | AB79: Google | AC79: =TRIM(PROPER(AB79)) -> Google | AD79: 583.18 | AE79: 583.18 | AF79: =N79*L79 -> 583.18 | AG79: =_xlfn.XLOOKUP(H79, 'Customer Data'!A79,'Customer Data'!B79) -> Customer_79 | AH79: =_xlfn.XLOOKUP(H79,'Customer Data'!A79,'Customer Data'!C79) -> Female | AI79: =_xlfn.XLOOKUP(H79,'Customer Data'!A79,'Customer Data'!D79) -> 20 | AJ79: =_xlfn.XLOOKUP(H79,'Customer Data'!A79,'Customer Data'!E79) -> Enugu | AK79: =VLOOKUP(K79,'Product Category'!A:B,2,FALSE) -> Electronics | AL79: =VLOOKUP(Z79,Coupons!A:B,2,FALSE) -> 0 | AM79: =AE79*AL79 -> 0 | AN79: =N79*0.7 -> 408.226 | AO79: =AN79*L79 -> 408.226 | AP79: =AF79-AM79 -> 583.18 | AQ79: =AP79-AO79 -> 174.954 | AR79: =AP79/AO79 -> 1.4285714
A80: ORD200078 | B80: =(RIGHT(A80, LEN(A80)-3))*1 -> 200078 | C80: 45510 | D80: 45510 | E80: =(TEXT(D80, "yyyy"))*1 -> 2024 | F80: =TEXT(D80, "mmmm") -> August | G80: =TEXT(D80, "dddd") -> Tuesday | H80: C32029 | I80: =(RIGHT(H80, LEN(H80)-1))*1 -> 32029 | J80: Printer | K80: =TRIM(PROPER(J80)) -> Printer | L80: 4 | M80: 175.36 | N80: =(TRIM(PROPER(M80)))*1 -> 175.36 | O80: 146 Main St | P80: =LEFT(O80, FIND(" ", O80)-1) -> 146 | Q80: =RIGHT(O80, LEN(O80) - FIND(" ", O80)) -> Main St | R80: Debit Card | S80: =TRIM(PROPER(R80)) -> Debit Card | T80: Delivered | U80: =TRIM(PROPER(T80)) -> Delivered | V80: TRK68535532 | W80: =RIGHT(V80, LEN(V80)-3) -> 68535532 | X80: 4 | Y80: FREESHIP | Z80: =TRIM(UPPER(IF(Y80="", "NO COUPON", Y80))) -> FREESHIP | AA80: =IF(Z80="NO COUPON","NO","YES") -> YES | AB80: Instagram | AC80: =TRIM(PROPER(AB80)) -> Instagram | AD80: 701.44 | AE80: 701.44 | AF80: =N80*L80 -> 701.44 | AG80: =_xlfn.XLOOKUP(H80, 'Customer Data'!A80,'Customer Data'!B80) -> Customer_80 | AH80: =_xlfn.XLOOKUP(H80,'Customer Data'!A80,'Customer Data'!C80) -> Female | AI80: =_xlfn.XLOOKUP(H80,'Customer Data'!A80,'Customer Data'!D80) -> 45 | AJ80: =_xlfn.XLOOKUP(H80,'Customer Data'!A80,'Customer Data'!E80) -> Abuja | AK80: =VLOOKUP(K80,'Product Category'!A:B,2,FALSE) -> Electronics | AL80: =VLOOKUP(Z80,Coupons!A:B,2,FALSE) -> 0 | AM80: =AE80*AL80 -> 0 | AN80: =N80*0.7 -> 122.752 | AO80: =AN80*L80 -> 491.008 | AP80: =AF80-AM80 -> 701.44 | AQ80: =AP80-AO80 -> 210.432 | AR80: =AP80/AO80 -> 1.4285714
A81: ORD200079 | B81: =(RIGHT(A81, LEN(A81)-3))*1 -> 200079 | C81: 45726 | D81: 45726 | E81: =(TEXT(D81, "yyyy"))*1 -> 2025 | F81: =TEXT(D81, "mmmm") -> March | G81: =TEXT(D81, "dddd") -> Monday | H81: C76700 | I81: =(RIGHT(H81, LEN(H81)-1))*1 -> 76700 | J81: Tablet | K81: =TRIM(PROPER(J81)) -> Tablet | L81: 2 | M81: 311.91 | N81: =(TRIM(PROPER(M81)))*1 -> 311.91 | O81: 103 Main St | P81: =LEFT(O81, FIND(" ", O81)-1) -> 103 | Q81: =RIGHT(O81, LEN(O81) - FIND(" ", O81)) -> Main St | R81: Online | S81: =TRIM(PROPER(R81)) -> Online | T81: Shipped | U81: =TRIM(PROPER(T81)) -> Shipped | V81: TRK13036341 | W81: =RIGHT(V81, LEN(V81)-3) -> 13036341 | X81: 2 | Z81: =TRIM(UPPER(IF(Y81="", "NO COUPON", Y81))) -> NO COUPON | AA81: =IF(Z81="NO COUPON","NO","YES") -> NO | AB81: Facebook | AC81: =TRIM(PROPER(AB81)) -> Facebook | AD81: 623.82 | AE81: 623.82 | AF81: =N81*L81 -> 623.82 | AG81: =_xlfn.XLOOKUP(H81, 'Customer Data'!A81,'Customer Data'!B81) -> Customer_81 | AH81: =_xlfn.XLOOKUP(H81,'Customer Data'!A81,'Customer Data'!C81) -> Female | AI81: =_xlfn.XLOOKUP(H81,'Customer Data'!A81,'Customer Data'!D81) -> 38 | AJ81: =_xlfn.XLOOKUP(H81,'Customer Data'!A81,'Customer Data'!E81) -> Port-Harcourt | AK81: =VLOOKUP(K81,'Product Category'!A:B,2,FALSE) -> Electronics | AL81: =VLOOKUP(Z81,Coupons!A:B,2,FALSE) -> 0 | AM81: =AE81*AL81 -> 0 | AN81: =N81*0.7 -> 218.337 | AO81: =AN81*L81 -> 436.674 | AP81: =AF81-AM81 -> 623.82 | AQ81: =AP81-AO81 -> 187.146 | AR81: =AP81/AO81 -> 1.4285714
A82: ORD200080 | B82: =(RIGHT(A82, LEN(A82)-3))*1 -> 200080 | C82: 45104 | D82: 45104 | E82: =(TEXT(D82, "yyyy"))*1 -> 2023 | F82: =TEXT(D82, "mmmm") -> June | G82: =TEXT(D82, "dddd") -> Tuesday | H82: C29041 | I82: =(RIGHT(H82, LEN(H82)-1))*1 -> 29041 | J82: Phone | K82: =TRIM(PROPER(J82)) -> Phone | L82: 3 | M82: 589.56 | N82: =(TRIM(PROPER(M82)))*1 -> 589.56 | O82: 591 Main St | P82: =LEFT(O82, FIND(" ", O82)-1) -> 591 | Q82: =RIGHT(O82, LEN(O82) - FIND(" ", O82)) -> Main St | R82: Online | S82: =TRIM(PROPER(R82)) -> Online | T82: Returned | U82: =TRIM(PROPER(T82)) -> Returned | V82: TRK28840655 | W82: =RIGHT(V82, LEN(V82)-3) -> 28840655 | X82: 6 | Z82: =TRIM(UPPER(IF(Y82="", "NO COUPON", Y82))) -> NO COUPON | AA82: =IF(Z82="NO COUPON","NO","YES") -> NO | AB82: Facebook | AC82: =TRIM(PROPER(AB82)) -> Facebook | AD82: 1768.68 | AE82: 1768.68 | AF82: =N82*L82 -> 1768.68 | AG82: =_xlfn.XLOOKUP(H82, 'Customer Data'!A82,'Customer Data'!B82) -> Customer_82 | AH82: =_xlfn.XLOOKUP(H82,'Customer Data'!A82,'Customer Data'!C82) -> Female | AI82: =_xlfn.XLOOKUP(H82,'Customer Data'!A82,'Customer Data'!D82) -> 42 | AJ82: =_xlfn.XLOOKUP(H82,'Customer Data'!A82,'Customer Data'!E82) -> Kano | AK82: =VLOOKUP(K82,'Product Category'!A:B,2,FALSE) -> Electronics | AL82: =VLOOKUP(Z82,Coupons!A:B,2,FALSE) -> 0 | AM82: =AE82*AL82 -> 0 | AN82: =N82*0.7 -> 412.692 | AO82: =AN82*L82 -> 1238.076 | AP82: =AF82-AM82 -> 1768.68 | AQ82: =AP82-AO82 -> 530.604 | AR82: =AP82/AO82 -> 1.4285714
A83: ORD200081 | B83: =(RIGHT(A83, LEN(A83)-3))*1 -> 200081 | C83: 45085 | D83: 45085 | E83: =(TEXT(D83, "yyyy"))*1 -> 2023 | F83: =TEXT(D83, "mmmm") -> June | G83: =TEXT(D83, "dddd") -> Thursday | H83: C29314 | I83: =(RIGHT(H83, LEN(H83)-1))*1 -> 29314 | J83: Monitor | K83: =TRIM(PROPER(J83)) -> Monitor | L83: 2 | M83: 394.3 | N83: =(TRIM(PROPER(M83)))*1 -> 394.3 | O83: 496 Main St | P83: =LEFT(O83, FIND(" ", O83)-1) -> 496 | Q83: =RIGHT(O83, LEN(O83) - FIND(" ", O83)) -> Main St | R83: Cash | S83: =TRIM(PROPER(R83)) -> Cash | T83: Shipped | U83: =TRIM(PROPER(T83)) -> Shipped | V83: TRK59876213 | W83: =RIGHT(V83, LEN(V83)-3) -> 59876213 | X83: 6 | Y83: FREESHIP | Z83: =TRIM(UPPER(IF(Y83="", "NO COUPON", Y83))) -> FREESHIP | AA83: =IF(Z83="NO COUPON","NO","YES") -> YES | AB83: Email | AC83: =TRIM(PROPER(AB83)) -> Email | AD83: 788.6 | AE83: 788.6 | AF83: =N83*L83 -> 788.6 | AG83: =_xlfn.XLOOKUP(H83, 'Customer Data'!A83,'Customer Data'!B83) -> Customer_83 | AH83: =_xlfn.XLOOKUP(H83,'Customer Data'!A83,'Customer Data'!C83) -> Female | AI83: =_xlfn.XLOOKUP(H83,'Customer Data'!A83,'Customer Data'!D83) -> 40 | AJ83: =_xlfn.XLOOKUP(H83,'Customer Data'!A83,'Customer Data'!E83) -> Kano | AK83: =VLOOKUP(K83,'Product Category'!A:B,2,FALSE) -> Electronics | AL83: =VLOOKUP(Z83,Coupons!A:B,2,FALSE) -> 0 | AM83: =AE83*AL83 -> 0 | AN83: =N83*0.7 -> 276.01 | AO83: =AN83*L83 -> 552.02 | AP83: =AF83-AM83 -> 788.6 | AQ83: =AP83-AO83 -> 236.58 | AR83: =AP83/AO83 -> 1.4285714
A84: ORD200082 | B84: =(RIGHT(A84, LEN(A84)-3))*1 -> 200082 | C84: 45296 | D84: 45296 | E84: =(TEXT(D84, "yyyy"))*1 -> 2024 | F84: =TEXT(D84, "mmmm") -> January | G84: =TEXT(D84, "dddd") -> Friday | H84: C65799 | I84: =(RIGHT(H84, LEN(H84)-1))*1 -> 65799 | J84: Tablet | K84: =TRIM(PROPER(J84)) -> Tablet | L84: 4 | M84: 565.2 | N84: =(TRIM(PROPER(M84)))*1 -> 565.2 | O84: 971 Main St | P84: =LEFT(O84, FIND(" ", O84)-1) -> 971 | Q84: =RIGHT(O84, LEN(O84) - FIND(" ", O84)) -> Main St | R84: Debit Card | S84: =TRIM(PROPER(R84)) -> Debit Card | T84: Shipped | U84: =TRIM(PROPER(T84)) -> Shipped | V84: TRK66906607 | W84: =RIGHT(V84, LEN(V84)-3) -> 66906607 | X84: 9 | Y84: SAVE10 | Z84: =TRIM(UPPER(IF(Y84="", "NO COUPON", Y84))) -> SAVE10 | AA84: =IF(Z84="NO COUPON","NO","YES") -> YES | AB84: Google | AC84: =TRIM(PROPER(AB84)) -> Google | AD84: 2260.8 | AE84: 2260.8 | AF84: =N84*L84 -> 2260.8 | AG84: =_xlfn.XLOOKUP(H84, 'Customer Data'!A84,'Customer Data'!B84) -> Customer_84 | AH84: =_xlfn.XLOOKUP(H84,'Customer Data'!A84,'Customer Data'!C84) -> Male | AI84: =_xlfn.XLOOKUP(H84,'Customer Data'!A84,'Customer Data'!D84) -> 53 | AJ84: =_xlfn.XLOOKUP(H84,'Customer Data'!A84,'Customer Data'!E84) -> Abuja | AK84: =VLOOKUP(K84,'Product Category'!A:B,2,FALSE) -> Electronics | AL84: =VLOOKUP(Z84,Coupons!A:B,2,FALSE) -> 0.1 | AM84: =AE84*AL84 -> 226.08 | AN84: =N84*0.7 -> 395.64 | AO84: =AN84*L84 -> 1582.56 | AP84: =AF84-AM84 -> 2034.72 | AQ84: =AP84-AO84 -> 452.16 | AR84: =AP84/AO84 -> 1.2857143
A85: ORD200083 | B85: =(RIGHT(A85, LEN(A85)-3))*1 -> 200083 | C85: 45160 | D85: 45160 | E85: =(TEXT(D85, "yyyy"))*1 -> 2023 | F85: =TEXT(D85, "mmmm") -> August | G85: =TEXT(D85, "dddd") -> Tuesday | H85: C15681 | I85: =(RIGHT(H85, LEN(H85)-1))*1 -> 15681 | J85: Laptop | K85: =TRIM(PROPER(J85)) -> Laptop | L85: 4 | M85: 540.41 | N85: =(TRIM(PROPER(M85)))*1 -> 540.41 | O85: 989 Main St | P85: =LEFT(O85, FIND(" ", O85)-1) -> 989 | Q85: =RIGHT(O85, LEN(O85) - FIND(" ", O85)) -> Main St | R85: Credit Card | S85: =TRIM(PROPER(R85)) -> Credit Card | T85: Cancelled | U85: =TRIM(PROPER(T85)) -> Cancelled | V85: TRK75112172 | W85: =RIGHT(V85, LEN(V85)-3) -> 75112172 | X85: 6 | Z85: =TRIM(UPPER(IF(Y85="", "NO COUPON", Y85))) -> NO COUPON | AA85: =IF(Z85="NO COUPON","NO","YES") -> NO | AB85: Referral | AC85: =TRIM(PROPER(AB85)) -> Referral | AD85: 2161.64 | AE85: 2161.64 | AF85: =N85*L85 -> 2161.64 | AG85: =_xlfn.XLOOKUP(H85, 'Customer Data'!A85,'Customer Data'!B85) -> Customer_85 | AH85: =_xlfn.XLOOKUP(H85,'Customer Data'!A85,'Customer Data'!C85) -> Female | AI85: =_xlfn.XLOOKUP(H85,'Customer Data'!A85,'Customer Data'!D85) -> 60 | AJ85: =_xlfn.XLOOKUP(H85,'Customer Data'!A85,'Customer Data'!E85) -> Port-Harcourt | AK85: =VLOOKUP(K85,'Product Category'!A:B,2,FALSE) -> Electronics | AL85: =VLOOKUP(Z85,Coupons!A:B,2,FALSE) -> 0 | AM85: =AE85*AL85 -> 0 | AN85: =N85*0.7 -> 378.287 | AO85: =AN85*L85 -> 1513.148 | AP85: =AF85-AM85 -> 2161.64 | AQ85: =AP85-AO85 -> 648.492 | AR85: =AP85/AO85 -> 1.4285714
A86: ORD200084 | B86: =(RIGHT(A86, LEN(A86)-3))*1 -> 200084 | C86: 45166 | D86: 45166 | E86: =(TEXT(D86, "yyyy"))*1 -> 2023 | F86: =TEXT(D86, "mmmm") -> August | G86: =TEXT(D86, "dddd") -> Monday | H86: C64160 | I86: =(RIGHT(H86, LEN(H86)-1))*1 -> 64160 | J86: Monitor | K86: =TRIM(PROPER(J86)) -> Monitor | L86: 2 | M86: 165.49 | N86: =(TRIM(PROPER(M86)))*1 -> 165.49 | O86: 967 Main St | P86: =LEFT(O86, FIND(" ", O86)-1) -> 967 | Q86: =RIGHT(O86, LEN(O86) - FIND(" ", O86)) -> Main St | R86: Online | S86: =TRIM(PROPER(R86)) -> Online | T86: Shipped | U86: =TRIM(PROPER(T86)) -> Shipped | V86: TRK34121529 | W86: =RIGHT(V86, LEN(V86)-3) -> 34121529 | X86: 4 | Y86: WINTER15 | Z86: =TRIM(UPPER(IF(Y86="", "NO COUPON", Y86))) -> WINTER15 | AA86: =IF(Z86="NO COUPON","NO","YES") -> YES | AB86: Instagram | AC86: =TRIM(PROPER(AB86)) -> Instagram | AD86: 330.98 | AE86: 330.98 | AF86: =N86*L86 -> 330.98 | AG86: =_xlfn.XLOOKUP(H86, 'Customer Data'!A86,'Customer Data'!B86) -> Customer_86 | AH86: =_xlfn.XLOOKUP(H86,'Customer Data'!A86,'Customer Data'!C86) -> Male | AI86: =_xlfn.XLOOKUP(H86,'Customer Data'!A86,'Customer Data'!D86) -> 42 | AJ86: =_xlfn.XLOOKUP(H86,'Customer Data'!A86,'Customer Data'!E86) -> Enugu | AK86: =VLOOKUP(K86,'Product Category'!A:B,2,FALSE) -> Electronics | AL86: =VLOOKUP(Z86,Coupons!A:B,2,FALSE) -> 0.15 | AM86: =AE86*AL86 -> 49.647 | AN86: =N86*0.7 -> 115.843 | AO86: =AN86*L86 -> 231.686 | AP86: =AF86-AM86 -> 281.333 | AQ86: =AP86-AO86 -> 49.647 | AR86: =AP86/AO86 -> 1.2142857
A87: ORD200085 | B87: =(RIGHT(A87, LEN(A87)-3))*1 -> 200085 | C87: 45544 | D87: 45544 | E87: =(TEXT(D87, "yyyy"))*1 -> 2024 | F87: =TEXT(D87, "mmmm") -> September | G87: =TEXT(D87, "dddd") -> Monday | H87: C14553 | I87: =(RIGHT(H87, LEN(H87)-1))*1 -> 14553 | J87: Tablet | K87: =TRIM(PROPER(J87)) -> Tablet | L87: 3 | M87: 146.73 | N87: =(TRIM(PROPER(M87)))*1 -> 146.73 | O87: 768 Main St | P87: =LEFT(O87, FIND(" ", O87)-1) -> 768 | Q87: =RIGHT(O87, LEN(O87) - FIND(" ", O87)) -> Main St | R87: Cash | S87: =TRIM(PROPER(R87)) -> Cash | T87: Delivered | U87: =TRIM(PROPER(T87)) -> Delivered | V87: TRK93538334 | W87: =RIGHT(V87, LEN(V87)-3) -> 93538334 | X87: 8 | Y87: FREESHIP | Z87: =TRIM(UPPER(IF(Y87="", "NO COUPON", Y87))) -> FREESHIP | AA87: =IF(Z87="NO COUPON","NO","YES") -> YES | AB87: Email | AC87: =TRIM(PROPER(AB87)) -> Email | AD87: 440.19 | AE87: 440.19 | AF87: =N87*L87 -> 440.19 | AG87: =_xlfn.XLOOKUP(H87, 'Customer Data'!A87,'Customer Data'!B87) -> Customer_87 | AH87: =_xlfn.XLOOKUP(H87,'Customer Data'!A87,'Customer Data'!C87) -> Male | AI87: =_xlfn.XLOOKUP(H87,'Customer Data'!A87,'Customer Data'!D87) -> 39 | AJ87: =_xlfn.XLOOKUP(H87,'Customer Data'!A87,'Customer Data'!E87) -> Port-Harcourt | AK87: =VLOOKUP(K87,'Product Category'!A:B,2,FALSE) -> Electronics | AL87: =VLOOKUP(Z87,Coupons!A:B,2,FALSE) -> 0 | AM87: =AE87*AL87 -> 0 | AN87: =N87*0.7 -> 102.711 | AO87: =AN87*L87 -> 308.133 | AP87: =AF87-AM87 -> 440.19 | AQ87: =AP87-AO87 -> 132.057 | AR87: =AP87/AO87 -> 1.4285714
A88: ORD200086 | B88: =(RIGHT(A88, LEN(A88)-3))*1 -> 200086 | C88: 45462 | D88: 45462 | E88: =(TEXT(D88, "yyyy"))*1 -> 2024 | F88: =TEXT(D88, "mmmm") -> June | G88: =TEXT(D88, "dddd") -> Wednesday | H88: C88205 | I88: =(RIGHT(H88, LEN(H88)-1))*1 -> 88205 | J88: Printer | K88: =TRIM(PROPER(J88)) -> Printer | L88: 5 | M88: 643.03 | N88: =(TRIM(PROPER(M88)))*1 -> 643.03 | O88: 447 Main St | P88: =LEFT(O88, FIND(" ", O88)-1) -> 447 | Q88: =RIGHT(O88, LEN(O88) - FIND(" ", O88)) -> Main St | R88: Online | S88: =TRIM(PROPER(R88)) -> Online | T88: Cancelled | U88: =TRIM(PROPER(T88)) -> Cancelled | V88: TRK93504166 | W88: =RIGHT(V88, LEN(V88)-3) -> 93504166 | X88: 5 | Y88: FREESHIP | Z88: =TRIM(UPPER(IF(Y88="", "NO COUPON", Y88))) -> FREESHIP | AA88: =IF(Z88="NO COUPON","NO","YES") -> YES | AB88: Referral | AC88: =TRIM(PROPER(AB88)) -> Referral | AD88: 3215.15 | AE88: 3215.15 | AF88: =N88*L88 -> 3215.15 | AG88: =_xlfn.XLOOKUP(H88, 'Customer Data'!A88,'Customer Data'!B88) -> Customer_88 | AH88: =_xlfn.XLOOKUP(H88,'Customer Data'!A88,'Customer Data'!C88) -> Female | AI88: =_xlfn.XLOOKUP(H88,'Customer Data'!A88,'Customer Data'!D88) -> 36 | AJ88: =_xlfn.XLOOKUP(H88,'Customer Data'!A88,'Customer Data'!E88) -> Owerri | AK88: =VLOOKUP(K88,'Product Category'!A:B,2,FALSE) -> Electronics | AL88: =VLOOKUP(Z88,Coupons!A:B,2,FALSE) -> 0 | AM88: =AE88*AL88 -> 0 | AN88: =N88*0.7 -> 450.121 | AO88: =AN88*L88 -> 2250.605 | AP88: =AF88-AM88 -> 3215.15 | AQ88: =AP88-AO88 -> 964.545 | AR88: =AP88/AO88 -> 1.4285714
A89: ORD200087 | B89: =(RIGHT(A89, LEN(A89)-3))*1 -> 200087 | C89: 45575 | D89: 45575 | E89: =(TEXT(D89, "yyyy"))*1 -> 2024 | F89: =TEXT(D89, "mmmm") -> October | G89: =TEXT(D89, "dddd") -> Thursday | H89: C91245 | I89: =(RIGHT(H89, LEN(H89)-1))*1 -> 91245 | J89: Tablet | K89: =TRIM(PROPER(J89)) -> Tablet | L89: 3 | M89: 225.11 | N89: =(TRIM(PROPER(M89)))*1 -> 225.11 | O89: 915 Main St | P89: =LEFT(O89, FIND(" ", O89)-1) -> 915 | Q89: =RIGHT(O89, LEN(O89) - FIND(" ", O89)) -> Main St | R89: Cash | S89: =TRIM(PROPER(R89)) -> Cash | T89: Shipped | U89: =TRIM(PROPER(T89)) -> Shipped | V89: TRK46976391 | W89: =RIGHT(V89, LEN(V89)-3) -> 46976391 | X89: 4 | Y89: SAVE10 | Z89: =TRIM(UPPER(IF(Y89="", "NO COUPON", Y89))) -> SAVE10 | AA89: =IF(Z89="NO COUPON","NO","YES") -> YES | AB89: Facebook | AC89: =TRIM(PROPER(AB89)) -> Facebook | AD89: 675.33 | AE89: 675.33 | AF89: =N89*L89 -> 675.33 | AG89: =_xlfn.XLOOKUP(H89, 'Customer Data'!A89,'Customer Data'!B89) -> Customer_89 | AH89: =_xlfn.XLOOKUP(H89,'Customer Data'!A89,'Customer Data'!C89) -> Female | AI89: =_xlfn.XLOOKUP(H89,'Customer Data'!A89,'Customer Data'!D89) -> 35 | AJ89: =_xlfn.XLOOKUP(H89,'Customer Data'!A89,'Customer Data'!E89) -> Kano | AK89: =VLOOKUP(K89,'Product Category'!A:B,2,FALSE) -> Electronics | AL89: =VLOOKUP(Z89,Coupons!A:B,2,FALSE) -> 0.1 | AM89: =AE89*AL89 -> 67.533 | AN89: =N89*0.7 -> 157.577 | AO89: =AN89*L89 -> 472.731 | AP89: =AF89-AM89 -> 607.797 | AQ89: =AP89-AO89 -> 135.066 | AR89: =AP89/AO89 -> 1.2857143
A90: ORD200088 | B90: =(RIGHT(A90, LEN(A90)-3))*1 -> 200088 | C90: 45813 | D90: 45813 | E90: =(TEXT(D90, "yyyy"))*1 -> 2025 | F90: =TEXT(D90, "mmmm") -> June | G90: =TEXT(D90, "dddd") -> Thursday | H90: C75439 | I90: =(RIGHT(H90, LEN(H90)-1))*1 -> 75439 | J90: Desk | K90: =TRIM(PROPER(J90)) -> Desk | L90: 3 | M90: 114.81 | N90: =(TRIM(PROPER(M90)))*1 -> 114.81 | O90: 318 Main St | P90: =LEFT(O90, FIND(" ", O90)-1) -> 318 | Q90: =RIGHT(O90, LEN(O90) - FIND(" ", O90)) -> Main St | R90: Gift Card | S90: =TRIM(PROPER(R90)) -> Gift Card | T90: Cancelled | U90: =TRIM(PROPER(T90)) -> Cancelled | V90: TRK19831653 | W90: =RIGHT(V90, LEN(V90)-3) -> 19831653 | X90: 7 | Z90: =TRIM(UPPER(IF(Y90="", "NO COUPON", Y90))) -> NO COUPON | AA90: =IF(Z90="NO COUPON","NO","YES") -> NO | AB90: Google | AC90: =TRIM(PROPER(AB90)) -> Google | AD90: 344.43 | AE90: 344.43 | AF90: =N90*L90 -> 344.43 | AG90: =_xlfn.XLOOKUP(H90, 'Customer Data'!A90,'Customer Data'!B90) -> Customer_90 | AH90: =_xlfn.XLOOKUP(H90,'Customer Data'!A90,'Customer Data'!C90) -> Male | AI90: =_xlfn.XLOOKUP(H90,'Customer Data'!A90,'Customer Data'!D90) -> 38 | AJ90: =_xlfn.XLOOKUP(H90,'Customer Data'!A90,'Customer Data'!E90) -> Enugu | AK90: =VLOOKUP(K90,'Product Category'!A:B,2,FALSE) -> Furniture | AL90: =VLOOKUP(Z90,Coupons!A:B,2,FALSE) -> 0 | AM90: =AE90*AL90 -> 0 | AN90: =N90*0.7 -> 80.367 | AO90: =AN90*L90 -> 241.101 | AP90: =AF90-AM90 -> 344.43 | AQ90: =AP90-AO90 -> 103.329 | AR90: =AP90/AO90 -> 1.4285714
A91: ORD200089 | B91: =(RIGHT(A91, LEN(A91)-3))*1 -> 200089 | C91: 45713 | D91: 45713 | E91: =(TEXT(D91, "yyyy"))*1 -> 2025 | F91: =TEXT(D91, "mmmm") -> February | G91: =TEXT(D91, "dddd") -> Tuesday | H91: C17181 | I91: =(RIGHT(H91, LEN(H91)-1))*1 -> 17181 | J91: Printer | K91: =TRIM(PROPER(J91)) -> Printer | L91: 5 | M91: 455.33 | N91: =(TRIM(PROPER(M91)))*1 -> 455.33 | O91: 291 Main St | P91: =LEFT(O91, FIND(" ", O91)-1) -> 291 | Q91: =RIGHT(O91, LEN(O91) - FIND(" ", O91)) -> Main St | R91: Credit Card | S91: =TRIM(PROPER(R91)) -> Credit Card | T91: Cancelled | U91: =TRIM(PROPER(T91)) -> Cancelled | V91: TRK78912978 | W91: =RIGHT(V91, LEN(V91)-3) -> 78912978 | X91: 8 | Y91: FREESHIP | Z91: =TRIM(UPPER(IF(Y91="", "NO COUPON", Y91))) -> FREESHIP | AA91: =IF(Z91="NO COUPON","NO","YES") -> YES | AB91: Google | AC91: =TRIM(PROPER(AB91)) -> Google | AD91: 2276.65 | AE91: 2276.65 | AF91: =N91*L91 -> 2276.65 | AG91: =_xlfn.XLOOKUP(H91, 'Customer Data'!A91,'Customer Data'!B91) -> Customer_91 | AH91: =_xlfn.XLOOKUP(H91,'Customer Data'!A91,'Customer Data'!C91) -> Male | AI91: =_xlfn.XLOOKUP(H91,'Customer Data'!A91,'Customer Data'!D91) -> 28 | AJ91: =_xlfn.XLOOKUP(H91,'Customer Data'!A91,'Customer Data'!E91) -> Abuja | AK91: =VLOOKUP(K91,'Product Category'!A:B,2,FALSE) -> Electronics | AL91: =VLOOKUP(Z91,Coupons!A:B,2,FALSE) -> 0 | AM91: =AE91*AL91 -> 0 | AN91: =N91*0.7 -> 318.731 | AO91: =AN91*L91 -> 1593.655 | AP91: =AF91-AM91 -> 2276.65 | AQ91: =AP91-AO91 -> 682.995 | AR91: =AP91/AO91 -> 1.4285714
A92: ORD200090 | B92: =(RIGHT(A92, LEN(A92)-3))*1 -> 200090 | C92: 45187 | D92: 45187 | E92: =(TEXT(D92, "yyyy"))*1 -> 2023 | F92: =TEXT(D92, "mmmm") -> September | G92: =TEXT(D92, "dddd") -> Monday | H92: C36540 | I92: =(RIGHT(H92, LEN(H92)-1))*1 -> 36540 | J92: Chair | K92: =TRIM(PROPER(J92)) -> Chair | L92: 4 | M92: 182.08 | N92: =(TRIM(PROPER(M92)))*1 -> 182.08 | O92: 611 Main St | P92: =LEFT(O92, FIND(" ", O92)-1) -> 611 | Q92: =RIGHT(O92, LEN(O92) - FIND(" ", O92)) -> Main St | R92: Gift Card | S92: =TRIM(PROPER(R92)) -> Gift Card | T92: Delivered | U92: =TRIM(PROPER(T92)) -> Delivered | V92: TRK35828122 | W92: =RIGHT(V92, LEN(V92)-3) -> 35828122 | X92: 4 | Y92: SAVE10 | Z92: =TRIM(UPPER(IF(Y92="", "NO COUPON", Y92))) -> SAVE10 | AA92: =IF(Z92="NO COUPON","NO","YES") -> YES | AB92: Email | AC92: =TRIM(PROPER(AB92)) -> Email | AD92: 728.32 | AE92: 728.32 | AF92: =N92*L92 -> 728.32 | AG92: =_xlfn.XLOOKUP(H92, 'Customer Data'!A92,'Customer Data'!B92) -> Customer_92 | AH92: =_xlfn.XLOOKUP(H92,'Customer Data'!A92,'Customer Data'!C92) -> Female | AI92: =_xlfn.XLOOKUP(H92,'Customer Data'!A92,'Customer Data'!D92) -> 39 | AJ92: =_xlfn.XLOOKUP(H92,'Customer Data'!A92,'Customer Data'!E92) -> Port-Harcourt | AK92: =VLOOKUP(K92,'Product Category'!A:B,2,FALSE) -> Furniture | AL92: =VLOOKUP(Z92,Coupons!A:B,2,FALSE) -> 0.1 | AM92: =AE92*AL92 -> 72.832 | AN92: =N92*0.7 -> 127.456 | AO92: =AN92*L92 -> 509.824 | AP92: =AF92-AM92 -> 655.488 | AQ92: =AP92-AO92 -> 145.664 | AR92: =AP92/AO92 -> 1.2857143
A93: ORD200091 | B93: =(RIGHT(A93, LEN(A93)-3))*1 -> 200091 | C93: 45000 | D93: 45000 | E93: =(TEXT(D93, "yyyy"))*1 -> 2023 | F93: =TEXT(D93, "mmmm") -> March | G93: =TEXT(D93, "dddd") -> Wednesday | H93: C98216 | I93: =(RIGHT(H93, LEN(H93)-1))*1 -> 98216 | J93: Laptop | K93: =TRIM(PROPER(J93)) -> Laptop | L93: 5 | M93: 492.75 | N93: =(TRIM(PROPER(M93)))*1 -> 492.75 | O93: 196 Main St | P93: =LEFT(O93, FIND(" ", O93)-1) -> 196 | Q93: =RIGHT(O93, LEN(O93) - FIND(" ", O93)) -> Main St | R93: Cash | S93: =TRIM(PROPER(R93)) -> Cash | T93: Shipped | U93: =TRIM(PROPER(T93)) -> Shipped | V93: TRK40986666 | W93: =RIGHT(V93, LEN(V93)-3) -> 40986666 | X93: 6 | Y93: WINTER15 | Z93: =TRIM(UPPER(IF(Y93="", "NO COUPON", Y93))) -> WINTER15 | AA93: =IF(Z93="NO COUPON","NO","YES") -> YES | AB93: Referral | AC93: =TRIM(PROPER(AB93)) -> Referral | AD93: 2463.75 | AE93: 2463.75 | AF93: =N93*L93 -> 2463.75 | AG93: =_xlfn.XLOOKUP(H93, 'Customer Data'!A93,'Customer Data'!B93) -> Customer_93 | AH93: =_xlfn.XLOOKUP(H93,'Customer Data'!A93,'Customer Data'!C93) -> Female | AI93: =_xlfn.XLOOKUP(H93,'Customer Data'!A93,'Customer Data'!D93) -> 18 | AJ93: =_xlfn.XLOOKUP(H93,'Customer Data'!A93,'Customer Data'!E93) -> Port-Harcourt | AK93: =VLOOKUP(K93,'Product Category'!A:B,2,FALSE) -> Electronics | AL93: =VLOOKUP(Z93,Coupons!A:B,2,FALSE) -> 0.15 | AM93: =AE93*AL93 -> 369.5625 | AN93: =N93*0.7 -> 344.925 | AO93: =AN93*L93 -> 1724.625 | AP93: =AF93-AM93 -> 2094.1875 | AQ93: =AP93-AO93 -> 369.5625 | AR93: =AP93/AO93 -> 1.2142857
A94: ORD200092 | B94: =(RIGHT(A94, LEN(A94)-3))*1 -> 200092 | C94: 45453 | D94: 45453 | E94: =(TEXT(D94, "yyyy"))*1 -> 2024 | F94: =TEXT(D94, "mmmm") -> June | G94: =TEXT(D94, "dddd") -> Monday | H94: C29568 | I94: =(RIGHT(H94, LEN(H94)-1))*1 -> 29568 | J94: Printer | K94: =TRIM(PROPER(J94)) -> Printer | L94: 4 | M94: 48.61 | N94: =(TRIM(PROPER(M94)))*1 -> 48.61 | O94: 203 Main St | P94: =LEFT(O94, FIND(" ", O94)-1) -> 203 | Q94: =RIGHT(O94, LEN(O94) - FIND(" ", O94)) -> Main St | R94: Online | S94: =TRIM(PROPER(R94)) -> Online | T94: Shipped | U94: =TRIM(PROPER(T94)) -> Shipped | V94: TRK46531075 | W94: =RIGHT(V94, LEN(V94)-3) -> 46531075 | X94: 7 | Y94: FREESHIP | Z94: =TRIM(UPPER(IF(Y94="", "NO COUPON", Y94))) -> FREESHIP | AA94: =IF(Z94="NO COUPON","NO","YES") -> YES | AB94: Facebook | AC94: =TRIM(PROPER(AB94)) -> Facebook | AD94: 194.44 | AE94: 194.44 | AF94: =N94*L94 -> 194.44 | AG94: =_xlfn.XLOOKUP(H94, 'Customer Data'!A94,'Customer Data'!B94) -> Customer_94 | AH94: =_xlfn.XLOOKUP(H94,'Customer Data'!A94,'Customer Data'!C94) -> Male | AI94: =_xlfn.XLOOKUP(H94,'Customer Data'!A94,'Customer Data'!D94) -> 46 | AJ94: =_xlfn.XLOOKUP(H94,'Customer Data'!A94,'Customer Data'!E94) -> Owerri | AK94: =VLOOKUP(K94,'Product Category'!A:B,2,FALSE) -> Electronics | AL94: =VLOOKUP(Z94,Coupons!A:B,2,FALSE) -> 0 | AM94: =AE94*AL94 -> 0 | AN94: =N94*0.7 -> 34.027 | AO94: =AN94*L94 -> 136.108 | AP94: =AF94-AM94 -> 194.44 | AQ94: =AP94-AO94 -> 58.332 | AR94: =AP94/AO94 -> 1.4285714
A95: ORD200093 | B95: =(RIGHT(A95, LEN(A95)-3))*1 -> 200093 | C95: 44940 | D95: 44940 | E95: =(TEXT(D95, "yyyy"))*1 -> 2023 | F95: =TEXT(D95, "mmmm") -> January | G95: =TEXT(D95, "dddd") -> Saturday | H95: C97262 | I95: =(RIGHT(H95, LEN(H95)-1))*1 -> 97262 | J95: Desk | K95: =TRIM(PROPER(J95)) -> Desk | L95: 4 | M95: 431.01 | N95: =(TRIM(PROPER(M95)))*1 -> 431.01 | O95: 837 Main St | P95: =LEFT(O95, FIND(" ", O95)-1) -> 837 | Q95: =RIGHT(O95, LEN(O95) - FIND(" ", O95)) -> Main St | R95: Credit Card | S95: =TRIM(PROPER(R95)) -> Credit Card | T95: Returned | U95: =TRIM(PROPER(T95)) -> Returned | V95: TRK65990229 | W95: =RIGHT(V95, LEN(V95)-3) -> 65990229 | X95: 7 | Z95: =TRIM(UPPER(IF(Y95="", "NO COUPON", Y95))) -> NO COUPON | AA95: =IF(Z95="NO COUPON","NO","YES") -> NO | AB95: Referral | AC95: =TRIM(PROPER(AB95)) -> Referral | AD95: 1724.04 | AE95: 1724.04 | AF95: =N95*L95 -> 1724.04 | AG95: =_xlfn.XLOOKUP(H95, 'Customer Data'!A95,'Customer Data'!B95) -> Customer_95 | AH95: =_xlfn.XLOOKUP(H95,'Customer Data'!A95,'Customer Data'!C95) -> Male | AI95: =_xlfn.XLOOKUP(H95,'Customer Data'!A95,'Customer Data'!D95) -> 60 | AJ95: =_xlfn.XLOOKUP(H95,'Customer Data'!A95,'Customer Data'!E95) -> Port-Harcourt | AK95: =VLOOKUP(K95,'Product Category'!A:B,2,FALSE) -> Furniture | AL95: =VLOOKUP(Z95,Coupons!A:B,2,FALSE) -> 0 | AM95: =AE95*AL95 -> 0 | AN95: =N95*0.7 -> 301.707 | AO95: =AN95*L95 -> 1206.828 | AP95: =AF95-AM95 -> 1724.04 | AQ95: =AP95-AO95 -> 517.212 | AR95: =AP95/AO95 -> 1.4285714
A96: ORD200094 | B96: =(RIGHT(A96, LEN(A96)-3))*1 -> 200094 | C96: 44968 | D96: 44968 | E96: =(TEXT(D96, "yyyy"))*1 -> 2023 | F96: =TEXT(D96, "mmmm") -> February | G96: =TEXT(D96, "dddd") -> Saturday | H96: C79821 | I96: =(RIGHT(H96, LEN(H96)-1))*1 -> 79821 | J96: Chair | K96: =TRIM(PROPER(J96)) -> Chair | L96: 1 | M96: 531.18 | N96: =(TRIM(PROPER(M96)))*1 -> 531.18 | O96: 781 Main St | P96: =LEFT(O96, FIND(" ", O96)-1) -> 781 | Q96: =RIGHT(O96, LEN(O96) - FIND(" ", O96)) -> Main St | R96: Gift Card | S96: =TRIM(PROPER(R96)) -> Gift Card | T96: Returned | U96: =TRIM(PROPER(T96)) -> Returned | V96: TRK12780193 | W96: =RIGHT(V96, LEN(V96)-3) -> 12780193 | X96: 6 | Y96: WINTER15 | Z96: =TRIM(UPPER(IF(Y96="", "NO COUPON", Y96))) -> WINTER15 | AA96: =IF(Z96="NO COUPON","NO","YES") -> YES | AB96: Instagram | AC96: =TRIM(PROPER(AB96)) -> Instagram | AD96: 531.18 | AE96: 531.18 | AF96: =N96*L96 -> 531.18 | AG96: =_xlfn.XLOOKUP(H96, 'Customer Data'!A96,'Customer Data'!B96) -> Customer_96 | AH96: =_xlfn.XLOOKUP(H96,'Customer Data'!A96,'Customer Data'!C96) -> Female | AI96: =_xlfn.XLOOKUP(H96,'Customer Data'!A96,'Customer Data'!D96) -> 44 | AJ96: =_xlfn.XLOOKUP(H96,'Customer Data'!A96,'Customer Data'!E96) -> Port-Harcourt | AK96: =VLOOKUP(K96,'Product Category'!A:B,2,FALSE) -> Furniture | AL96: =VLOOKUP(Z96,Coupons!A:B,2,FALSE) -> 0.15 | AM96: =AE96*AL96 -> 79.677 | AN96: =N96*0.7 -> 371.826 | AO96: =AN96*L96 -> 371.826 | AP96: =AF96-AM96 -> 451.503 | AQ96: =AP96-AO96 -> 79.677 | AR96: =AP96/AO96 -> 1.2142857
A97: ORD200095 | B97: =(RIGHT(A97, LEN(A97)-3))*1 -> 200095 | C97: 45009 | D97: 45009 | E97: =(TEXT(D97, "yyyy"))*1 -> 2023 | F97: =TEXT(D97, "mmmm") -> March | G97: =TEXT(D97, "dddd") -> Friday | H97: C76761 | I97: =(RIGHT(H97, LEN(H97)-1))*1 -> 76761 | J97: Printer | K97: =TRIM(PROPER(J97)) -> Printer | L97: 4 | M97: 117.51 | N97: =(TRIM(PROPER(M97)))*1 -> 117.51 | O97: 839 Main St | P97: =LEFT(O97, FIND(" ", O97)-1) -> 839 | Q97: =RIGHT(O97, LEN(O97) - FIND(" ", O97)) -> Main St | R97: Debit Card | S97: =TRIM(PROPER(R97)) -> Debit Card | T97: Returned | U97: =TRIM(PROPER(T97)) -> Returned | V97: TRK60179774 | W97: =RIGHT(V97, LEN(V97)-3) -> 60179774 | X97: 7 | Z97: =TRIM(UPPER(IF(Y97="", "NO COUPON", Y97))) -> NO COUPON | AA97: =IF(Z97="NO COUPON","NO","YES") -> NO | AB97: Referral | AC97: =TRIM(PROPER(AB97)) -> Referral | AD97: 470.04 | AE97: 470.04 | AF97: =N97*L97 -> 470.04 | AG97: =_xlfn.XLOOKUP(H97, 'Customer Data'!A97,'Customer Data'!B97) -> Customer_97 | AH97: =_xlfn.XLOOKUP(H97,'Customer Data'!A97,'Customer Data'!C97) -> Male | AI97: =_xlfn.XLOOKUP(H97,'Customer Data'!A97,'Customer Data'!D97) -> 24 | AJ97: =_xlfn.XLOOKUP(H97,'Customer Data'!A97,'Customer Data'!E97) -> Owerri | AK97: =VLOOKUP(K97,'Product Category'!A:B,2,FALSE) -> Electronics | AL97: =VLOOKUP(Z97,Coupons!A:B,2,FALSE) -> 0 | AM97: =AE97*AL97 -> 0 | AN97: =N97*0.7 -> 82.257 | AO97: =AN97*L97 -> 329.028 | AP97: =AF97-AM97 -> 470.04 | AQ97: =AP97-AO97 -> 141.012 | AR97: =AP97/AO97 -> 1.4285714
A98: ORD200096 | B98: =(RIGHT(A98, LEN(A98)-3))*1 -> 200096 | C98: 45444 | D98: 45444 | E98: =(TEXT(D98, "yyyy"))*1 -> 2024 | F98: =TEXT(D98, "mmmm") -> June | G98: =TEXT(D98, "dddd") -> Saturday | H98: C93007 | I98: =(RIGHT(H98, LEN(H98)-1))*1 -> 93007 | J98: Phone | K98: =TRIM(PROPER(J98)) -> Phone | L98: 2 | M98: 232.83 | N98: =(TRIM(PROPER(M98)))*1 -> 232.83 | O98: 103 Main St | P98: =LEFT(O98, FIND(" ", O98)-1) -> 103 | Q98: =RIGHT(O98, LEN(O98) - FIND(" ", O98)) -> Main St | R98: Gift Card | S98: =TRIM(PROPER(R98)) -> Gift Card | T98: Delivered | U98: =TRIM(PROPER(T98)) -> Delivered | V98: TRK85696091 | W98: =RIGHT(V98, LEN(V98)-3) -> 85696091 | X98: 7 | Z98: =TRIM(UPPER(IF(Y98="", "NO COUPON", Y98))) -> NO COUPON | AA98: =IF(Z98="NO COUPON","NO","YES") -> NO | AB98: Instagram | AC98: =TRIM(PROPER(AB98)) -> Instagram | AD98: 465.66 | AE98: 465.66 | AF98: =N98*L98 -> 465.66 | AG98: =_xlfn.XLOOKUP(H98, 'Customer Data'!A98,'Customer Data'!B98) -> Customer_98 | AH98: =_xlfn.XLOOKUP(H98,'Customer Data'!A98,'Customer Data'!C98) -> Female | AI98: =_xlfn.XLOOKUP(H98,'Customer Data'!A98,'Customer Data'!D98) -> 34 | AJ98: =_xlfn.XLOOKUP(H98,'Customer Data'!A98,'Customer Data'!E98) -> Port-Harcourt | AK98: =VLOOKUP(K98,'Product Category'!A:B,2,FALSE) -> Electronics | AL98: =VLOOKUP(Z98,Coupons!A:B,2,FALSE) -> 0 | AM98: =AE98*AL98 -> 0 | AN98: =N98*0.7 -> 162.981 | AO98: =AN98*L98 -> 325.962 | AP98: =AF98-AM98 -> 465.66 | AQ98: =AP98-AO98 -> 139.698 | AR98: =AP98/AO98 -> 1.4285714
A99: ORD200097 | B99: =(RIGHT(A99, LEN(A99)-3))*1 -> 200097 | C99: 45678 | D99: 45678 | E99: =(TEXT(D99, "yyyy"))*1 -> 2025 | F99: =TEXT(D99, "mmmm") -> January | G99: =TEXT(D99, "dddd") -> Tuesday | H99: C15624 | I99: =(RIGHT(H99, LEN(H99)-1))*1 -> 15624 | J99: Tablet | K99: =TRIM(PROPER(J99)) -> Tablet | L99: 5 | M99: 619.52 | N99: =(TRIM(PROPER(M99)))*1 -> 619.52 | O99: 922 Main St | P99: =LEFT(O99, FIND(" ", O99)-1) -> 922 | Q99: =RIGHT(O99, LEN(O99) - FIND(" ", O99)) -> Main St | R99: Debit Card | S99: =TRIM(PROPER(R99)) -> Debit Card | T99: Pending | U99: =TRIM(PROPER(T99)) -> Pending | V99: TRK40621141 | W99: =RIGHT(V99, LEN(V99)-3) -> 40621141 | X99: 9 | Z99: =TRIM(UPPER(IF(Y99="", "NO COUPON", Y99))) -> NO COUPON | AA99: =IF(Z99="NO COUPON","NO","YES") -> NO | AB99: Email | AC99: =TRIM(PROPER(AB99)) -> Email | AD99: 3097.6 | AE99: 3097.6 | AF99: =N99*L99 -> 3097.6 | AG99: =_xlfn.XLOOKUP(H99, 'Customer Data'!A99,'Customer Data'!B99) -> Customer_99 | AH99: =_xlfn.XLOOKUP(H99,'Customer Data'!A99,'Customer Data'!C99) -> Male | AI99: =_xlfn.XLOOKUP(H99,'Customer Data'!A99,'Customer Data'!D99) -> 32 | AJ99: =_xlfn.XLOOKUP(H99,'Customer Data'!A99,'Customer Data'!E99) -> Enugu | AK99: =VLOOKUP(K99,'Product Category'!A:B,2,FALSE) -> Electronics | AL99: =VLOOKUP(Z99,Coupons!A:B,2,FALSE) -> 0 | AM99: =AE99*AL99 -> 0 | AN99: =N99*0.7 -> 433.664 | AO99: =AN99*L99 -> 2168.32 | AP99: =AF99-AM99 -> 3097.6 | AQ99: =AP99-AO99 -> 929.28 | AR99: =AP99/AO99 -> 1.4285714
A100: ORD200098 | B100: =(RIGHT(A100, LEN(A100)-3))*1 -> 200098 | C100: 44940 | D100: 44940 | E100: =(TEXT(D100, "yyyy"))*1 -> 2023 | F100: =TEXT(D100, "mmmm") -> January | G100: =TEXT(D100, "dddd") -> Saturday | H100: C70921 | I100: =(RIGHT(H100, LEN(H100)-1))*1 -> 70921 | J100: Printer | K100: =TRIM(PROPER(J100)) -> Printer | L100: 2 | M100: 228.54 | N100: =(TRIM(PROPER(M100)))*1 -> 228.54 | O100: 533 Main St | P100: =LEFT(O100, FIND(" ", O100)-1) -> 533 | Q100: =RIGHT(O100, LEN(O100) - FIND(" ", O100)) -> Main St | R100: Debit Card | S100: =TRIM(PROPER(R100)) -> Debit Card | T100: Pending | U100: =TRIM(PROPER(T100)) -> Pending | V100: TRK54983109 | W100: =RIGHT(V100, LEN(V100)-3) -> 54983109 | X100: 3 | Z100: =TRIM(UPPER(IF(Y100="", "NO COUPON", Y100))) -> NO COUPON | AA100: =IF(Z100="NO COUPON","NO","YES") -> NO | AB100: Email | AC100: =TRIM(PROPER(AB100)) -> Email | AD100: 457.08 | AE100: 457.08 | AF100: =N100*L100 -> 457.08 | AG100: =_xlfn.XLOOKUP(H100, 'Customer Data'!A100,'Customer Data'!B100) -> Customer_100 | AH100: =_xlfn.XLOOKUP(H100,'Customer Data'!A100,'Customer Data'!C100) -> Male | AI100: =_xlfn.XLOOKUP(H100,'Customer Data'!A100,'Customer Data'!D100) -> 29 | AJ100: =_xlfn.XLOOKUP(H100,'Customer Data'!A100,'Customer Data'!E100) -> Port-Harcourt | AK100: =VLOOKUP(K100,'Product Category'!A:B,2,FALSE) -> Electronics | AL100: =VLOOKUP(Z100,Coupons!A:B,2,FALSE) -> 0 | AM100: =AE100*AL100 -> 0 | AN100: =N100*0.7 -> 159.978 | AO100: =AN100*L100 -> 319.956 | AP100: =AF100-AM100 -> 457.08 | AQ100: =AP100-AO100 -> 137.124 | AR100: =AP100/AO100 -> 1.4285714
...

Sheet Pivot Table
A2: MONTHLY SALES TREND
A3: Row Labels | B3: Sum of Net Revenue
A4: January | B4: 116661.65
A5: February | B5: 104438.21
A6: March | B6: 115867.35
A7: April | B7: 102254.78
A8: May | B8: 127428.65
A9: June | B9: 161879.12
A10: July | B10: 81392.632
A11: August | B11: 81704.641
A12: September | B12: 64828.181
A13: October | B13: 83275.658
A14: November | B14: 71920.896
A15: December | B15: 77253.655
A16: Grand Total | B16: 1188905.4
A19: REVENUE BY PRODUTS
A20: Row Labels | B20: Sum of Net Revenue
A21: Chair | B21: 185379.09
A22: Printer | B22: 183589.53
A23: Laptop | B23: 181126.26
A24: Tablet | B24: 173930.26
A25: Monitor | B25: 163429.12
A26: Desk | B26: 157845.44
A27: Phone | B27: 143605.73
A28: Grand Total | B28: 1188905.4
A31: REVENUE BY CATEGORY
A32: Row Labels | B32: Sum of Net Revenue
A33: Electronics | B33: 845680.9
A34: Furniture | B34: 343224.52
A35: Grand Total | B35: 1188905.4
A38: ORDERS BY STATUS
A39: Row Labels | B39: Count of Order_ID
A40: Cancelled | B40: 250
A41: Returned | B41: 247
A42: Pending | B42: 237
A43: Shipped | B43: 235
A44: Delivered | B44: 231
A45: Grand Total | B45: 1200
A48: REVENUE BY COUPON
A49: Row Labels | B49: Sum of Revenue
A50: FREESHIP | B50: 335036.99
A51: NO COUPON | B51: 322401.41
A52: SAVE10 | B52: 304840.02
A53: WINTER15 | B53: 302483.54
A54: Grand Total | B54: 1264762
A57: REVENUE BY REFERRAL
A58: Row Labels | B58: Sum of Revenue
A59: Instagram | B59: 275285.45
A60: Email | B60: 261808.55
A61: Google | B61: 250441.48
A62: Facebook | B62: 250410.9
A63: Referral | B63: 226815.58
A64: Grand Total | B64: 1264762
A67: REVENUE BY GENDER
A68: Row Labels | B68: Sum of Revenue
A69: Male | B69: 639503.95
A70: Female | B70: 625258.01
A71: Grand Total | B71: 1264762
A74: REVENUE BY CITY
A75: Row Labels | B75: Sum of Revenue
A76: Lagos | B76: 232098.7
A77: Kano | B77: 223790.33
A78: Port-Harcourt | B78: 217987.58
A79: Abuja | B79: 205081.6
A80: Owerri | B80: 200580.15
A81: Enugu | B81: 185223.6
A82: Grand Total | B82: 1264762
A85: PROFIT BY PRODUCT
A86: Row Labels | B86: Sum of Profit
A87: Chair | B87: 48445.011
A88: Printer | B88: 46660.707
A89: Laptop | B89: 46637.666
A90: Tablet | B90: 43331.998
A91: Desk | B91: 40623.486
A92: Monitor | B92: 40473.128
A93: Phone | B93: 37400.059
A94: Grand Total | B94: 303572.06
A97: PROFIT BY CATEGORY
A98: Row Labels | B98: Sum of Profit
A99: Electronics | B99: 214503.56
A100: Furniture | B100: 89068.497
A101: Grand Total | B101: 303572.05
A104: PROFIT BY MONTH
A105: Row Labels | B105: Sum of Profit
A106: January | B106: 29642.39
A107: February | B107: 25796.864
A108: March | B108: 29178.697
A109: April | B109: 25824.547
A110: May | B110: 32828.841
A111: June | B111: 42447.83
A112: July | B112: 21343.384
A113: August | B113: 21264.394
A114: September | B114: 16303.026
A115: October | B115: 20391.284
A116: November | B116: 19075.495
A117: December | B117: 19475.305
A118: Grand Total | B118: 303572.06
A121: PROFIT BY COUPON USAGE
A122: Row Labels | B122: Sum of Profit
A123: YES | B123: 206851.63
...

Sheet Dashboard

Sheet Analysis

Sheet Recommendation

Sheet Insight

Sheet Visualization Description
